Workbook
Name CompanyName: YourCFOGuy
Name CS: CS!$B$4:$AN$53
Name CS_Budget: CS_Budget!$B$4:$AN$53
Name CurrentMonth: List!$W$3
Name GandA: 'G&A'!$B$4:$AN$53
Name GandA_Budget: 'G&A_Budget'!$B$4:$AN$53
Name RandD: 'R&D'!$B$4:$AN$53
Name RandD_Budget: 'R&D_Budget'!$B$4:$AN$53
Name SandM: 'S&M'!$B$4:$AN$53
Name SandM_Budget: 'S&M_Budget'!$B$4:$AN$53
Name Slicer_Period: #N/A
Name StartDate: 44227

Sheet Instructions
D5: The Ultimate Dashboard
D11: Legal Disclaimer | L11: 3 Ways I can help you | U11: Instructions
A13: This document is provided as a reference and template, and the financial information included should not be considered a certified business valuation, or projection. The information provided by Your CFO Guy (“we,” “us” or “our”) on https://yourcfoguy.com (the “Site”) is for general informational purposes only. All information on the Site is provided in good faith, however we make no representation or warranty of any kind, express or implied, regarding the accuracy, adequacy, validity, reliability, availability or completeness of any information on the Site. UNDER NO CIRCUMSTANCE SHALL WE HAVE ANY LIABILITY TO YOU FOR ANY LOSS OR DAMAGE OF ANY KIND INCURRED AS A RESULT OF THE USE OF THE SITE OR RELIANCE ON ANY INFORMATION PROVIDED ON THE SITE. YOUR USE OF THE SITE AND YOUR RELIANCE ON ANY INFORMATION ON THE SITE IS SOLELY AT YOUR OWN RISK. The Site cannot and does not contain financial advice. The financial information is provided for general informational and educational purposes only and is not a substitute for professional advice. Accordingly, before taking any actions based upon such information, we encourage you to consult with the appropriate professionals. We do not provide any kind of financial advice. THE USE OR RELIANCE OF ANY INFORMATION CONTAINED ON THIS SITE IS SOLELY AT YOUR OWN RISK. | J13: #VALUE! | K13: Take control of your Finance & Accounting Function | S13: #VALUE! | T13: Watch the full YouTube video here
J16: Click Here | S16: #VALUE! | T16: s
J20: #VALUE! | K20: Get Access to 100+ Finance & Accounting Templates | S20: To get started, Click File > Save As > Download a Copy
J23: Click Here
J27: #VALUE! | K27: Work with me 1-on-1
J30: Book Now

Sheet Dashboard
C1: FINANCIAL DASHBOARD
B2: #VALUE! | O2: BY DEPARTMENT | W2: BY COST
B18: vs BUDGET | O18: BY DEPARTMENT | S18: Budget | T18: Actual | U18: ▲ | V18: % | W18: BY COST | AA18: Budget | AB18: Actual | AC18: ▲ | AD18: %
O19: Customer Support | S19: =Data!V10 -> 151803.75 | T19: =Data!W10 -> 82873.122 | U19: =Data!X10 -> 68930.629 | V19: =Data!Y10 -> 0.83176098 | W19: Advertising | AA19: =Data!AB10 -> 245241.11 | AB19: =Data!AC10 -> 130260.72 | AC19: =Data!AD10 -> 114980.39 | AD19: =IFERROR(AC19/ABS(AA19),0) -> 0.46884633
O21: General & Administrative | S21: =Data!V11 -> 248464.66 | T21: =Data!W11 -> 219330.2 | U21: =Data!X11 -> 29134.464 | V21: =Data!Y12 -> 0.19509478 | W21: Other G&A | AA21: =Data!AB11 -> 292884.35 | AB21: =Data!AC11 -> 212909.19 | AC21: =Data!AD11 -> 79975.166 | AD21: =IFERROR(AC21/ABS(AA21),0) -> 0.27306056
B22: REVENUE | E22: =Data!Q49 -> GROSS PROFIT | H22: =Data!R49 -> EBITDA
O23: Research & Development | S23: =Data!V12 -> 184162.14 | T23: =Data!W12 -> 154098.36 | U23: =Data!X12 -> 30063.785 | V23: =Data!Y14 -> 0.31934681 | W23: Payroll | AA23: =Data!AB12 -> 327740.25 | AB23: =Data!AC12 -> 264464.02 | AC23: =Data!AD12 -> 63276.23 | AD23: =IFERROR(AC23/ABS(AA23),0) -> 0.19306823
B24: =Data!P57 -> -5122.1619 | E24: =Data!Q57 -> -123182.38 | H24: =Data!R57 -> 104879.22
O25: Sales & Marketing | S25: =Data!V13 -> 357781.28 | T25: =Data!W13 -> 257848.56 | U25: =Data!X13 -> 99932.721 | V25: =Data!Y16 -> 0 | W25: Professional Fees | AA25: =Data!AB13 -> 76346.124 | AB25: =Data!AC13 -> 106516.31 | AC25: =Data!AD13 -> -30170.189 | AD25: =IFERROR(AC25/ABS(AA25),0) -> -0.39517644
O27: Total | S27: =SUM(S19:S26) -> 942211.83 | T27: =SUM(T19:T26) -> 714150.23 | U27: =SUM(U19:U26) -> 228061.6 | V27: =IFERROR(U27/ABS(S27),0) -> 0.24204918 | W27: Total | AA27: =SUM(AA19:AA26) -> 942211.83 | AB27: =SUM(AB19:AB26) -> 714150.23 | AC27: =SUM(AC19:AC26) -> 228061.6 | AD27: =IFERROR(AC27/ABS(AA27),0) -> 0.24204918
B29: vs PRIOR PERIOD | O29: BY DEPARTMENT | S29: Prior Period | T29: Actual | U29: ▲ | V29: % | W29: BY COST | AA29: Prior Period | AB29: Actual | AC29: ▲ | AD29: %
O30: Customer Support | S30: =Data!V20 -> 74262.567 | T30: =Data!W20 -> 82873.122 | U30: =Data!X20 -> 8610.5548 | V30: =Data!Y20 -> 0.11594744 | W30: Advertising | AA30: =Data!AB20 -> 146366.51 | AB30: =Data!AC20 -> 130260.72 | AC30: =Data!AD20 -> -16105.797 | AD30: =IFERROR(AC30/ABS(AA30),0) -> -0.11003744
O32: General & Administrative | S32: =Data!V21 -> 191874.76 | T32: =Data!W21 -> 219330.2 | U32: =Data!X21 -> 27455.436 | V32: =Data!Y22 -> 0.069685313 | W32: Other G&A | AA32: =Data!AB21 -> 184365.17 | AB32: =Data!AC21 -> 212909.19 | AC32: =Data!AD21 -> 28544.018 | AD32: =IFERROR(AC32/ABS(AA32),0) -> 0.15482327
O34: Research & Development | S34: =Data!V22 -> 144059.52 | T34: =Data!W22 -> 154098.36 | U34: =Data!X22 -> 10038.833 | V34: =Data!Y24 -> 0.044268743 | W34: Payroll | AA34: =Data!AB22 -> 255693.73 | AB34: =Data!AC22 -> 264464.02 | AC34: =Data!AD22 -> 8770.2849 | AD34: =IFERROR(AC34/ABS(AA34),0) -> 0.03429996
O36: Sales & Marketing | S36: =Data!V23 -> 273679.06 | T36: =Data!W23 -> 257848.56 | U36: =Data!X23 -> -15830.497 | V36: =Data!Y27 -> 0 | W36: Professional Fees | AA36: =Data!AB23 -> 97450.493 | AB36: =Data!AC23 -> 106516.31 | AC36: =Data!AD23 -> 9065.8206 | AD36: =IFERROR(AC36/ABS(AA36),0) -> 0.093030013
O38: Total | S38: =SUM(S30:S37) -> 683875.91 | T38: =SUM(T30:T37) -> 714150.23 | U38: =SUM(U30:U37) -> 30274.327 | V38: =IFERROR(U38/ABS(S38),0) -> 0.044268743 | W38: Total | AA38: =SUM(AA30:AA37) -> 683875.91 | AB38: =SUM(AB30:AB37) -> 714150.23 | AC38: =SUM(AC30:AC37) -> 30274.327 | AD38: =IFERROR(AC38/ABS(AA38),0) -> 0.044268743
B40: vs PRIOR YEAR | O40: BY DEPARTMENT | S40: Prior Year | T40: Actual | U40: ▲ | V40: % | W40: BY COST | AA40: Prior Year | AB40: Actual | AC40: ▲ | AD40: %
O41: Customer Support | S41: =Data!V30 -> 73148.433 | T41: =Data!W30 -> 82873.122 | U41: =Data!X30 -> 9724.689 | V41: =Data!Y30 -> 0.1329446 | W41: Advertising | AA41: =Data!AB30 -> 144548.59 | AB41: =Data!AC30 -> 130260.72 | AC41: =Data!AD30 -> -14287.872 | AD41: =IFERROR(AC41/ABS(AA41),0) -> -0.098844772
O43: General & Administrative | S43: =Data!V31 -> 179360.63 | T43: =Data!W31 -> 219330.2 | U43: =Data!X31 -> 39969.57 | V43: =Data!Y32 -> 0.14926387 | W43: Other G&A | AA43: =Data!AB31 -> 170315.51 | AB43: =Data!AC31 -> 212909.19 | AC43: =Data!AD31 -> 42593.677 | AD43: =IFERROR(AC43/ABS(AA43),0) -> 0.2500869
O45: Research & Development | S45: =Data!V32 -> 134084.4 | T45: =Data!W32 -> 154098.36 | U45: =Data!X32 -> 20013.956 | V45: =Data!Y34 -> 0.065764798 | W45: Payroll | AA45: =Data!AB32 -> 263571.97 | AB45: =Data!AC32 -> 264464.02 | AC45: =Data!AD32 -> 892.04467 | AD45: =IFERROR(AC45/ABS(AA45),0) -> 0.0033844444
O47: Sales & Marketing | S47: =Data!V33 -> 283488.94 | T47: =Data!W33 -> 257848.56 | U47: =Data!X33 -> -25640.381 | V47: =Data!Y37 -> 0 | W47: Professional Fees | AA47: =Data!AB33 -> 91646.33 | AB47: =Data!AC33 -> 106516.31 | AC47: =Data!AD33 -> 14869.984 | AD47: =IFERROR(AC47/ABS(AA47),0) -> 0.162254
O49: Total | S49: =SUM(S41:S48) -> 670082.4 | T49: =SUM(T41:T48) -> 714150.23 | U49: =SUM(U41:U48) -> 44067.834 | V49: =IFERROR(U49/ABS(S49),0) -> 0.065764798 | W49: Total | AA49: =SUM(AA41:AA48) -> 670082.4 | AB49: =SUM(AB41:AB48) -> 714150.23 | AC49: =SUM(AC41:AC48) -> 44067.834 | AD49: =IFERROR(AC49/ABS(AA49),0) -> 0.065764798

Sheet Data
F6: Section | G6: Expenses | AG6: Section | AH6: Expenses | AP6: Departments | AQ6: All
O7: Section | P7: (Multiple Items) | U7: Section | V7: Expenses | AA7: Section | AB7: Expenses
AP8: P&L | AQ8: Actual
B9: Revenue & Gross Margin | C9: Revenue | D9: Gross margin | G9: Customer Support | H9: General & Administrative | I9: Research & Development | J9: Sales & Marketing | L9: Section | M9: Expenses | O9: BvA: Rev, GP, EBITDA | P9: Budget | Q9: Actual | R9: Var to Budget Income ($) | S9: Var to Budget Income (%) | U9: BvA: Opex By Dept | V9: Budget | W9: Actual | X9: Var to Budget Expense ($) | Y9: Var to Budget Expense (%) | AA9: BvA: Opex By Cost Type | AB9: Budget | AC9: Actual | AD9: Var to Budget Expense ($) | AE9: Var to Budget Expense (%) | AH9: Customer Support | AI9: General & Administrative | AJ9: Research & Development | AK9: Sales & Marketing | AM9: Section | AN9: Expenses | AP9: Income | AQ9: 801118.03
B10: Jan-24 | C10: 112146.24 | D10: 0.87300372 | F10: Jan-24 | G10: 11405.29 | H10: 30761.505 | I10: 21048.484 | J10: 36671.753 | O10: Revenue | P10: 806240.19 | Q10: 801118.03 | R10: -5122.1619 | S10: -0.0063937669 | U10: Customer Support | V10: 151803.75 | W10: 82873.122 | X10: 68930.629 | Y10: 0.83176098 | AA10: Advertising | AB10: 245241.11 | AC10: 130260.72 | AD10: 114980.39 | AE10: 0.88269431 | AG10: Jan-24 | AH10: 11405.29 | AI10: 30761.505 | AJ10: 21048.484 | AK10: 36671.753 | AP10: Cost of Goods Sold | AQ10: 141454.25
B11: Feb-24 | C11: 115510.63 | D11: 0.81252824 | F11: Feb-24 | G11: 11747.449 | H11: 30146.275 | I11: 21358.44 | J11: 37609.95 | O11: Gross Profit | P11: 782846.16 | Q11: 659663.78 | R11: -123182.38 | S11: -0.18673509 | U11: General & Administrative | V11: 248464.66 | W11: 219330.2 | X11: 29134.464 | Y11: 0.1328338 | AA11: Other G&A | AB11: 292884.35 | AC11: 212909.19 | AD11: 79975.166 | AE11: 0.37563041 | AG11: Feb-24 | AH11: 11747.449 | AI11: 30146.275 | AJ11: 21358.44 | AK11: 37609.95 | AP11: Gross Profit | AQ11: 659663.78
B12: Mar-24 | C12: 112045.31 | D12: 0.85152687 | F12: Mar-24 | G12: 11777.678 | H12: 30578.689 | I12: 21709.845 | J12: 37645.05 | L12: Customer Support | M12: 82873.122 | O12: EBITDA | P12: -159365.67 | Q12: -54486.453 | R12: 104879.22 | S12: 1.9248679 | U12: Research & Development | V12: 184162.14 | W12: 154098.36 | X12: 30063.785 | Y12: 0.19509478 | AA12: Payroll | AB12: 327740.25 | AC12: 264464.02 | AD12: 63276.23 | AE12: 0.23926215 | AG12: Mar-24 | AH12: 11777.678 | AI12: 30578.689 | AJ12: 21709.845 | AK12: 37645.05 | AM12: Customer Support | AN12: 82873.122 | AP12: Expenses | AQ12: 714150.23
B13: Apr-24 | C13: 115406.67 | D13: 0.75095103 | F13: Apr-24 | G13: 11834.589 | H13: 31094.819 | I13: 22361.14 | J13: 38118.482 | L13: General & Administrative | M13: 219330.2 | O13: Grand Total | P13: 1429720.7 | Q13: 1406295.4 | R13: -23425.317 | S13: -0.016657466 | U13: Sales & Marketing | V13: 357781.28 | W13: 257848.56 | X13: 99932.721 | Y13: 0.38756362 | AA13: Professional Fees | AB13: 76346.124 | AC13: 106516.31 | AD13: -30170.189 | AE13: -0.28324478 | AG13: Apr-24 | AH13: 11834.589 | AI13: 31094.819 | AJ13: 22361.14 | AK13: 38118.482 | AM13: General & Administrative | AN13: 219330.2 | AP13: Advertising | AQ13: 130260.72
B14: May-24 | C14: 111944.47 | D14: 0.81973828 | F14: May-24 | G14: 12189.627 | H14: 32277.813 | I14: 22722.701 | J14: 36197.416 | L14: Research & Development | M14: 154098.36 | U14: Grand Total | V14: 942211.83 | W14: 714150.23 | X14: 228061.6 | Y14: 0.31934681 | AA14: Grand Total | AB14: 942211.83 | AC14: 714150.23 | AD14: 228061.6 | AE14: 0.31934681 | AG14: May-24 | AH14: 12189.627 | AI14: 32277.813 | AJ14: 22722.701 | AK14: 36197.416 | AM14: Research & Development | AN14: 154098.36 | AP14: Advertising & Marketing | AQ14: 80711.767
B15: Jun-24 | C15: 115302.81 | D15: 0.79904088 | F15: Jun-24 | G15: 12023.519 | H15: 31632.257 | I15: 23128.109 | J15: 35273.847 | L15: Sales & Marketing | M15: 257848.56 | AG15: Jun-24 | AH15: 12023.519 | AI15: 31632.257 | AJ15: 23128.109 | AK15: 35273.847 | AM15: Sales & Marketing | AN15: 257848.56 | AP15: Conferences & Events | AQ15: 49548.948
B16: Jul-24 | C16: 118761.89 | D16: 0.85829608 | F16: Jul-24 | G16: 11894.971 | H16: 32838.839 | I16: 21769.637 | J16: 36332.063 | L16: Grand Total | M16: 714150.23 | AG16: Jul-24 | AH16: 11894.971 | AI16: 32838.839 | AJ16: 21769.637 | AK16: 36332.063 | AM16: Grand Total | AN16: 714150.23 | AP16: Other G&A | AQ16: 212909.19
O17: Section | P17: (Multiple Items) | U17: Section | V17: Expenses | AA17: Section | AB17: Expenses | AP17: Payroll | AQ17: 264464.02
AP18: Professional Fees | AQ18: 106516.31
O19: AvPP: Rev, GP, EBITDA | P19: Prior Period | Q19: Actual | R19: Var to Prior Period ($) | S19: Var to Prior Period (%) | U19: AvPP: Opex By Dept | V19: Prior Period | W19: Actual | X19: Var to Prior Period ($) | Y19: Var to Prior Period (%) | AA19: AvPP: Opex By Cost Type | AB19: Prior Period | AC19: Actual | AD19: Var to Prior Period ($) | AE19: Var to Prior Period (%) | AP19: EBITDA | AQ19: -54486.453
O20: Revenue | P20: 747344.82 | Q20: 801118.03 | R20: 53773.213 | S20: 0.071952346 | U20: Customer Support | V20: 74262.567 | W20: 82873.122 | X20: 8610.5548 | Y20: 0.11594744 | AA20: Advertising | AB20: 146366.51 | AC20: 130260.72 | AD20: -16105.797 | AE20: -0.11003744 | AP20: Other Income | AQ20: 0
O21: Gross Profit | P21: 623631.09 | Q21: 659663.78 | R21: 36032.688 | S21: 0.05777885 | U21: General & Administrative | V21: 191874.76 | W21: 219330.2 | X21: 27455.436 | Y21: 0.1430904 | AA21: Other G&A | AB21: 184365.17 | AC21: 212909.19 | AD21: 28544.018 | AE21: 0.15482327 | AP21: Other Expenses | AQ21: 2067.6949
O22: EBITDA | P22: -60244.814 | Q22: -54486.453 | R22: 5758.3609 | S22: 0.095582683 | U22: Research & Development | V22: 144059.52 | W22: 154098.36 | X22: 10038.833 | Y22: 0.069685313 | AA22: Payroll | AB22: 255693.73 | AC22: 264464.02 | AD22: 8770.2849 | AE22: 0.03429996 | AP22: Interest Expense | AQ22: 74437.017
O23: Grand Total | P23: 1310731.1 | Q23: 1406295.4 | R23: 95564.261 | S23: 0.072909128 | U23: Sales & Marketing | V23: 273679.06 | W23: 257848.56 | X23: -15830.497 | Y23: -0.05784329 | AA23: Professional Fees | AB23: 97450.493 | AC23: 106516.31 | AD23: 9065.8206 | AE23: 0.093030013 | AP23: Net Other Income | AQ23: -76504.712
F24: Section | G24: Expenses | L24: Section | M24: Expenses | U24: Grand Total | V24: 683875.91 | W24: 714150.23 | X24: 30274.327 | Y24: 0.044268743 | AA24: Grand Total | AB24: 683875.91 | AC24: 714150.23 | AD24: 30274.327 | AE24: 0.044268743 | AG24: Section | AH24: Expenses | AM24: Section | AN24: Expenses | AP24: Net Income | AQ24: -130991.16
AP25: Grand Total | AQ25: 2130908.7
G27: Advertising | H27: Other G&A | I27: Payroll | J27: Professional Fees | L27: Advertising | M27: 130260.72 | O27: Section | P27: (Multiple Items) | U27: Section | V27: Expenses | AA27: Section | AB27: Expenses | AH27: Advertising | AI27: Other G&A | AJ27: Payroll | AK27: Professional Fees | AM27: Advertising | AN27: 130260.72
F28: Jan-24 | G28: 19431.892 | H28: 29529.336 | I28: 36264.882 | J28: 14660.922 | L28: Other G&A | M28: 212909.19 | AG28: Jan-24 | AH28: 19431.892 | AI28: 29529.336 | AJ28: 36264.882 | AK28: 14660.922 | AM28: Other G&A | AN28: 212909.19
F29: Feb-24 | G29: 19953.336 | H29: 29350.079 | I29: 37044.557 | J29: 14514.141 | L29: Payroll | M29: 264464.02 | O29: AvPY: Rev, GP, EBITDA | P29: Prior Year | Q29: Actual | R29: Var to Prior Year ($) | S29: Var to Prior Year (%) | U29: AvPY: Opex By Dept | V29: Prior Year | W29: Actual | X29: Var to Prior Year ($) | Y29: Var to Prior Year (%) | AA29: AvPY: Opex By Cost Type | AB29: Prior Year | AC29: Actual | AD29: Var to Prior Year ($) | AE29: Var to Prior Year (%) | AG29: Feb-24 | AH29: 19953.336 | AI29: 29350.079 | AJ29: 37044.557 | AK29: 14514.141 | AM29: Payroll | AN29: 264464.02
F30: Mar-24 | G30: 19835.193 | H30: 29407.745 | I30: 37529.781 | J30: 14938.542 | L30: Professional Fees | M30: 106516.31 | O30: Revenue | P30: 714351.19 | Q30: 801118.03 | R30: 86766.842 | S30: 0.12146244 | U30: Customer Support | V30: 73148.433 | W30: 82873.122 | X30: 9724.689 | Y30: 0.1329446 | AA30: Advertising | AB30: 144548.59 | AC30: 130260.72 | AD30: -14287.872 | AE30: -0.098844772 | AG30: Mar-24 | AH30: 19835.193 | AI30: 29407.745 | AJ30: 37529.781 | AK30: 14938.542 | AM30: Professional Fees | AN30: 106516.31
F31: Apr-24 | G31: 19786.868 | H31: 30154.32 | I31: 38092.387 | J31: 15375.455 | L31: Grand Total | M31: 714150.23 | O31: Gross Profit | P31: 558738.28 | Q31: 659663.78 | R31: 100925.5 | S31: 0.18063108 | U31: General & Administrative | V31: 179360.63 | W31: 219330.2 | X31: 39969.57 | Y31: 0.22284472 | AA31: Other G&A | AB31: 170315.51 | AC31: 212909.19 | AD31: 42593.677 | AE31: 0.2500869 | AG31: Apr-24 | AH31: 19786.868 | AI31: 30154.32 | AJ31: 38092.387 | AK31: 15375.455 | AM31: Grand Total | AN31: 714150.23
F32: May-24 | G32: 18029.407 | H32: 31227.748 | I32: 38614.425 | J32: 15515.977 | O32: EBITDA | P32: -111344.12 | Q32: -54486.453 | R32: 56857.664 | S32: 0.51064812 | U32: Research & Development | V32: 134084.4 | W32: 154098.36 | X32: 20013.956 | Y32: 0.14926387 | AA32: Payroll | AB32: 263571.97 | AC32: 264464.02 | AD32: 892.04467 | AE32: 0.0033844444 | AG32: May-24 | AH32: 18029.407 | AI32: 31227.748 | AJ32: 38614.425 | AK32: 15515.977
F33: Jun-24 | G33: 16401.45 | H33: 31067.125 | I33: 39060.712 | J33: 15528.444 | O33: Grand Total | P33: 1161745.4 | Q33: 1406295.4 | R33: 244550 | S33: 0.21050224 | U33: Sales & Marketing | V33: 283488.94 | W33: 257848.56 | X33: -25640.381 | Y33: -0.09044579 | AA33: Professional Fees | AB33: 91646.33 | AC33: 106516.31 | AD33: 14869.984 | AE33: 0.162254 | AG33: Jun-24 | AH33: 16401.45 | AI33: 31067.125 | AJ33: 39060.712 | AK33: 15528.444
F34: Jul-24 | G34: 16822.569 | H34: 32172.834 | I34: 37857.273 | J34: 15982.833 | U34: Grand Total | V34: 670082.4 | W34: 714150.23 | X34: 44067.834 | Y34: 0.065764798 | AA34: Grand Total | AB34: 670082.4 | AC34: 714150.23 | AD34: 44067.834 | AE34: 0.065764798 | AG34: Jul-24 | AH34: 16822.569 | AI34: 32172.834 | AJ34: 37857.273 | AK34: 15982.833
O35: Budget | P35: REVENUE | Q35: GROSS PROFIT | R35: EBITDA
O36: A (+) | P36: =MIN(IF(S10>0,S10,0),1) -> 0 | Q36: =MIN(IF(S11>0,S11,0),1) -> 0 | R36: =MIN(IF(S12>0,S12,0),1) -> 1
O37: B (+) | P37: =MAX(IF(S10>0,1-P36,0),0) -> 0 | Q37: =MAX(IF(S11>0,1-Q36,0),0) -> 0 | R37: =MAX(IF(S12>0,1-R36,0),0) -> 0
O38: A (-) | P38: =ABS(MIN(IF(S10<0,S10,0),1)) -> 0.0063937669 | Q38: =ABS(MIN(IF(S11<0,S11,0),1)) -> 0.18673509 | R38: =ABS(MIN(IF(S12<0,S12,0),1)) -> 0
O39: B (-) | P39: =IF(S10<0,MIN(1-P38,1),0) -> 0.99360623 | Q39: =IF(S11<0,MIN(1-Q38,1),0) -> 0.81326491 | R39: =IF(S12<0,MIN(1-R38,1),0) -> 0
O40: text | P40: =IF(P36>0,TEXT(P36,"0%")& " hit",IF(P38>0,TEXT(P38,"0%")&" miss","")) -> 1% miss | Q40: =IF(Q36>0,TEXT(Q36,"0%")& " hit",IF(Q38>0,TEXT(Q38,"0%")&" miss","")) -> 19% miss | R40: =IF(R36>0,TEXT(R36,"0%")& " hit",IF(R38>0,TEXT(R38,"0%")&" miss","")) -> 100% hit
O42: Prior Period | P42: REVENUE | Q42: GROSS PROFIT | R42: EBITDA
O43: A (+) | P43: =MIN(IF(S20>0,S20,0),1) -> 0.071952346 | Q43: =MIN(IF(S21>0,S21,0),1) -> 0.05777885 | R43: =MIN(IF(S22>0,S22,0),1) -> 0.095582683
O44: B (+) | P44: =MAX(IF(S20>0,1-P43,0),0) -> 0.92804765 | Q44: =MAX(IF(S21>0,1-Q43,0),0) -> 0.94222115 | R44: =MAX(IF(S22>0,1-R43,0),0) -> 0.90441732
O45: A (-) | P45: =ABS(MIN(IF(S20<0,S20,0),1)) -> 0 | Q45: =ABS(MIN(IF(S21<0,S21,0),1)) -> 0 | R45: =ABS(MIN(IF(S22<0,S22,0),1)) -> 0
O46: B (-) | P46: =IF(S20<0,MIN(1-P45,1),0) -> 0 | Q46: =IF(S21<0,MIN(1-Q45,1),0) -> 0 | R46: =IF(S22<0,MIN(1-R45,1),0) -> 0
O47: text | P47: =IF(P43>0,TEXT(P43,"0%")& " hit",IF(P45>0,TEXT(P45,"0%")&" miss","")) -> 7% hit | Q47: =IF(Q43>0,TEXT(Q43,"0%")& " hit",IF(Q45>0,TEXT(Q45,"0%")&" miss","")) -> 6% hit | R47: =IF(R43>0,TEXT(R43,"0%")& " hit",IF(R45>0,TEXT(R45,"0%")&" miss","")) -> 10% hit
O49: Prior Year | P49: REVENUE | Q49: GROSS PROFIT | R49: EBITDA
O50: A (+) | P50: =MIN(IF(S30>0,S30,0),1) -> 0.12146244 | Q50: =MIN(IF(S31>0,S31,0),1) -> 0.18063108 | R50: =MIN(IF(S32>0,S32,0),1) -> 0.51064812
O51: B (+) | P51: =MAX(IF(S30>0,1-P50,0),0) -> 0.87853756 | Q51: =MAX(IF(S31>0,1-Q50,0),0) -> 0.81936892 | R51: =MAX(IF(S32>0,1-R50,0),0) -> 0.48935188
O52: A (-) | P52: =ABS(MIN(IF(S30<0,S30,0),1)) -> 0 | Q52: =ABS(MIN(IF(S31<0,S31,0),1)) -> 0 | R52: =ABS(MIN(IF(S32<0,S32,0),1)) -> 0
O53: B (-) | P53: =IF(S30<0,MIN(1-P52,1),0) -> 0 | Q53: =IF(S31<0,MIN(1-Q52,1),0) -> 0 | R53: =IF(S32<0,MIN(1-R52,1),0) -> 0
O54: text | P54: =IF(P50>0,TEXT(P50,"0%")& " hit",IF(P52>0,TEXT(P52,"0%")&" miss","")) -> 12% hit | Q54: =IF(Q50>0,TEXT(Q50,"0%")& " hit",IF(Q52>0,TEXT(Q52,"0%")&" miss","")) -> 18% hit | R54: =IF(R50>0,TEXT(R50,"0%")& " hit",IF(R52>0,TEXT(R52,"0%")&" miss","")) -> 51% hit
O56: Metric | P56: REVENUE | Q56: GROSS PROFIT | R56: EBITDA
O57: Variance (Budget) | P57: =R10 -> -5122.1619 | Q57: =R11 -> -123182.38 | R57: =R12 -> 104879.22
O58: Variance (Prior Period) | P58: =R20 -> 53773.213 | Q58: =R21 -> 36032.688 | R58: =R22 -> 5758.3609
O59: Variance (Prior Year) | P59: =R30 -> 86766.842 | Q59: =R31 -> 100925.5 | R59: =R32 -> 56857.664
O61: Text | P61: REVENUE | Q61: GROSS PROFIT | R61: EBITDA
O62: Variance (Budget) | P62: =IF(P57>0,"Exceeded Budget","Missed Budget") -> Missed Budget | Q62: =IF(Q57>0,"Exceeded Budget","Missed Budget") -> Missed Budget | R62: =IF(R57>0,"Exceeded Budget","Missed Budget") -> Exceeded Budget
O63: Variance (Prior Period) | P63: =IF(P58>0,"Exceeded Budget","Missed Budget") -> Exceeded Budget | Q63: =IF(Q58>0,"Exceeded Budget","Missed Budget") -> Exceeded Budget | R63: =IF(R58>0,"Exceeded Budget","Missed Budget") -> Exceeded Budget
O64: Variance (Prior Year) | P64: =IF(P59>0,"Exceeded Budget","Missed Budget") -> Exceeded Budget | Q64: =IF(Q59>0,"Exceeded Budget","Missed Budget") -> Exceeded Budget | R64: =IF(R59>0,"Exceeded Budget","Missed Budget") -> Exceeded Budget

Sheet List
B2: Departments | D2: Summary Groupings | F2: Metrics | H2: Versions | J2: Files | L2: Period | N2: Account | O2: Section | P2: Summary Grouping | Q2: Sign | S2: Period | T2: Date | V2: Metric | W2: Amount | Y2: Section | Z2: Sign
B3: Customer Support | D3: Revenue | F3: Revenue | H3: Actual | J3: =2*4 -> 8 | L3: 2023 | N3: Revenue | O3: Income | P3: Revenue | Q3: 1 | S3: 2023 Start | T3: 44927 | V3: Current Month | W3: 45504 | Y3: Income | Z3: 1
B4: General & Administrative | D4: COGS | F4: COGS | H4: Budget | L4: 2024 | N4: Sales | O4: Income | P4: Revenue | Q4: 1 | S4: 2023 End | T4: 45291 | Y4: Cost of Goods Sold | Z4: -1
B5: Research & Development | D5: Gross Profit | F5: Gross Profit | L5: 2025 | N5: Cost of Goods Sold | O5: Cost of Goods Sold | P5: COGS | Q5: -1 | S5: 2024 Start | T5: =EDATE(T3,12) -> 45292 | Y5: Gross Profit | Z5: 1
B6: Sales & Marketing | D6: Payroll | F6: General & Administrative | L6: YTD | N6: Web Domain & Hosting Fees | O6: Cost of Goods Sold | P6: COGS | Q6: -1 | S6: 2024 End | T6: =EDATE(T4,12) -> 45657 | Y6: Expenses | Z6: -1
D7: Advertising | F7: Research & Development | L7: Current Month | N7: Merchant Account Fees | O7: Cost of Goods Sold | P7: COGS | Q7: -1 | S7: 2025 Start | T7: =EDATE(T5,12) -> 45658 | Y7: EBITDA | Z7: 1
D8: Professional Fees | F8: Sales & Marketing | L8: Trailing 3 Months | N8: Gross Profit | O8: Gross Profit | P8: Gross Profit | Q8: 1 | S8: 2025 End | T8: =EDATE(T6,12) -> 46022 | Y8: Other Income | Z8: 1
D9: Other G&A | F9: Customer Support | L9: Trailing 6 Months | N9: Expenses | O9: Expenses | P9: Other G&A | Q9: -1 | S9: Current Month Start | T9: =EOMONTH(CurrentMonth,-1)+1 -> 45474 | Y9: Other Expenses | Z9: -1
D10: EBITDA | F10: EBITDA | L10: Trailing 12 Months | N10: Advertising & Marketing | O10: Expenses | P10: Advertising | Q10: -1 | S10: Current Month End | T10: =CurrentMonth -> 45504 | Y10: Net Other Income | Z10: 1
D11: Net Other Income | F11: Net Other Income | N11: Bank Charges & Fees | O11: Expenses | P11: Other G&A | Q11: -1 | S11: Trailing 3 Mo Start | T11: =EOMONTH(CurrentMonth,-3)+1 -> 45413 | Y11: Net Income | Z11: 1
D12: Net Income | F12: Net Income | N12: Conferences & Events | O12: Expenses | P12: Advertising | Q12: -1 | S12: Trailing 3 mo End | T12: =EOMONTH(T11,2) -> 45504
D13: Number of Hires | N13: Software & Apps | O13: Expenses | P13: Other G&A | Q13: -1 | S13: Trailing 6 Mo Start | T13: =EOMONTH(T11,-4)+1 -> 45323
N14: Insurance | O14: Expenses | P14: Other G&A | Q14: -1 | S14: Trailing 6 Mo End | T14: =EOMONTH(T13,5) -> 45504
N15: Office Expenses | O15: Expenses | P15: Other G&A | Q15: -1 | S15: Trailing 12 Mo Start | T15: =EDATE(T9,-11) -> 45139
N16: Office Supplies | O16: Expenses | P16: Other G&A | Q16: -1 | S16: Trailing 12 Mo End | T16: =EOMONTH(T15,11) -> 45504
N17: Rent & Lease | O17: Expenses | P17: Other G&A | Q17: -1 | S17: YTD Start | T17: =DATE(YEAR(CurrentMonth),1,1) -> 45292
N18: Utilities | O18: Expenses | P18: Other G&A | Q18: -1 | S18: YTD End | T18: =CurrentMonth -> 45504
N19: Professional Services | O19: Expenses | P19: Professional Fees | Q19: -1 | S19: ="Prior Period "&S9 -> Prior Period Current Month Start | T19: =EDATE(T9,-1) -> 45444
N20: Accounting Fees | O20: Expenses | P20: Professional Fees | Q20: -1 | S20: ="Prior Period "&S10 -> Prior Period Current Month End | T20: =EDATE(CurrentMonth,-1) -> 45473
N21: Consulting Fees | O21: Expenses | P21: Professional Fees | Q21: -1 | S21: ="Prior Period "&S11 -> Prior Period Trailing 3 Mo Start | T21: =EDATE(T11,-3) -> 45323
N22: Legal Fees | O22: Expenses | P22: Professional Fees | Q22: -1 | S22: ="Prior Period "&S12 -> Prior Period Trailing 3 mo End | T22: =EDATE(T12,-3) -> 45412
N23: Recruiting Fees | O23: Expenses | P23: Professional Fees | Q23: -1 | S23: ="Prior Period "&S13 -> Prior Period Trailing 6 Mo Start | T23: =EDATE(T13,-6) -> 45139
N24: Payroll Expenses | O24: Expenses | P24: Payroll | Q24: -1 | S24: ="Prior Period "&S14 -> Prior Period Trailing 6 Mo End | T24: =EDATE(T14,-6) -> 45322
N25: Salary & Wages | O25: Expenses | P25: Payroll | Q25: -1 | S25: ="Prior Period "&S15 -> Prior Period Trailing 12 Mo Start | T25: =EDATE(T15,-12) -> 44774
N26: Payroll Taxes | O26: Expenses | P26: Payroll | Q26: -1 | S26: ="Prior Period "&S16 -> Prior Period Trailing 12 Mo End | T26: =EDATE(T16,-12) -> 45138
N27: Health Insurance | O27: Expenses | P27: Payroll | Q27: -1 | S27: ="Prior Period "&S17 -> Prior Period YTD Start | T27: =EOMONTH(T28,-(MONTH(T18)-MONTH(T17)+1))+1 -> 45078
N28: Payroll Processing Fees | O28: Expenses | P28: Payroll | Q28: -1 | S28: ="Prior Period "&S18 -> Prior Period YTD End | T28: =EOMONTH(T17,-1) -> 45291
N29: Commissions Expense | O29: Expenses | P29: Payroll | Q29: -1 | S29: ="Prior Year "&S9 -> Prior Year Current Month Start | T29: =EDATE(T9,-12) -> 45108
N30: Taxes & Licenses | O30: Expenses | P30: Other G&A | Q30: -1 | S30: ="Prior Year "&S10 -> Prior Year Current Month End | T30: =EDATE(CurrentMonth,-12) -> 45138
N31: Travel, Meals & Entertainment | O31: Expenses | P31: Other G&A | Q31: -1 | S31: ="Prior Year "&S11 -> Prior Year Trailing 3 Mo Start | T31: =EDATE(T11,-12) -> 45047
N32: Lodging | O32: Expenses | P32: Other G&A | Q32: -1 | S32: ="Prior Year "&S12 -> Prior Year Trailing 3 mo End | T32: =EDATE(T12,-12) -> 45138
N33: Meals & Entertainment | O33: Expenses | P33: Other G&A | Q33: -1 | S33: ="Prior Year "&S13 -> Prior Year Trailing 6 Mo Start | T33: =EDATE(T13,-12) -> 44958
N34: Travel | O34: Expenses | P34: Other G&A | Q34: -1 | S34: ="Prior Year "&S14 -> Prior Year Trailing 6 Mo End | T34: =EDATE(T14,-12) -> 45138
N35: Net Operating Income | O35: EBITDA | P35: EBITDA | Q35: 1 | S35: ="Prior Year "&S15 -> Prior Year Trailing 12 Mo Start | T35: =EDATE(T15,-12) -> 44774
N36: Other Income | O36: Other Income | P36: Other Income | Q36: 1 | S36: ="Prior Year "&S16 -> Prior Year Trailing 12 Mo End | T36: =EDATE(T16,-12) -> 45138
N37: Interest Income | O37: Other Income | P37: Other Income | Q37: 1 | S37: ="Prior Year "&S17 -> Prior Year YTD Start | T37: =EDATE(T17,-12) -> 44927
N38: Other Expenses | O38: Other Expenses | P38: Other Expenses | Q38: -1 | S38: ="Prior Year "&S18 -> Prior Year YTD End | T38: =EDATE(T18,-12) -> 45138
N39: Depreciation Expense | O39: Other Expenses | P39: Other Expenses | Q39: -1
N40: Interest Expense | O40: Other Expenses | P40: Other Expenses | Q40: -1
N41: Net Other Income | O41: =Mappings[[#This Row],[Account]] -> Net Other Income | P41: Net Other Income | Q41: 1
N42: Net Income | O42: =Mappings[[#This Row],[Account]] -> Net Income | P42: Net Income | Q42: 1

Sheet G&A
A1: Income Statement
A2: Your CFO Guy
A3: General & Admnistrative
C4: Growth | E4: 44957 | F4: =EOMONTH(E4,1) -> 44985 | G4: =EOMONTH(F4,1) -> 45016 | H4: =EOMONTH(G4,1) -> 45046 | I4: =EOMONTH(H4,1) -> 45077 | J4: =EOMONTH(I4,1) -> 45107 | K4: =EOMONTH(J4,1) -> 45138 | L4: =EOMONTH(K4,1) -> 45169 | M4: =EOMONTH(L4,1) -> 45199 | ... AN4: =EOMONTH(AM4,1) -> 46022
B5: Revenue
B6: Sales | C6: 0.03 | E6: 100000 | F6: =E6*(1+$C6) -> 103000 | G6: =F6*(0.97) -> 99910 | H6: =G6*(1+$C6) -> 102907.3 | I6: =H6*(0.97) -> 99820.081 | J6: =I6*(1+$C6) -> 102814.68 | K6: =J6*(1+$C6) -> 105899.12 | L6: =K6*(0.97) -> 102722.15 | M6: =L6*(1+$C6) -> 105803.81 | N6: =M6*(1+$C6) -> 108977.93 | O6: =N6*(1+$C6) -> 112247.27 | P6: =O6*(0.97) -> 108879.85 | Q6: =P6*(1+$C6) -> 112146.24 | R6: =Q6*(1+$C6) -> 115510.63 | S6: =R6*(0.97) -> 112045.31 | T6: =S6*(1+$C6) -> 115406.67 | U6: =T6*(0.97) -> 111944.47 | V6: =U6*(1+$C6) -> 115302.81 | W6: =V6*(1+$C6) -> 118761.89 | X6: =W6*(0.97) -> 115199.03 | Y6: =X6*(0.97) -> 111743.06 | Z6: =Y6*(1+$C6) -> 115095.35 | AA6: =Z6*(1+$C6) -> 118548.22 | AB6: =AA6*(1+$C6) -> 122104.66 | AC6: =AB6*(0.97) -> 118441.52 | AD6: =AC6*(1+$C6) -> 121994.77 | AE6: =AD6*(1+$C6) -> 125654.61 | AF6: =AE6*(1+$C6) -> 129424.25 | AG6: =AF6*(0.97) -> 125541.52 | AH6: =AG6*(1+$C6) -> 129307.77 | AI6: =AH6*(1+$C6) -> 133187 | AJ6: =AI6*(0.97) -> 129191.39 | AK6: =AJ6*(1+$C6) -> 133067.13 | AL6: =AK6*(1+$C6) -> 137059.15 | AM6: =AL6*(1+$C6) -> 141170.92 | AN6: =AM6*(0.97) -> 136935.79
B7: Total Revenue | E7: =SUM(E6 + E5) -> 100000 | F7: =SUM(F6 + F5) -> 103000 | G7: =SUM(G6 + G5) -> 99910 | H7: =SUM(H6 + H5) -> 102907.3 | I7: =SUM(I6 + I5) -> 99820.081 | J7: =SUM(J6 + J5) -> 102814.68 | K7: =SUM(K6 + K5) -> 105899.12 | L7: =SUM(L6 + L5) -> 102722.15 | ... AN7: =SUM(AN6 + AN5) -> 136935.79
B8: Cost of Goods Sold
B9: Web Domain & Hosting Fees | E9: 25000 | F9: 30900 | G9: 13987.4 | H9: 27784.971 | I9: 19964.016 | J9: 13365.909 | K9: 22238.816 | L9: 12326.658 | M9: 17986.649 | N9: 20705.807 | O9: 20204.508 | P9: 13065.582 | Q9: 13457.549 | R9: 20791.914 | S9: 15686.344 | T9: 27697.601 | U9: 19030.56 | V9: 21907.533 | W9: 15439.046 | X9: 25343.787 | Y9: 14526.598 | Z9: 11509.535 | AA9: 21338.679 | AB9: 18315.699 | AC9: 15397.398 | AD9: 25618.901 | AE9: 23874.376 | AF9: 38827.275 | AG9: 37662.456 | AH9: 28447.709 | AI9: 38624.23 | AJ9: 25838.278 | AK9: 25282.755 | AL9: 34264.786 | AM9: 22587.347 | AN9: 15062.937
B10: Merchant Account Fees | C10: 0.1 | E10: 250 | F10: =E10*(1+$C10) -> 275 | G10: =F10*(1+$C10) -> 302.5 | H10: =G10*(1+$C10) -> 332.75 | I10: =H10*(1+$C10) -> 366.025 | J10: =I10*(1+$C10) -> 402.6275 | K10: =J10*(1+$C10) -> 442.89025 | L10: =K10*(1+$C10) -> 487.17928 | M10: =L10*(1+$C10) -> 535.8972 | ... AN10: =AM10*(1+$C10) -> 7025.6092
B11: Total Cost of Goods Sold | E11: =SUM(E10, E9 + E8) -> 25250 | F11: =SUM(F10, F9 + F8) -> 31175 | G11: =SUM(G10, G9 + G8) -> 14289.9 | H11: =SUM(H10, H9 + H8) -> 28117.721 | I11: =SUM(I10, I9 + I8) -> 20330.041 | J11: =SUM(J10, J9 + J8) -> 13768.536 | K11: =SUM(K10, K9 + K8) -> 22681.706 | L11: =SUM(L10, L9 + L8) -> 12813.837 | ... AN11: =SUM(AN10, AN9 + AN8) -> 22088.546
B12: Gross Profit | E12: =E7-E11 -> 74750 | F12: =F7-F11 -> 71825 | G12: =G7-G11 -> 85620.1 | H12: =H7-H11 -> 74789.579 | I12: =I7-I11 -> 79490.04 | J12: =J7-J11 -> 89046.147 | K12: =K7-K11 -> 83217.418 | L12: =L7-L11 -> 89908.313 | ... AN12: =AN7-AN11 -> 114847.25
B13: Expenses
B14: Advertising & Marketing | C14: 0 | E14: 0 | F14: 0 | G14: 0 | H14: 0 | I14: 0 | J14: 0 | K14: 0 | L14: 0 | M14: 0 | N14: 0 | O14: 0 | P14: 0 | Q14: 0 | R14: 0 | S14: 0 | T14: 0 | U14: 0 | V14: 0 | W14: 0 | X14: 0 | Y14: 0 | Z14: 0 | AA14: 0 | AB14: 0 | AC14: 0 | AD14: 0 | AE14: 0 | AF14: 0 | AG14: 0 | AH14: 0 | AI14: 0 | AJ14: 0 | AK14: 0 | AL14: 0 | AM14: 0 | AN14: 0
B15: Bank Charges & Fees | C15: 0.03 | E15: 350 | F15: =E15*(1+$C15) -> 360.5 | G15: =F15*(0.98) -> 353.29 | H15: =G15*(1+$C15) -> 363.8887 | I15: =H15*(1+$C15) -> 374.80536 | J15: =I15*(0.98) -> 367.30925 | K15: =J15*(1+$C15) -> 378.32853 | L15: =K15*(1+$C15) -> 389.67839 | M15: =L15*(1+$C15) -> 401.36874 | N15: =M15*(0.98) -> 393.34136 | O15: =N15*(1+$C15) -> 405.14161 | P15: =O15*(1+$C15) -> 417.29585 | Q15: =P15*(1+$C15) -> 429.81473 | R15: =Q15*(0.98) -> 421.21843 | S15: =R15*(1+$C15) -> 433.85499 | T15: =S15*(1+$C15) -> 446.87064 | U15: =T15*(1+$C15) -> 460.27676 | V15: =U15*(0.98) -> 451.07122 | W15: =V15*(1+$C15) -> 464.60336 | X15: =W15*(1+$C15) -> 478.54146 | Y15: =X15*(0.98) -> 468.97063 | Z15: =Y15*(1+$C15) -> 483.03975 | AA15: =Z15*(1+$C15) -> 497.53094 | AB15: =AA15*(0.98) -> 487.58032 | AC15: =AB15*(1+$C15) -> 502.20773 | AD15: =AC15*(0.98) -> 492.16358 | AE15: =AD15*(1+$C15) -> 506.92848 | AF15: =AE15*(0.98) -> 496.78991 | AG15: =AF15*(1+$C15) -> 511.69361 | AH15: =AG15*(0.98) -> 501.45974 | AI15: =AH15*(1+$C15) -> 516.50353 | AJ15: =AI15*(1+$C15) -> 531.99864 | AK15: =AJ15*(1+$C15) -> 547.9586 | AL15: =AK15*(0.98) -> 536.99942 | AM15: =AL15*(1+$C15) -> 553.10941 | AN15: =AM15*(1+$C15) -> 569.70269
B16: Conferences & Events | C16: 0.04 | E16: 1000 | F16: =E16*(1+$C16) -> 1040 | G16: =F16*(0.9) -> 936 | H16: =G16*(1+$C16) -> 973.44 | I16: =H16*(1+$C16) -> 1012.3776 | J16: =I16*(0.98) -> 992.13005 | K16: =J16*(1+$C16) -> 1031.8152 | L16: =K16*(1+$C16) -> 1073.0879 | M16: =L16*(1+$C16) -> 1116.0114 | N16: =M16*(0.98) -> 1093.6911 | O16: =N16*(1+$C16) -> 1137.4388 | P16: =O16*(1+$C16) -> 1182.9363 | Q16: =P16*(1+$C16) -> 1230.2538 | R16: =Q16*(0.98) -> 1205.6487 | S16: =R16*(1+$C16) -> 1253.8747 | T16: =S16*(1+$C16) -> 1304.0297 | U16: =T16*(1+$C16) -> 1356.1908 | V16: =U16*(0.98) -> 1329.067 | W16: =V16*(1+$C16) -> 1382.2297 | X16: =W16*(1+$C16) -> 1437.5189 | Y16: =X16*(0.98) -> 1408.7685 | Z16: =Y16*(1+$C16) -> 1465.1193 | AA16: =Z16*(1+$C16) -> 1523.724 | AB16: =AA16*(0.98) -> 1493.2495 | AC16: =AB16*(1+$C16) -> 1552.9795 | AD16: =AC16*(0.98) -> 1521.9199 | AE16: =AD16*(1+$C16) -> 1582.7967 | AF16: =AE16*(0.98) -> 1551.1408 | AG16: =AF16*(1+$C16) -> 1613.1864 | AH16: =AG16*(0.98) -> 1580.9227 | AI16: =AH16*(1+$C16) -> 1644.1596 | AJ16: =AI16*(1+$C16) -> 1709.926 | AK16: =AJ16*(1+$C16) -> 1778.323 | AL16: =AK16*(0.98) -> 1742.7566 | AM16: =AL16*(1+$C16) -> 1812.4668 | AN16: =AM16*(1+$C16) -> 1884.9655
B17: Software & Apps | C17: 0.05 | E17: 4000 | F17: =E17*(1+$C17) -> 4200 | G17: =F17*(0.98) -> 4116 | H17: =G17*(1+$C17) -> 4321.8 | I17: =H17*(1+$C17) -> 4537.89 | J17: =I17*(0.98) -> 4447.1322 | K17: =J17*(1+$C17) -> 4669.4888 | L17: =K17*(1+$C17) -> 4902.9633 | M17: =L17*(1+$C17) -> 5148.1114 | N17: =M17*(0.98) -> 5045.1492 | O17: =N17*(1+$C17) -> 5297.4066 | P17: =O17*(1+$C17) -> 5562.277 | Q17: =P17*(1+$C17) -> 5840.3908 | R17: =Q17*(0.98) -> 5723.583 | S17: =R17*(1+$C17) -> 6009.7622 | T17: =S17*(1+$C17) -> 6310.2503 | U17: =T17*(1+$C17) -> 6625.7628 | V17: =U17*(0.98) -> 6493.2475 | W17: =V17*(1+$C17) -> 6817.9099 | X17: =W17*(1+$C17) -> 7158.8054 | Y17: =X17*(0.98) -> 7015.6293 | Z17: =Y17*(1+$C17) -> 7366.4108 | AA17: =Z17*(1+$C17) -> 7734.7313 | AB17: =AA17*(0.98) -> 7580.0367 | AC17: =AB17*(1+$C17) -> 7959.0385 | AD17: =AC17*(0.98) -> 7799.8577 | AE17: =AD17*(1+$C17) -> 8189.8506 | AF17: =AE17*(0.98) -> 8026.0536 | AG17: =AF17*(1+$C17) -> 8427.3563 | AH17: =AG17*(0.98) -> 8258.8092 | AI17: =AH17*(1+$C17) -> 8671.7496 | AJ17: =AI17*(1+$C17) -> 9105.3371 | AK17: =AJ17*(1+$C17) -> 9560.6039 | AL17: =AK17*(0.98) -> 9369.3919 | AM17: =AL17*(1+$C17) -> 9837.8615 | AN17: =AM17*(1+$C17) -> 10329.755
B18: Insurance | C18: 0.03 | E18: 250 | F18: =E18*(1+$C18) -> 257.5 | G18: =F18*(0.98) -> 252.35 | H18: =G18*(1+$C18) -> 259.9205 | I18: =H18*(1+$C18) -> 267.71812 | J18: =I18*(0.98) -> 262.36375 | K18: =J18*(1+$C18) -> 270.23467 | L18: =K18*(1+$C18) -> 278.34171 | M18: =L18*(1+$C18) -> 286.69196 | N18: =M18*(0.98) -> 280.95812 | O18: =N18*(1+$C18) -> 289.38686 | P18: =O18*(1+$C18) -> 298.06847 | Q18: =P18*(1+$C18) -> 307.01052 | R18: =Q18*(0.98) -> 300.87031 | S18: =R18*(1+$C18) -> 309.89642 | T18: =S18*(1+$C18) -> 319.19331 | U18: =T18*(1+$C18) -> 328.76911 | V18: =U18*(0.98) -> 322.19373 | W18: =V18*(1+$C18) -> 331.85954 | X18: =W18*(1+$C18) -> 341.81533 | Y18: =X18*(0.98) -> 334.97902 | Z18: =Y18*(1+$C18) -> 345.02839 | AA18: =Z18*(1+$C18) -> 355.37924 | AB18: =AA18*(0.98) -> 348.27166 | AC18: =AB18*(1+$C18) -> 358.71981 | AD18: =AC18*(0.98) -> 351.54541 | AE18: =AD18*(1+$C18) -> 362.09177 | AF18: =AE18*(0.98) -> 354.84994 | AG18: =AF18*(1+$C18) -> 365.49544 | AH18: =AG18*(0.98) -> 358.18553 | AI18: =AH18*(1+$C18) -> 368.93109 | AJ18: =AI18*(1+$C18) -> 379.99903 | AK18: =AJ18*(1+$C18) -> 391.399 | AL18: =AK18*(0.98) -> 383.57102 | AM18: =AL18*(1+$C18) -> 395.07815 | AN18: =AM18*(1+$C18) -> 406.93049
B19: Office Expenses | C19: 0.03 | E19: 0 | F19: =E19*(1+$C19) -> 0 | G19: =F19*(0.98) -> 0 | H19: =G19*(1+$C19) -> 0 | I19: =H19*(1+$C19) -> 0 | J19: =I19*(0.98) -> 0 | K19: =J19*(1+$C19) -> 0 | L19: =K19*(1+$C19) -> 0 | M19: =L19*(1+$C19) -> 0 | N19: =M19*(0.98) -> 0 | O19: =N19*(1+$C19) -> 0 | P19: =O19*(1+$C19) -> 0 | Q19: =P19*(1+$C19) -> 0 | R19: =Q19*(0.98) -> 0 | S19: =R19*(1+$C19) -> 0 | T19: =S19*(1+$C19) -> 0 | U19: =T19*(1+$C19) -> 0 | V19: =U19*(0.98) -> 0 | W19: =V19*(1+$C19) -> 0 | X19: =W19*(1+$C19) -> 0 | Y19: =X19*(0.98) -> 0 | Z19: =Y19*(1+$C19) -> 0 | AA19: =Z19*(1+$C19) -> 0 | AB19: =AA19*(0.98) -> 0 | AC19: =AB19*(1+$C19) -> 0 | AD19: =AC19*(0.98) -> 0 | AE19: =AD19*(1+$C19) -> 0 | AF19: =AE19*(0.98) -> 0 | AG19: =AF19*(1+$C19) -> 0 | AH19: =AG19*(0.98) -> 0 | AI19: =AH19*(1+$C19) -> 0 | AJ19: =AI19*(1+$C19) -> 0 | AK19: =AJ19*(1+$C19) -> 0 | AL19: =AK19*(0.98) -> 0 | AM19: =AL19*(1+$C19) -> 0 | AN19: =AM19*(1+$C19) -> 0
B20: Office Supplies | C20: 0.05 | E20: 800 | F20: =E20*(1+$C20) -> 840 | G20: =F20*(0.98) -> 823.2 | H20: =G20*(1+$C20) -> 864.36 | I20: =H20*(1+$C20) -> 907.578 | J20: =I20*(0.98) -> 889.42644 | K20: =J20*(1+$C20) -> 933.89776 | L20: =K20*(1+$C20) -> 980.59265 | M20: =L20*(1+$C20) -> 1029.6223 | N20: =M20*(0.98) -> 1009.0298 | O20: =N20*(1+$C20) -> 1059.4813 | P20: =O20*(1+$C20) -> 1112.4554 | Q20: =P20*(1+$C20) -> 1168.0782 | R20: =Q20*(0.98) -> 1144.7166 | S20: =R20*(1+$C20) -> 1201.9524 | T20: =S20*(1+$C20) -> 1262.0501 | U20: =T20*(1+$C20) -> 1325.1526 | V20: =U20*(0.98) -> 1298.6495 | W20: =V20*(1+$C20) -> 1363.582 | X20: =W20*(1+$C20) -> 1431.7611 | Y20: =X20*(0.98) -> 1403.1259 | Z20: =Y20*(1+$C20) -> 1473.2822 | AA20: =Z20*(1+$C20) -> 1546.9463 | AB20: =AA20*(0.98) -> 1516.0073 | AC20: =AB20*(1+$C20) -> 1591.8077 | AD20: =AC20*(0.98) -> 1559.9715 | AE20: =AD20*(1+$C20) -> 1637.9701 | AF20: =AE20*(0.98) -> 1605.2107 | AG20: =AF20*(1+$C20) -> 1685.4713 | AH20: =AG20*(0.98) -> 1651.7618 | AI20: =AH20*(1+$C20) -> 1734.3499 | AJ20: =AI20*(1+$C20) -> 1821.0674 | AK20: =AJ20*(1+$C20) -> 1912.1208 | AL20: =AK20*(0.98) -> 1873.8784 | AM20: =AL20*(1+$C20) -> 1967.5723 | AN20: =AM20*(1+$C20) -> 2065.9509
B21: Rent & Lease | C21: 0.03 | E21: 3500 | F21: =E21*(1+$C21) -> 3605 | G21: =F21*(0.98) -> 3532.9 | H21: =G21*(1+$C21) -> 3638.887 | I21: =H21*(1+$C21) -> 3748.0536 | J21: =I21*(0.98) -> 3673.0925 | K21: =J21*(1+$C21) -> 3783.2853 | L21: =K21*(1+$C21) -> 3896.7839 | M21: =L21*(1+$C21) -> 4013.6874 | N21: =M21*(0.98) -> 3933.4136 | O21: =N21*(1+$C21) -> 4051.4161 | P21: =O21*(1+$C21) -> 4172.9585 | Q21: =P21*(1+$C21) -> 4298.1473 | R21: =Q21*(0.98) -> 4212.1843 | S21: =R21*(1+$C21) -> 4338.5499 | T21: =S21*(1+$C21) -> 4468.7064 | U21: =T21*(1+$C21) -> 4602.7676 | V21: =U21*(0.98) -> 4510.7122 | W21: =V21*(1+$C21) -> 4646.0336 | X21: =W21*(1+$C21) -> 4785.4146 | Y21: =X21*(0.98) -> 4689.7063 | Z21: =Y21*(1+$C21) -> 4830.3975 | AA21: =Z21*(1+$C21) -> 4975.3094 | AB21: =AA21*(0.98) -> 4875.8032 | AC21: =AB21*(1+$C21) -> 5022.0773 | AD21: =AC21*(0.9) -> 4519.8696 | AE21: =AD21*(0.9) -> 4067.8826 | AF21: =AE21*(0.9) -> 3661.0944 | AG21: =AF21*(0.9) -> 3294.9849 | AH21: =AG21*(0.98) -> 3229.0852 | AI21: =AH21*(1+$C21) -> 3325.9578 | AJ21: =AI21*(1+$C21) -> 3425.7365 | AK21: =AJ21*(1+$C21) -> 3528.5086 | AL21: =AK21*(0.9) -> 3175.6578 | AM21: =AL21*(0.9) -> 2858.092 | AN21: =AM21*(0.9) -> 2572.2828
B22: Utilities | C22: 0.03 | E22: 350 | F22: =E22*(1+$C22) -> 360.5 | G22: =F22*(0.98) -> 353.29 | H22: =G22*(1+$C22) -> 363.8887 | I22: =H22*(1+$C22) -> 374.80536 | J22: =I22*(0.98) -> 367.30925 | K22: =J22*(1+$C22) -> 378.32853 | L22: =K22*(1+$C22) -> 389.67839 | M22: =L22*(1+$C22) -> 401.36874 | N22: =M22*(0.98) -> 393.34136 | O22: =N22*(1+$C22) -> 405.14161 | P22: =O22*(1+$C22) -> 417.29585 | Q22: =P22*(1+$C22) -> 429.81473 | R22: =Q22*(0.98) -> 421.21843 | S22: =R22*(1+$C22) -> 433.85499 | T22: =S22*(1+$C22) -> 446.87064 | U22: =T22*(1+$C22) -> 460.27676 | V22: =U22*(0.98) -> 451.07122 | W22: =V22*(1+$C22) -> 464.60336 | X22: =W22*(1+$C22) -> 478.54146 | Y22: =X22*(0.98) -> 468.97063 | Z22: =Y22*(1+$C22) -> 483.03975 | AA22: =Z22*(1+$C22) -> 497.53094 | AB22: =AA22*(0.98) -> 487.58032 | AC22: =AB22*(1+$C22) -> 502.20773 | AD22: =AC22*(0.98) -> 492.16358 | AE22: =AD22*(1+$C22) -> 506.92848 | AF22: =AE22*(0.98) -> 496.78991 | AG22: =AF22*(1+$C22) -> 511.69361 | AH22: =AG22*(0.98) -> 501.45974 | AI22: =AH22*(1+$C22) -> 516.50353 | AJ22: =AI22*(1+$C22) -> 531.99864 | AK22: =AJ22*(1+$C22) -> 547.9586 | AL22: =AK22*(0.98) -> 536.99942 | AM22: =AL22*(1+$C22) -> 553.10941 | AN22: =AM22*(1+$C22) -> 569.70269
B23: Total Office Expenses | E23: =SUM(E22, E21, E20 + E19) -> 4650 | F23: =SUM(F22, F21, F20 + F19) -> 4805.5 | G23: =SUM(G22, G21, G20 + G19) -> 4709.39 | H23: =SUM(H22, H21, H20 + H19) -> 4867.1357 | I23: =SUM(I22, I21, I20 + I19) -> 5030.437 | J23: =SUM(J22, J21, J20 + J19) -> 4929.8282 | K23: =SUM(K22, K21, K20 + K19) -> 5095.5116 | L23: =SUM(L22, L21, L20 + L19) -> 5267.0549 | ... AN23: =SUM(AN22, AN21, AN20 + AN19) -> 5207.9364
B24: Professional Services | E24: 0 | F24: =E24*(1+$C24) -> 0 | G24: =F24*(0.98) -> 0 | H24: =G24*(1+$C24) -> 0 | I24: =H24*(1+$C24) -> 0 | J24: =I24*(0.98) -> 0 | K24: =J24*(1+$C24) -> 0 | L24: =K24*(1+$C24) -> 0 | M24: =L24*(1+$C24) -> 0 | N24: =M24*(0.98) -> 0 | O24: =N24*(1+$C24) -> 0 | P24: =O24*(1+$C24) -> 0 | Q24: =P24*(1+$C24) -> 0 | R24: =Q24*(0.98) -> 0 | S24: =R24*(1+$C24) -> 0 | T24: =S24*(1+$C24) -> 0 | U24: =T24*(1+$C24) -> 0 | V24: =U24*(0.98) -> 0 | W24: =V24*(1+$C24) -> 0 | X24: =W24*(1+$C24) -> 0 | Y24: =X24*(0.98) -> 0 | Z24: =Y24*(1+$C24) -> 0 | AA24: =Z24*(1+$C24) -> 0 | AB24: =AA24*(0.98) -> 0 | AC24: =AB24*(1+$C24) -> 0 | AD24: =AC24*(0.98) -> 0 | AE24: =AD24*(1+$C24) -> 0 | AF24: =AE24*(0.98) -> 0 | AG24: =AF24*(1+$C24) -> 0 | AH24: =AG24*(0.98) -> 0 | AI24: =AH24*(1+$C24) -> 0 | AJ24: =AI24*(1+$C24) -> 0 | AK24: =AJ24*(1+$C24) -> 0 | AL24: =AK24*(0.98) -> 0 | AM24: =AL24*(1+$C24) -> 0 | AN24: =AM24*(1+$C24) -> 0
B25: Accounting Fees | C25: 0.02 | E25: 1000 | F25: =E25*(1+$C25) -> 1020 | G25: =F25*(0.98) -> 999.6 | H25: =G25*(1+$C25) -> 1019.592 | I25: =H25*(1+$C25) -> 1039.9838 | J25: =I25*(0.98) -> 1019.1842 | K25: =J25*(1+$C25) -> 1039.5678 | L25: =K25*(1+$C25) -> 1060.3592 | M25: =L25*(1+$C25) -> 1081.5664 | N25: =M25*(0.98) -> 1059.9351 | O25: =N25*(1+$C25) -> 1081.1338 | P25: =O25*(1+$C25) -> 1102.7564 | Q25: =P25*(1+$C25) -> 1124.8116 | R25: =Q25*(0.98) -> 1102.3153 | S25: =R25*(1+$C25) -> 1124.3616 | T25: =S25*(1+$C25) -> 1146.8489 | U25: =T25*(1+$C25) -> 1169.7859 | V25: =U25*(0.98) -> 1146.3901 | W25: =V25*(1+$C25) -> 1169.3179 | X25: =W25*(1+$C25) -> 1192.7043 | Y25: =X25*(0.98) -> 1168.8502 | Z25: =Y25*(1+$C25) -> 1192.2272 | AA25: =Z25*(1+$C25) -> 1216.0718 | AB25: =AA25*(0.98) -> 1191.7503 | AC25: =AB25*(1+$C25) -> 1215.5853 | AD25: =AC25*(0.98) -> 1191.2736 | AE25: =AD25*(1+$C25) -> 1215.0991 | AF25: =AE25*(0.98) -> 1190.7971 | AG25: =AF25*(1+$C25) -> 1214.6131 | AH25: =AG25*(0.98) -> 1190.3208 | AI25: =AH25*(1+$C25) -> 1214.1272 | AJ25: =AI25*(1+$C25) -> 1238.4098 | AK25: =AJ25*(1+$C25) -> 1263.1779 | AL25: =AK25*(0.98) -> 1237.9144 | AM25: =AL25*(1+$C25) -> 1262.6727 | AN25: =AM25*(1+$C25) -> 1287.9261
B26: Consulting Fees | C26: 0.03 | E26: 2500 | F26: =E26*(1+$C26) -> 2575 | G26: =F26*(0.98) -> 2523.5 | H26: =G26*(1+$C26) -> 2599.205 | I26: =H26*(1+$C26) -> 2677.1811 | J26: =I26*(0.98) -> 2623.6375 | K26: =J26*(1+$C26) -> 2702.3467 | L26: =K26*(1+$C26) -> 2783.4171 | M26: =L26*(1+$C26) -> 2866.9196 | N26: =M26*(0.98) -> 2809.5812 | O26: =N26*(1+$C26) -> 2893.8686 | P26: =O26*(1+$C26) -> 2980.6847 | Q26: =P26*(1+$C26) -> 3070.1052 | R26: =Q26*(0.98) -> 3008.7031 | S26: =R26*(1+$C26) -> 3098.9642 | T26: =S26*(1+$C26) -> 3191.9331 | U26: =T26*(1+$C26) -> 3287.6911 | V26: =U26*(0.98) -> 3221.9373 | W26: =V26*(1+$C26) -> 3318.5954 | X26: =W26*(1+$C26) -> 3418.1533 | Y26: =X26*(0.98) -> 3349.7902 | Z26: =Y26*(1+$C26) -> 3450.2839 | AA26: =Z26*(1+$C26) -> 3553.7924 | AB26: =AA26*(0.98) -> 3482.7166 | AC26: =AB26*(1+$C26) -> 3587.1981 | AD26: =AC26*(0.98) -> 3515.4541 | AE26: =AD26*(1+$C26) -> 3620.9177 | AF26: =AE26*(0.98) -> 3548.4994 | AG26: =AF26*(1+$C26) -> 3654.9544 | AH26: =AG26*(0.98) -> 3581.8553 | AI26: =AH26*(1+$C26) -> 3689.3109 | AJ26: =AI26*(1+$C26) -> 3799.9903 | AK26: =AJ26*(1+$C26) -> 3913.99 | AL26: =AK26*(0.98) -> 3835.7102 | AM26: =AL26*(1+$C26) -> 3950.7815 | AN26: =AM26*(1+$C26) -> 4069.3049
B27: Legal Fees | C27: 0.03 | E27: 1500 | F27: =E27*(1+$C27) -> 1545 | G27: =F27*(0.98) -> 1514.1 | H27: =G27*(1+$C27) -> 1559.523 | I27: =H27*(1+$C27) -> 1606.3087 | J27: =I27*(0.98) -> 1574.1825 | K27: =J27*(1+$C27) -> 1621.408 | L27: =K27*(1+$C27) -> 1670.0502 | M27: =L27*(1+$C27) -> 1720.1517 | N27: =M27*(0.98) -> 1685.7487 | O27: =N27*(1+$C27) -> 1736.3212 | P27: =O27*(1+$C27) -> 1788.4108 | Q27: =P27*(1+$C27) -> 1842.0631 | R27: =Q27*(0.98) -> 1805.2219 | S27: =R27*(1+$C27) -> 1859.3785 | T27: =S27*(1+$C27) -> 1915.1599 | U27: =T27*(1+$C27) -> 1972.6147 | V27: =U27*(0.98) -> 1933.1624 | W27: =V27*(1+$C27) -> 1991.1572 | X27: =W27*(1+$C27) -> 2050.892 | Y27: =X27*(0.98) -> 2009.8741 | Z27: =Y27*(1+$C27) -> 2070.1703 | AA27: =Z27*(1+$C27) -> 2132.2755 | AB27: =AA27*(0.98) -> 2089.6299 | AC27: =AB27*(1+$C27) -> 2152.3188 | AD27: =AC27*(0.98) -> 2109.2725 | AE27: =AD27*(1+$C27) -> 2172.5506 | AF27: =AE27*(0.98) -> 2129.0996 | AG27: =AF27*(1+$C27) -> 2192.9726 | AH27: =AG27*(0.98) -> 2149.1132 | AI27: =AH27*(1+$C27) -> 2213.5866 | AJ27: =AI27*(1+$C27) -> 2279.9942 | AK27: =AJ27*(1+$C27) -> 2348.394 | AL27: =AK27*(0.98) -> 2301.4261 | AM27: =AL27*(1+$C27) -> 2370.4689 | AN27: =AM27*(1+$C27) -> 2441.583
B28: Recruiting Fees | C28: 0.03 | E28: 2000 | F28: =E28*(1+$C28) -> 2060 | G28: =F28*(0.98) -> 2018.8 | H28: =G28*(1+$C28) -> 2079.364 | I28: =H28*(1+$C28) -> 2141.7449 | J28: =I28*(0.98) -> 2098.91 | K28: =J28*(1+$C28) -> 2161.8773 | L28: =K28*(1+$C28) -> 2226.7336 | M28: =L28*(1+$C28) -> 2293.5357 | N28: =M28*(0.98) -> 2247.6649 | O28: =N28*(1+$C28) -> 2315.0949 | P28: =O28*(1+$C28) -> 2384.5477 | Q28: =P28*(1+$C28) -> 2456.0842 | R28: =Q28*(0.98) -> 2406.9625 | S28: =R28*(1+$C28) -> 2479.1714 | T28: =S28*(1+$C28) -> 2553.5465 | U28: =T28*(1+$C28) -> 2630.1529 | V28: =U28*(0.98) -> 2577.5498 | W28: =V28*(1+$C28) -> 2654.8763 | X28: =W28*(1+$C28) -> 2734.5226 | Y28: =X28*(0.98) -> 2679.8322 | Z28: =Y28*(1+$C28) -> 2760.2271 | AA28: =Z28*(1+$C28) -> 2843.0339 | AB28: =AA28*(0.98) -> 2786.1733 | AC28: =AB28*(1+$C28) -> 2869.7585 | AD28: =AC28*(0.98) -> 2812.3633 | AE28: =AD28*(1+$C28) -> 2896.7342 | AF28: =AE28*(0.98) -> 2838.7995 | AG28: =AF28*(1+$C28) -> 2923.9635 | AH28: =AG28*(0.98) -> 2865.4842 | AI28: =AH28*(1+$C28) -> 2951.4488 | AJ28: =AI28*(1+$C28) -> 3039.9922 | AK28: =AJ28*(1+$C28) -> 3131.192 | AL28: =AK28*(0.98) -> 3068.5681 | AM28: =AL28*(1+$C28) -> 3160.6252 | AN28: =AM28*(1+$C28) -> 3255.4439
B29: Total Professional Services | E29: =SUM(E28, E27, E26, E25 + E24) -> 7000 | F29: =SUM(F28, F27, F26, F25 + F24) -> 7200 | G29: =SUM(G28, G27, G26, G25 + G24) -> 7056 | H29: =SUM(H28, H27, H26, H25 + H24) -> 7257.684 | I29: =SUM(I28, I27, I26, I25 + I24) -> 7465.2186 | J29: =SUM(J28, J27, J26, J25 + J24) -> 7315.9142 | K29: =SUM(K28, K27, K26, K25 + K24) -> 7525.1998 | L29: =SUM(L28, L27, L26, L25 + L24) -> 7740.5601 | ... AN29: =SUM(AN28, AN27, AN26, AN25 + AN24) -> 11054.258
B30: Payroll Expenses | C30: 0.03 | E30: 0 | F30: =E30*(1+$C30) -> 0 | G30: =F30*(0.98) -> 0 | H30: =G30*(1+$C30) -> 0 | I30: =H30*(1+$C30) -> 0 | J30: =I30*(0.98) -> 0 | K30: =J30*(1+$C30) -> 0 | L30: =K30*(1+$C30) -> 0 | M30: =L30*(1+$C30) -> 0 | N30: =M30*(0.98) -> 0 | O30: =N30*(1+$C30) -> 0 | P30: =O30*(1+$C30) -> 0 | Q30: =P30*(1+$C30) -> 0 | R30: =Q30*(0.98) -> 0 | S30: =R30*(1+$C30) -> 0 | T30: =S30*(1+$C30) -> 0 | U30: =T30*(1+$C30) -> 0 | V30: =U30*(0.98) -> 0 | W30: =V30*(1+$C30) -> 0 | X30: =W30*(1+$C30) -> 0 | Y30: =X30*(0.98) -> 0 | Z30: =Y30*(1+$C30) -> 0 | AA30: =Z30*(1+$C30) -> 0 | AB30: =AA30*(0.98) -> 0 | AC30: =AB30*(1+$C30) -> 0 | AD30: =AC30*(0.98) -> 0 | AE30: =AD30*(1+$C30) -> 0 | AF30: =AE30*(0.98) -> 0 | AG30: =AF30*(1+$C30) -> 0 | AH30: =AG30*(0.98) -> 0 | AI30: =AH30*(1+$C30) -> 0 | AJ30: =AI30*(1+$C30) -> 0 | AK30: =AJ30*(1+$C30) -> 0 | AL30: =AK30*(0.98) -> 0 | AM30: =AL30*(1+$C30) -> 0 | AN30: =AM30*(1+$C30) -> 0
B31: Salary & Wages | C31: 0.05 | E31: 5000 | F31: =E31*(1+$C31) -> 5250 | G31: =F31*(0.98) -> 5145 | H31: =G31*(0.9) -> 4630.5 | I31: =H31*(0.9) -> 4167.45 | J31: =I31*(0.9) -> 3750.705 | K31: =J31*(1+$C31) -> 3938.2403 | L31: =K31*(1+$C31) -> 4135.1523 | M31: =L31*(1+$C31) -> 4341.9099 | N31: =M31*(0.98) -> 4255.0717 | O31: =N31*(1+$C31) -> 4467.8253 | P31: =O31*(1+$C31) -> 4691.2165 | Q31: =P31*(1+$C31) -> 4925.7774 | R31: =Q31*(0.98) -> 4827.2618 | S31: =R31*(0.9) -> 4344.5356 | T31: =S31*(0.9) -> 3910.0821 | U31: =T31*(1+$C31) -> 4105.5862 | V31: =U31*(0.98) -> 4023.4744 | W31: =V31*(1+$C31) -> 4224.6482 | X31: =W31*(1+$C31) -> 4435.8806 | Y31: =X31*(0.98) -> 4347.163 | Z31: =Y31*(0.9) -> 3912.4467 | AA31: =Z31*(0.9) -> 3521.202 | AB31: =AA31*(0.9) -> 3169.0818 | AC31: =AB31*(1+$C31) -> 3327.5359 | AD31: =AC31*(0.98) -> 3260.9852 | AE31: =AD31*(1+$C31) -> 3424.0344 | AF31: =AE31*(0.98) -> 3355.5537 | AG31: =AF31*(1+$C31) -> 3523.3314 | AH31: =AG31*(0.9) -> 3170.9983 | AI31: =AH31*(0.9) -> 2853.8985 | AJ31: =AI31*(0.9) -> 2568.5086 | AK31: =AJ31*(1+$C31) -> 2696.934 | AL31: =AK31*(0.98) -> 2642.9954 | AM31: =AL31*(1+$C31) -> 2775.1451 | AN31: =AM31*(1+$C31) -> 2913.9024
B32: Payroll Taxes | C32: 0.03 | E32: 500 | F32: =E32*(1+$C32) -> 515 | G32: =F32*(0.98) -> 504.7 | H32: =G32*(1+$C32) -> 519.841 | I32: =H32*(1+$C32) -> 535.43623 | J32: =I32*(0.98) -> 524.72751 | K32: =J32*(1+$C32) -> 540.46933 | L32: =K32*(1+$C32) -> 556.68341 | M32: =L32*(1+$C32) -> 573.38391 | N32: =M32*(0.98) -> 561.91623 | O32: =N32*(1+$C32) -> 578.77372 | P32: =O32*(1+$C32) -> 596.13693 | Q32: =P32*(1+$C32) -> 614.02104 | R32: =Q32*(0.98) -> 601.74062 | S32: =R32*(1+$C32) -> 619.79284 | T32: =S32*(1+$C32) -> 638.38662 | U32: =T32*(1+$C32) -> 657.53822 | V32: =U32*(0.98) -> 644.38746 | W32: =V32*(1+$C32) -> 663.71908 | X32: =W32*(1+$C32) -> 683.63065 | Y32: =X32*(0.98) -> 669.95804 | Z32: =Y32*(1+$C32) -> 690.05678 | AA32: =Z32*(1+$C32) -> 710.75849 | AB32: =AA32*(0.98) -> 696.54332 | AC32: =AB32*(1+$C32) -> 717.43962 | AD32: =AC32*(0.98) -> 703.09082 | AE32: =AD32*(1+$C32) -> 724.18355 | AF32: =AE32*(0.98) -> 709.69988 | AG32: =AF32*(1+$C32) -> 730.99087 | AH32: =AG32*(0.98) -> 716.37106 | AI32: =AH32*(1+$C32) -> 737.86219 | AJ32: =AI32*(1+$C32) -> 759.99805 | AK32: =AJ32*(1+$C32) -> 782.798 | AL32: =AK32*(0.98) -> 767.14204 | AM32: =AL32*(1+$C32) -> 790.1563 | AN32: =AM32*(1+$C32) -> 813.86099
B33: Health Insurance | C33: 0.03 | E33: 450 | F33: =E33*(1+$C33) -> 463.5 | G33: =F33*(0.98) -> 454.23 | H33: =G33*(1+$C33) -> 467.8569 | I33: =H33*(1+$C33) -> 481.89261 | J33: =I33*(0.98) -> 472.25475 | K33: =J33*(1+$C33) -> 486.4224 | L33: =K33*(1+$C33) -> 501.01507 | M33: =L33*(1+$C33) -> 516.04552 | N33: =M33*(0.98) -> 505.72461 | O33: =N33*(1+$C33) -> 520.89635 | P33: =O33*(1+$C33) -> 536.52324 | Q33: =P33*(1+$C33) -> 552.61894 | R33: =Q33*(0.98) -> 541.56656 | S33: =R33*(1+$C33) -> 557.81356 | T33: =S33*(1+$C33) -> 574.54796 | U33: =T33*(1+$C33) -> 591.7844 | V33: =U33*(0.98) -> 579.94871 | W33: =V33*(1+$C33) -> 597.34717 | X33: =W33*(1+$C33) -> 615.26759 | Y33: =X33*(0.98) -> 602.96224 | Z33: =Y33*(1+$C33) -> 621.0511 | AA33: =Z33*(1+$C33) -> 639.68264 | AB33: =AA33*(0.98) -> 626.88898 | AC33: =AB33*(1+$C33) -> 645.69565 | AD33: =AC33*(0.98) -> 632.78174 | AE33: =AD33*(1+$C33) -> 651.76519 | AF33: =AE33*(0.98) -> 638.72989 | AG33: =AF33*(1+$C33) -> 657.89179 | AH33: =AG33*(0.98) -> 644.73395 | AI33: =AH33*(1+$C33) -> 664.07597 | AJ33: =AI33*(1+$C33) -> 683.99825 | AK33: =AJ33*(1+$C33) -> 704.5182 | AL33: =AK33*(0.98) -> 690.42783 | AM33: =AL33*(1+$C33) -> 711.14067 | AN33: =AM33*(1+$C33) -> 732.47489
B34: Payroll Processing Fees | C34: 0.05 | E34: 50 | F34: =E34*(1+$C34) -> 52.5 | G34: =F34*(0.98) -> 51.45 | H34: =G34*(1+$C34) -> 54.0225 | I34: =H34*(1+$C34) -> 56.723625 | J34: =I34*(0.98) -> 55.589153 | K34: =J34*(1+$C34) -> 58.36861 | L34: =K34*(1+$C34) -> 61.287041 | M34: =L34*(1+$C34) -> 64.351393 | N34: =M34*(0.98) -> 63.064365 | O34: =N34*(1+$C34) -> 66.217583 | P34: =O34*(1+$C34) -> 69.528462 | Q34: =P34*(1+$C34) -> 73.004885 | R34: =Q34*(0.98) -> 71.544788 | S34: =R34*(1+$C34) -> 75.122027 | T34: =S34*(1+$C34) -> 78.878128 | U34: =T34*(1+$C34) -> 82.822035 | V34: =U34*(0.98) -> 81.165594 | W34: =V34*(1+$C34) -> 85.223874 | X34: =W34*(1+$C34) -> 89.485067 | Y34: =X34*(0.98) -> 87.695366 | Z34: =Y34*(1+$C34) -> 92.080134 | AA34: =Z34*(1+$C34) -> 96.684141 | AB34: =AA34*(0.98) -> 94.750458 | AC34: =AB34*(1+$C34) -> 99.487981 | AD34: =AC34*(0.98) -> 97.498222 | AE34: =AD34*(1+$C34) -> 102.37313 | AF34: =AE34*(0.98) -> 100.32567 | AG34: =AF34*(1+$C34) -> 105.34195 | AH34: =AG34*(0.98) -> 103.23511 | AI34: =AH34*(1+$C34) -> 108.39687 | AJ34: =AI34*(1+$C34) -> 113.81671 | AK34: =AJ34*(1+$C34) -> 119.50755 | AL34: =AK34*(0.98) -> 117.1174 | AM34: =AL34*(1+$C34) -> 122.97327 | AN34: =AM34*(1+$C34) -> 129.12193
B35: Commissions Expense | C35: 0.03 | E35: 0 | F35: =E35*(1+$C35) -> 0 | G35: =F35*(0.98) -> 0 | H35: =G35*(1+$C35) -> 0 | I35: =H35*(1+$C35) -> 0 | J35: =I35*(0.98) -> 0 | K35: =J35*(1+$C35) -> 0 | L35: =K35*(1+$C35) -> 0 | M35: =L35*(1+$C35) -> 0 | N35: =M35*(0.98) -> 0 | O35: =N35*(1+$C35) -> 0 | P35: =O35*(1+$C35) -> 0 | Q35: =P35*(1+$C35) -> 0 | R35: =Q35*(0.98) -> 0 | S35: =R35*(1+$C35) -> 0 | T35: =S35*(1+$C35) -> 0 | U35: =T35*(1+$C35) -> 0 | V35: =U35*(0.98) -> 0 | W35: =V35*(1+$C35) -> 0 | X35: =W35*(1+$C35) -> 0 | Y35: =X35*(0.98) -> 0 | Z35: =Y35*(1+$C35) -> 0 | AA35: =Z35*(1+$C35) -> 0 | AB35: =AA35*(0.98) -> 0 | AC35: =AB35*(1+$C35) -> 0 | AD35: =AC35*(0.98) -> 0 | AE35: =AD35*(1+$C35) -> 0 | AF35: =AE35*(0.98) -> 0 | AG35: =AF35*(1+$C35) -> 0 | AH35: =AG35*(0.98) -> 0 | AI35: =AH35*(1+$C35) -> 0 | AJ35: =AI35*(1+$C35) -> 0 | AK35: =AJ35*(1+$C35) -> 0 | AL35: =AK35*(0.98) -> 0 | AM35: =AL35*(1+$C35) -> 0 | AN35: =AM35*(1+$C35) -> 0
B36: Total Payroll Expenses | E36: =SUM(E35, E34, E33, E32, E31 + E30) -> 6000 | F36: =SUM(F35, F34, F33, F32, F31 + F30) -> 6281 | G36: =SUM(G35, G34, G33, G32, G31 + G30) -> 6155.38 | H36: =SUM(H35, H34, H33, H32, H31 + H30) -> 5672.2204 | I36: =SUM(I35, I34, I33, I32, I31 + I30) -> 5241.5025 | J36: =SUM(J35, J34, J33, J32, J31 + J30) -> 4803.2764 | K36: =SUM(K35, K34, K33, K32, K31 + K30) -> 5023.5006 | L36: =SUM(L35, L34, L33, L32, L31 + L30) -> 5254.1378 | ... AN36: =SUM(AN35, AN34, AN33, AN32, AN31 + AN30) -> 4589.3602
B37: Taxes & Licenses | C37: 0.05 | E37: 150 | F37: =E37*(1+$C37) -> 157.5 | G37: =F37*(0.98) -> 154.35 | H37: =G37*(1+$C37) -> 162.0675 | I37: =H37*(1+$C37) -> 170.17087 | J37: =I37*(0.98) -> 166.76746 | K37: =J37*(1+$C37) -> 175.10583 | L37: =K37*(1+$C37) -> 183.86112 | M37: =L37*(1+$C37) -> 193.05418 | N37: =M37*(0.98) -> 189.19309 | O37: =N37*(1+$C37) -> 198.65275 | P37: =O37*(1+$C37) -> 208.58539 | Q37: =P37*(1+$C37) -> 219.01466 | R37: =Q37*(0.98) -> 214.63436 | S37: =R37*(1+$C37) -> 225.36608 | T37: =S37*(1+$C37) -> 236.63439 | U37: =T37*(1+$C37) -> 248.4661 | V37: =U37*(0.98) -> 243.49678 | W37: =V37*(1+$C37) -> 255.67162 | X37: =W37*(1+$C37) -> 268.4552 | Y37: =X37*(0.98) -> 263.0861 | Z37: =Y37*(1+$C37) -> 276.2404 | AA37: =Z37*(1+$C37) -> 290.05242 | AB37: =AA37*(0.98) -> 284.25137 | AC37: =AB37*(1+$C37) -> 298.46394 | AD37: =AC37*(0.98) -> 292.49466 | AE37: =AD37*(1+$C37) -> 307.1194 | AF37: =AE37*(0.98) -> 300.97701 | AG37: =AF37*(1+$C37) -> 316.02586 | AH37: =AG37*(0.98) -> 309.70534 | AI37: =AH37*(1+$C37) -> 325.19061 | AJ37: =AI37*(1+$C37) -> 341.45014 | AK37: =AJ37*(1+$C37) -> 358.52265 | AL37: =AK37*(0.98) -> 351.3522 | AM37: =AL37*(1+$C37) -> 368.9198 | AN37: =AM37*(1+$C37) -> 387.3658
B38: Travel, Meals & Entertainment | C38: 0.03 | E38: 0 | F38: =E38*(1+$C38) -> 0 | G38: =F38*(0.98) -> 0 | H38: =G38*(1+$C38) -> 0 | I38: =H38*(1+$C38) -> 0 | J38: =I38*(0.98) -> 0 | K38: =J38*(1+$C38) -> 0 | L38: =K38*(1+$C38) -> 0 | M38: =L38*(1+$C38) -> 0 | N38: =M38*(0.98) -> 0 | O38: =N38*(1+$C38) -> 0 | P38: =O38*(1+$C38) -> 0 | Q38: =P38*(1+$C38) -> 0 | R38: =Q38*(0.98) -> 0 | S38: =R38*(1+$C38) -> 0 | T38: =S38*(1+$C38) -> 0 | U38: =T38*(1+$C38) -> 0 | V38: =U38*(0.98) -> 0 | W38: =V38*(1+$C38) -> 0 | X38: =W38*(1+$C38) -> 0 | Y38: =X38*(0.98) -> 0 | Z38: =Y38*(1+$C38) -> 0 | AA38: =Z38*(1+$C38) -> 0 | AB38: =AA38*(0.98) -> 0 | AC38: =AB38*(1+$C38) -> 0 | AD38: =AC38*(0.98) -> 0 | AE38: =AD38*(1+$C38) -> 0 | AF38: =AE38*(0.98) -> 0 | AG38: =AF38*(1+$C38) -> 0 | AH38: =AG38*(0.98) -> 0 | AI38: =AH38*(1+$C38) -> 0 | AJ38: =AI38*(1+$C38) -> 0 | AK38: =AJ38*(1+$C38) -> 0 | AL38: =AK38*(0.98) -> 0 | AM38: =AL38*(1+$C38) -> 0 | AN38: =AM38*(1+$C38) -> 0
B39: Lodging | C39: 0.03 | E39: 1000 | F39: =E39*(1+$C39) -> 1030 | G39: =F39*(0.98) -> 1009.4 | H39: =G39*(1+$C39) -> 1039.682 | I39: =H39*(1+$C39) -> 1070.8725 | J39: =I39*(0.98) -> 1049.455 | K39: =J39*(1+$C39) -> 1080.9387 | L39: =K39*(1+$C39) -> 1113.3668 | M39: =L39*(1+$C39) -> 1146.7678 | N39: =M39*(0.98) -> 1123.8325 | O39: =N39*(1+$C39) -> 1157.5474 | P39: =O39*(1+$C39) -> 1192.2739 | Q39: =P39*(1+$C39) -> 1228.0421 | R39: =Q39*(0.98) -> 1203.4812 | S39: =R39*(1+$C39) -> 1239.5857 | T39: =S39*(1+$C39) -> 1276.7732 | U39: =T39*(1+$C39) -> 1315.0764 | V39: =U39*(0.98) -> 1288.7749 | W39: =V39*(1+$C39) -> 1327.4382 | X39: =W39*(1+$C39) -> 1367.2613 | Y39: =X39*(0.98) -> 1339.9161 | Z39: =Y39*(1+$C39) -> 1380.1136 | AA39: =Z39*(1+$C39) -> 1421.517 | AB39: =AA39*(0.98) -> 1393.0866 | AC39: =AB39*(1+$C39) -> 1434.8792 | AD39: =AC39*(0.98) -> 1406.1816 | AE39: =AD39*(1+$C39) -> 1448.3671 | AF39: =AE39*(0.98) -> 1419.3998 | AG39: =AF39*(1+$C39) -> 1461.9817 | AH39: =AG39*(0.98) -> 1432.7421 | AI39: =AH39*(1+$C39) -> 1475.7244 | AJ39: =AI39*(1+$C39) -> 1519.9961 | AK39: =AJ39*(1+$C39) -> 1565.596 | AL39: =AK39*(0.98) -> 1534.2841 | AM39: =AL39*(1+$C39) -> 1580.3126 | AN39: =AM39*(1+$C39) -> 1627.722
B40: Meals & Entertainment | C40: 0.05 | E40: 400 | F40: =E40*(1+$C40) -> 420 | G40: =F40*(0.98) -> 411.6 | H40: =G40*(1+$C40) -> 432.18 | I40: =H40*(1+$C40) -> 453.789 | J40: =I40*(0.98) -> 444.71322 | K40: =J40*(1+$C40) -> 466.94888 | L40: =K40*(1+$C40) -> 490.29633 | M40: =L40*(1+$C40) -> 514.81114 | N40: =M40*(0.98) -> 504.51492 | O40: =N40*(1+$C40) -> 529.74066 | P40: =O40*(1+$C40) -> 556.2277 | Q40: =P40*(1+$C40) -> 584.03908 | R40: =Q40*(0.98) -> 572.3583 | S40: =R40*(1+$C40) -> 600.97622 | T40: =S40*(1+$C40) -> 631.02503 | U40: =T40*(1+$C40) -> 662.57628 | V40: =U40*(0.98) -> 649.32475 | W40: =V40*(1+$C40) -> 681.79099 | X40: =W40*(1+$C40) -> 715.88054 | Y40: =X40*(0.98) -> 701.56293 | Z40: =Y40*(1+$C40) -> 736.64108 | AA40: =Z40*(1+$C40) -> 773.47313 | AB40: =AA40*(0.98) -> 758.00367 | AC40: =AB40*(1+$C40) -> 795.90385 | AD40: =AC40*(0.98) -> 779.98577 | AE40: =AD40*(1+$C40) -> 818.98506 | AF40: =AE40*(0.98) -> 802.60536 | AG40: =AF40*(1+$C40) -> 842.73563 | AH40: =AG40*(0.98) -> 825.88092 | AI40: =AH40*(1+$C40) -> 867.17496 | AJ40: =AI40*(1+$C40) -> 910.53371 | AK40: =AJ40*(1+$C40) -> 956.06039 | AL40: =AK40*(0.98) -> 936.93919 | AM40: =AL40*(1+$C40) -> 983.78615 | AN40: =AM40*(1+$C40) -> 1032.9755
B41: Travel | C41: 0.03 | E41: 300 | F41: =E41*(1+$C41) -> 309 | G41: =F41*(0.98) -> 302.82 | H41: =G41*(1+$C41) -> 311.9046 | I41: =H41*(1+$C41) -> 321.26174 | J41: =I41*(0.98) -> 314.8365 | K41: =J41*(1+$C41) -> 324.2816 | L41: =K41*(1+$C41) -> 334.01005 | M41: =L41*(1+$C41) -> 344.03035 | N41: =M41*(0.98) -> 337.14974 | O41: =N41*(1+$C41) -> 347.26423 | P41: =O41*(1+$C41) -> 357.68216 | Q41: =P41*(1+$C41) -> 368.41262 | R41: =Q41*(0.98) -> 361.04437 | S41: =R41*(1+$C41) -> 371.8757 | T41: =S41*(1+$C41) -> 383.03197 | U41: =T41*(1+$C41) -> 394.52293 | V41: =U41*(0.98) -> 386.63248 | W41: =V41*(1+$C41) -> 398.23145 | X41: =W41*(1+$C41) -> 410.17839 | Y41: =X41*(0.98) -> 401.97482 | Z41: =Y41*(1+$C41) -> 414.03407 | AA41: =Z41*(1+$C41) -> 426.45509 | AB41: =AA41*(0.98) -> 417.92599 | AC41: =AB41*(1+$C41) -> 430.46377 | AD41: =AC41*(0.98) -> 421.85449 | AE41: =AD41*(1+$C41) -> 434.51013 | AF41: =AE41*(0.98) -> 425.81993 | AG41: =AF41*(1+$C41) -> 438.59452 | AH41: =AG41*(0.98) -> 429.82263 | AI41: =AH41*(1+$C41) -> 442.71731 | AJ41: =AI41*(1+$C41) -> 455.99883 | AK41: =AJ41*(1+$C41) -> 469.6788 | AL41: =AK41*(0.98) -> 460.28522 | AM41: =AL41*(1+$C41) -> 474.09378 | AN41: =AM41*(1+$C41) -> 488.31659
B42: Total Travel, Meals & Entertainment | E42: =SUM(E41, E40, E39 + E38) -> 1700 | F42: =E42*(1+$C42) -> 1700 | G42: =F42*(1+$C42) -> 1700 | H42: =G42*(1+$C42) -> 1700 | I42: =H42*(1+$C42) -> 1700 | J42: =I42*(1+$C42) -> 1700 | K42: =J42*(1+$C42) -> 1700 | L42: =K42*(1+$C42) -> 1700 | M42: =L42*(1+$C42) -> 1700 | ... AN42: =AM42*(1+$C42) -> 1700
B43: Total Expenses | E43: =SUM(E41, E40, E39, E38, E37, E35, E34, E33, E32, E31, E30, E28, E27, E26, E25, E24, E22, E21, E20, E19, E18, E17, E16, E15, E14 + E13) -> 25100 | F43: =SUM(F41, F40, F39, F38, F37, F35, F34, F33, F32, F31, F30, F28, F27, F26, F25, F24, F22, F21, F20, F19, F18, F17, F16, F15, F14 + F13) -> 26061 | G43: =SUM(G41, G40, G39, G38, G37, G35, G34, G33, G32, G31, G30, G28, G27, G26, G25, G24, G22, G21, G20, G19, G18, G17, G16, G15, G14 + G13) -> 25456.58 | H43: =SUM(H41, H40, H39, H38, H37, H35, H34, H33, H32, H31, H30, H28, H27, H26, H25, H24, H22, H21, H20, H19, H18, H17, H16, H15, H14 + H13) -> 25661.923 | I43: =SUM(I41, I40, I39, I38, I37, I35, I34, I33, I32, I31, I30, I28, I27, I26, I25, I24, I22, I21, I20, I19, I18, I17, I16, I15, I14 + I13) -> 25946.043 | J43: =SUM(J41, J40, J39, J38, J37, J35, J34, J33, J32, J31, J30, J28, J27, J26, J25, J24, J22, J21, J20, J19, J18, J17, J16, J15, J14 + J13) -> 25093.726 | K43: =SUM(K41, K40, K39, K38, K37, K35, K34, K33, K32, K31, K30, K28, K27, K26, K25, K24, K22, K21, K20, K19, K18, K17, K16, K15, K14 + K13) -> 26041.354 | L43: =SUM(L41, L40, L39, L38, L37, L35, L34, L33, L32, L31, L30, L28, L27, L26, L25, L24, L22, L21, L20, L19, L18, L17, L16, L15, L14 + L13) -> 27027.358 | ... AN43: =SUM(AN41, AN40, AN39, AN38, AN37, AN35, AN34, AN33, AN32, AN31, AN30, AN28, AN27, AN26, AN25, AN24, AN22, AN21, AN20, AN19, AN18, AN17, AN16, AN15, AN14 + AN13) -> 37579.288
B44: Net Operating Income | E44: =E12-E43 -> 49650 | F44: =F12-F43 -> 45764 | G44: =G12-G43 -> 60163.52 | H44: =H12-H43 -> 49127.656 | I44: =I12-I43 -> 53543.997 | J44: =J12-J43 -> 63952.421 | K44: =K12-K43 -> 57176.063 | L44: =L12-L43 -> 62880.955 | ... AN44: =AN12-AN43 -> 77267.959
B45: Other Income | C45: 0.03
B46: Interest Income | C46: 0.03 | E46: 0 | F46: =E46*(1+$C46) -> 0 | G46: =F46*(1+$C46) -> 0 | H46: =G46*(1+$C46) -> 0 | I46: =H46*(1+$C46) -> 0 | J46: =I46*(1+$C46) -> 0 | K46: =J46*(1+$C46) -> 0 | L46: =K46*(1+$C46) -> 0 | M46: =L46*(1+$C46) -> 0 | ... AN46: =AM46*(1+$C46) -> 0
B47: Total Other Income | E47: =SUM(E46 + E45) -> 0 | F47: =SUM(F46 + F45) -> 0 | G47: =SUM(G46 + G45) -> 0 | H47: =SUM(H46 + H45) -> 0 | I47: =SUM(I46 + I45) -> 0 | J47: =SUM(J46 + J45) -> 0 | K47: =SUM(K46 + K45) -> 0 | L47: =SUM(L46 + L45) -> 0 | ... AN47: =SUM(AN46 + AN45) -> 0
B48: Other Expenses | C48: 0.1
B49: Depreciation Expense | C49: 0.1 | E49: 69.444444 | F49: =E49*(1+$C49) -> 76.388889 | G49: =F49*(1+$C49) -> 84.027778 | H49: =G49*(1+$C49) -> 92.430556 | I49: =H49*(1+$C49) -> 101.67361 | J49: =I49*(1+$C49) -> 111.84097 | K49: =J49*(1+$C49) -> 123.02507 | L49: =K49*(1+$C49) -> 135.32758 | M49: =L49*(1+$C49) -> 148.86033 | ... AN49: =AM49*(1+$C49) -> 1951.5581
B50: Interest Expense | C50: 0.1 | E50: 2500 | F50: =E50*(1+$C50) -> 2750 | G50: =F50*(1+$C50) -> 3025 | H50: =G50*(1+$C50) -> 3327.5 | I50: =H50*(1+$C50) -> 3660.25 | J50: =I50*(1+$C50) -> 4026.275 | K50: =J50*(1+$C50) -> 4428.9025 | L50: =K50*(1+$C50) -> 4871.7928 | M50: =L50*(1+$C50) -> 5358.972 | ... AN50: =AM50*(1+$C50) -> 70256.092
B51: Total Other Expenses | E51: =SUM(E50, E49 + E48) -> 2569.4444 | F51: =SUM(F50, F49 + F48) -> 2826.3889 | G51: =SUM(G50, G49 + G48) -> 3109.0278 | H51: =SUM(H50, H49 + H48) -> 3419.9306 | I51: =SUM(I50, I49 + I48) -> 3761.9236 | J51: =SUM(J50, J49 + J48) -> 4138.116 | K51: =SUM(K50, K49 + K48) -> 4551.9276 | L51: =SUM(L50, L49 + L48) -> 5007.1203 | ... AN51: =SUM(AN50, AN49 + AN48) -> 72207.65
B52: Net Other Income | E52: =E47-E51 -> -2569.4444 | F52: =F47-F51 -> -2826.3889 | G52: =G47-G51 -> -3109.0278 | H52: =H47-H51 -> -3419.9306 | I52: =I47-I51 -> -3761.9236 | J52: =J47-J51 -> -4138.116 | K52: =K47-K51 -> -4551.9276 | L52: =L47-L51 -> -5007.1203 | ... AN52: =AN47-AN51 -> -72207.65
B53: Net Income | E53: =E44+E52 -> 47080.556 | F53: =F44+F52 -> 42937.611 | G53: =G44+G52 -> 57054.492 | H53: =H44+H52 -> 45707.725 | I53: =I44+I52 -> 49782.073 | J53: =J44+J52 -> 59814.305 | K53: =K44+K52 -> 52624.136 | L53: =L44+L52 -> 57873.834 | ... AN53: =AN44+AN52 -> 5060.3083
NSC267: 74
NSC268: 75
NSC269: 76
NSC270: 77
NSC271: 78
NRN272: Value Row | NSC272: 79 | NSE272: Value Row | NTQ272: Value Row
NRN273: Value Row | NSC273: 80 | NSE273: Value Row | NTQ273: Value Row
NRN274: Value Row | NSC274: 81 | NSE274: Value Row | NTQ274: Value Row
NRN275: Value Row | NSC275: 82 | NSE275: Value Row | NTQ275: Value Row
NRN276: Value Row | NSC276: 83 | NSE276: Value Row | NTO276: 74 | NTQ276: Value Row
NRN277: Value Row | NSC277: 84 | NSE277: Value Row | NTO277: 75 | NTQ277: Value Row
NSC278: 85 | NTO278: 76
NRN279: Value Row | NSC279: 86 | NSE279: Value Row | NTO279: 77 | NTQ279: Value Row
NRN280: Value Row | NSC280: 87 | NSE280: Value Row | NTO280: 78 | NTQ280: Value Row
NRN281: Value Row | NSC281: 88 | NSE281: Value Row | NTO281: 79 | NTQ281: Value Row
NRN282: Value Row | NSC282: 89 | NSE282: Value Row | NTO282: 80 | NTQ282: Value Row
NRN283: Value Row | NSC283: 90 | NSE283: Value Row | NTO283: 81 | NTQ283: Value Row
NRN284: Summation Row | NSC284: 91 | NSE284: Summation Row | NTO284: 82 | NTQ284: Summation Row
NSC285: 92 | NTO285: 83
NRN286: Value Row | NSC286: 93 | NSE286: Value Row | NTO286: 84 | NTQ286: Value Row
NRN287: Value Row | NSC287: 94 | NSE287: Value Row | NTO287: 85 | NTQ287: Value Row
NRN288: Value Row | NSE288: Value Row | NTO288: 86 | NTQ288: Value Row
NRN289: Value Row | NSE289: Value Row | NTO289: 87 | NTQ289: Value Row
NRN290: Summation Row | NSE290: Summation Row | NTO290: 88 | NTQ290: Summation Row
NRN291: Value Row | NSE291: Value Row | NTO291: 89 | NTQ291: Value Row
NRN292: Value Row | NSE292: Value Row | NTO292: 90 | NTQ292: Value Row
NRN293: Value Row | NSE293: Value Row | NTO293: 91 | NTQ293: Value Row
NTO294: 92
NRN295: Value Row | NSE295: Value Row | NTO295: 93 | NTQ295: Value Row
NSE296: Value Row | NTO296: 94 | NTQ296: Value Row
NSE297: Summation Row | NTO297: 95 | NTQ297: Summation Row
NTO298: 96
NTO299: 97
NTO300: 98
NTO301: 99
NTO302: 100
NTO303: 101
NTO304: 102

Sheet R&D
A1: Income Statement
A2: Your CFO Guy
A3: Research & Development
C4: Growth | E4: 44957 | F4: =EOMONTH(E4,1) -> 44985 | G4: =EOMONTH(F4,1) -> 45016 | H4: =EOMONTH(G4,1) -> 45046 | I4: =EOMONTH(H4,1) -> 45077 | J4: =EOMONTH(I4,1) -> 45107 | K4: =EOMONTH(J4,1) -> 45138 | L4: =EOMONTH(K4,1) -> 45169 | M4: =EOMONTH(L4,1) -> 45199 | ... AN4: =EOMONTH(AM4,1) -> 46022
B5: Revenue
B6: Sales | C6: 0.1 | E6: 0 | F6: 0 | G6: 0 | H6: 0 | I6: 0 | J6: 0 | K6: 0 | L6: 0 | M6: 0 | N6: 0 | O6: 0 | P6: 0 | Q6: 0 | R6: 0 | S6: 0 | T6: 0 | U6: 0 | V6: 0 | W6: 0 | X6: 0 | Y6: 0 | Z6: 0 | AA6: 0 | AB6: 0 | AC6: 0 | AD6: 0 | AE6: 0 | AF6: 0 | AG6: 0 | AH6: 0 | AI6: 0 | AJ6: 0 | AK6: 0 | AL6: 0 | AM6: 0 | AN6: 0
B7: Total Revenue | E7: =SUM(E6 + E5) -> 0 | F7: =SUM(F6 + F5) -> 0 | G7: =SUM(G6 + G5) -> 0 | H7: =SUM(H6 + H5) -> 0 | I7: =SUM(I6 + I5) -> 0 | J7: =SUM(J6 + J5) -> 0 | K7: =SUM(K6 + K5) -> 0 | L7: =SUM(L6 + L5) -> 0 | ... AN7: =SUM(AN6 + AN5) -> 0
B8: Cost of Goods Sold
B9: Web Domain & Hosting Fees | C9: 0.1 | E9: 0 | F9: 0 | G9: 0 | H9: 0 | I9: 0 | J9: 0 | K9: 0 | L9: 0 | M9: 0 | N9: 0 | O9: 0 | P9: 0 | Q9: 0 | R9: 0 | S9: 0 | T9: 0 | U9: 0 | V9: 0 | W9: 0 | X9: 0 | Y9: 0 | Z9: 0 | AA9: 0 | AB9: 0 | AC9: 0 | AD9: 0 | AE9: 0 | AF9: 0 | AG9: 0 | AH9: 0 | AI9: 0 | AJ9: 0 | AK9: 0 | AL9: 0 | AM9: 0 | AN9: 0
B10: Merchant Account Fees | C10: 0.1 | E10: 0 | F10: 0 | G10: 0 | H10: 0 | I10: 0 | J10: 0 | K10: 0 | L10: 0 | M10: 0 | N10: 0 | O10: 0 | P10: 0 | Q10: 0 | R10: 0 | S10: 0 | T10: 0 | U10: 0 | V10: 0 | W10: 0 | X10: 0 | Y10: 0 | Z10: 0 | AA10: 0 | AB10: 0 | AC10: 0 | AD10: 0 | AE10: 0 | AF10: 0 | AG10: 0 | AH10: 0 | AI10: 0 | AJ10: 0 | AK10: 0 | AL10: 0 | AM10: 0 | AN10: 0
B11: Total Cost of Goods Sold | E11: =SUM(E10, E9 + E8) -> 0 | F11: =SUM(F10, F9 + F8) -> 0 | G11: =SUM(G10, G9 + G8) -> 0 | H11: =SUM(H10, H9 + H8) -> 0 | I11: =SUM(I10, I9 + I8) -> 0 | J11: =SUM(J10, J9 + J8) -> 0 | K11: =SUM(K10, K9 + K8) -> 0 | L11: =SUM(L10, L9 + L8) -> 0 | ... AN11: =SUM(AN10, AN9 + AN8) -> 0
B12: Gross Profit | E12: =E7-E11 -> 0 | F12: =F7-F11 -> 0 | G12: =G7-G11 -> 0 | H12: =H7-H11 -> 0 | I12: =I7-I11 -> 0 | J12: =J7-J11 -> 0 | K12: =K7-K11 -> 0 | L12: =L7-L11 -> 0 | ... AN12: =AN7-AN11 -> 0
B13: Expenses
B14: Advertising & Marketing | C14: 0.03 | E14: 0 | F14: 0 | G14: 0 | H14: 0 | I14: 0 | J14: 0 | K14: 0 | L14: 0 | M14: 0 | N14: 0 | O14: 0 | P14: 0 | Q14: 0 | R14: 0 | S14: 0 | T14: 0 | U14: 0 | V14: 0 | W14: 0 | X14: 0 | Y14: 0 | Z14: 0 | AA14: 0 | AB14: 0 | AC14: 0 | AD14: 0 | AE14: 0 | AF14: 0 | AG14: 0 | AH14: 0 | AI14: 0 | AJ14: 0 | AK14: 0 | AL14: 0 | AM14: 0 | AN14: 0
B15: Bank Charges & Fees | C15: 0.03 | E15: 0 | F15: 0 | G15: 0 | H15: 0 | I15: 0 | J15: 0 | K15: 0 | L15: 0 | M15: 0 | N15: 0 | O15: 0 | P15: 0 | Q15: 0 | R15: 0 | S15: 0 | T15: 0 | U15: 0 | V15: 0 | W15: 0 | X15: 0 | Y15: 0 | Z15: 0 | AA15: 0 | AB15: 0 | AC15: 0 | AD15: 0 | AE15: 0 | AF15: 0 | AG15: 0 | AH15: 0 | AI15: 0 | AJ15: 0 | AK15: 0 | AL15: 0 | AM15: 0 | AN15: 0
B16: Conferences & Events | C16: 0.03 | E16: 0 | F16: 0 | G16: 0 | H16: 0 | I16: 0 | J16: 0 | K16: 0 | L16: 0 | M16: 0 | N16: 0 | O16: 0 | P16: 0 | Q16: 0 | R16: 0 | S16: 0 | T16: 0 | U16: 0 | V16: 0 | W16: 0 | X16: 0 | Y16: 0 | Z16: 0 | AA16: 0 | AB16: 0 | AC16: 0 | AD16: 0 | AE16: 0 | AF16: 0 | AG16: 0 | AH16: 0 | AI16: 0 | AJ16: 0 | AK16: 0 | AL16: 0 | AM16: 0 | AN16: 0
B17: Software & Apps | C17: 0.03 | E17: 2600 | F17: =E17*(1+$C17) -> 2678 | G17: =F17*(0.9) -> 2410.2 | H17: =G17*(1+$C17) -> 2482.506 | I17: =H17*(1+$C17) -> 2556.9812 | J17: =I17*(1+$C17) -> 2633.6906 | K17: =J17*(0.9) -> 2370.3216 | L17: =K17*(0.9) -> 2133.2894 | M17: =L17*(1+$C17) -> 2197.2881 | N17: =M17*(1+$C17) -> 2263.2067 | O17: =N17*(1+$C17) -> 2331.1029 | P17: =O17*(1+$C17) -> 2401.036 | Q17: =P17*(1+$C17) -> 2473.0671 | R17: =Q17*(0.9) -> 2225.7604 | S17: =R17*(0.9) -> 2003.1843 | T17: =S17*(1+$C17) -> 2063.2799 | U17: =T17*(1+$C17) -> 2125.1783 | V17: =U17*(0.9) -> 1912.6604 | W17: =V17*(1+$C17) -> 1970.0403 | X17: =W17*(1+$C17) -> 2029.1415 | Y17: =X17*(1+$C17) -> 2090.0157 | Z17: =Y17*(0.9) -> 1881.0141 | AA17: =Z17*(1+$C17) -> 1937.4446 | AB17: =AA17*(1+$C17) -> 1995.5679 | AC17: =AB17*(1+$C17) -> 2055.4349 | AD17: =AC17*(0.9) -> 1849.8914 | AE17: =AD17*(1+$C17) -> 1905.3882 | AF17: =AE17*(1+$C17) -> 1962.5498 | AG17: =AF17*(1+$C17) -> 2021.4263 | AH17: =AG17*(1+$C17) -> 2082.0691 | AI17: =AH17*(0.9) -> 1873.8622 | AJ17: =AI17*(0.9) -> 1686.476 | AK17: =AJ17*(1+$C17) -> 1737.0703 | AL17: =AK17*(1+$C17) -> 1789.1824 | AM17: =AL17*(0.9) -> 1610.2641 | AN17: =AM17*(0.9) -> 1449.2377
B18: Insurance | C18: 0.03 | E18: 150 | F18: =E18*(1+$C18) -> 154.5 | G18: =F18*(1+$C18) -> 159.135 | H18: =G18*(1+$C18) -> 163.90905 | I18: =H18*(1+$C18) -> 168.82632 | J18: =I18*(1+$C18) -> 173.89111 | K18: =J18*(1+$C18) -> 179.10784 | L18: =K18*(1+$C18) -> 184.48108 | M18: =L18*(1+$C18) -> 190.01551 | ... AN18: =AM18*(1+$C18) -> 422.07937
B19: Office Expenses | C19: 0.03 | E19: 0 | F19: =E19*(1+$C19) -> 0 | G19: =F19*(1+$C19) -> 0 | H19: =G19*(1+$C19) -> 0 | I19: =H19*(1+$C19) -> 0 | J19: =I19*(1+$C19) -> 0 | K19: =J19*(1+$C19) -> 0 | L19: =K19*(1+$C19) -> 0 | M19: =L19*(1+$C19) -> 0 | ... AN19: =AM19*(1+$C19) -> 0
B20: Office Supplies | C20: 0.03 | E20: 400 | F20: =E20*(1+$C20) -> 412 | G20: =F20*(1+$C20) -> 424.36 | H20: =G20*(1+$C20) -> 437.0908 | I20: =H20*(1+$C20) -> 450.20352 | J20: =I20*(1+$C20) -> 463.70963 | K20: =J20*(1+$C20) -> 477.62092 | L20: =K20*(1+$C20) -> 491.94955 | M20: =L20*(1+$C20) -> 506.70803 | ... AN20: =AM20*(1+$C20) -> 1125.545
B21: Rent & Lease | C21: 0.03 | E21: 0 | F21: 0 | G21: 0 | H21: 0 | I21: 0 | J21: 0 | K21: 0 | L21: 0 | M21: 0 | N21: 0 | O21: 0 | P21: 0 | Q21: 0 | R21: 0 | S21: 0 | T21: 0 | U21: 0 | V21: 0 | W21: 0 | X21: 0 | Y21: 0 | Z21: 0 | AA21: 0 | AB21: 0 | AC21: 0 | AD21: 0 | AE21: 0 | AF21: 0 | AG21: 0 | AH21: 0 | AI21: 0 | AJ21: 0 | AK21: 0 | AL21: 0 | AM21: 0 | AN21: 0
B22: Utilities | C22: 0.03 | E22: 0 | F22: 0 | G22: 0 | H22: 0 | I22: 0 | J22: 0 | K22: 0 | L22: 0 | M22: 0 | N22: 0 | O22: 0 | P22: 0 | Q22: 0 | R22: 0 | S22: 0 | T22: 0 | U22: 0 | V22: 0 | W22: 0 | X22: 0 | Y22: 0 | Z22: 0 | AA22: 0 | AB22: 0 | AC22: 0 | AD22: 0 | AE22: 0 | AF22: 0 | AG22: 0 | AH22: 0 | AI22: 0 | AJ22: 0 | AK22: 0 | AL22: 0 | AM22: 0 | AN22: 0
B23: Total Office Expenses | E23: =SUM(E22, E21, E20 + E19) -> 400 | F23: =SUM(F22, F21, F20 + F19) -> 412 | G23: =SUM(G22, G21, G20 + G19) -> 424.36 | H23: =SUM(H22, H21, H20 + H19) -> 437.0908 | I23: =SUM(I22, I21, I20 + I19) -> 450.20352 | J23: =SUM(J22, J21, J20 + J19) -> 463.70963 | K23: =SUM(K22, K21, K20 + K19) -> 477.62092 | L23: =SUM(L22, L21, L20 + L19) -> 491.94955 | ... AN23: =SUM(AN22, AN21, AN20 + AN19) -> 1125.545
B24: Professional Services | E24: 0 | F24: =E24*(1+$C24) -> 0 | G24: =F24*(1+$C24) -> 0 | H24: =G24*(1+$C24) -> 0 | I24: =H24*(1+$C24) -> 0 | J24: =I24*(1+$C24) -> 0 | K24: =J24*(1+$C24) -> 0 | L24: =K24*(1+$C24) -> 0 | M24: =L24*(1+$C24) -> 0 | ... AN24: =AM24*(1+$C24) -> 0
B25: Accounting Fees | C25: 0.03 | E25: 0 | F25: 0 | G25: 0 | H25: 0 | I25: 0 | J25: 0 | K25: 0 | L25: 0 | M25: 0 | N25: 0 | O25: 0 | P25: 0 | Q25: 0 | R25: 0 | S25: 0 | T25: 0 | U25: 0 | V25: 0 | W25: 0 | X25: 0 | Y25: 0 | Z25: 0 | AA25: 0 | AB25: 0 | AC25: 0 | AD25: 0 | AE25: 0 | AF25: 0 | AG25: 0 | AH25: 0 | AI25: 0 | AJ25: 0 | AK25: 0 | AL25: 0 | AM25: 0 | AN25: 0
B26: Consulting Fees | C26: 0.03 | E26: 0 | F26: =E26*(1+$C26) -> 0 | G26: =F26*(1+$C26) -> 0 | H26: =G26*(1+$C26) -> 0 | I26: =H26*(1+$C26) -> 0 | J26: =I26*(1+$C26) -> 0 | K26: =J26*(1+$C26) -> 0 | L26: =K26*(1+$C26) -> 0 | M26: =L26*(1+$C26) -> 0 | ... AN26: =AM26*(1+$C26) -> 0
B27: Legal Fees | C27: 0.03 | E27: 500 | F27: =E27*(1+$C27) -> 515 | G27: =F27*(1+$C27) -> 530.45 | H27: =G27*(1+$C27) -> 546.3635 | I27: =H27*(1+$C27) -> 562.75441 | J27: =I27*(1+$C27) -> 579.63704 | K27: =J27*(1+$C27) -> 597.02615 | L27: =K27*(1+$C27) -> 614.93693 | M27: =L27*(1+$C27) -> 633.38504 | ... AN27: =AM27*(1+$C27) -> 1406.9312
B28: Recruiting Fees | C28: 0.03 | E28: 2000 | F28: =E28*(1+$C28) -> 2060 | G28: =F28*(1+$C28) -> 2121.8 | H28: =G28*(1+$C28) -> 2185.454 | I28: =H28*(0.9) -> 1966.9086 | J28: =I28*(1+$C28) -> 2025.9159 | K28: =J28*(1+$C28) -> 2086.6933 | L28: =K28*(1+$C28) -> 2149.2941 | M28: =L28*(1+$C28) -> 2213.773 | N28: =M28*(1+$C28) -> 2280.1861 | O28: =N28*(1+$C28) -> 2348.5917 | P28: =O28*(0.9) -> 2113.7326 | Q28: =P28*(1+$C28) -> 2177.1445 | R28: =Q28*(1+$C28) -> 2242.4589 | S28: =R28*(1+$C28) -> 2309.7326 | T28: =S28*(1+$C28) -> 2379.0246 | U28: =T28*(0.9) -> 2141.1222 | V28: =U28*(1+$C28) -> 2205.3558 | W28: =V28*(1+$C28) -> 2271.5165 | X28: =W28*(1+$C28) -> 2339.662 | Y28: =X28*(1+$C28) -> 2409.8518 | Z28: =Y28*(1+$C28) -> 2482.1474 | AA28: =Z28*(1+$C28) -> 2556.6118 | AB28: =AA28*(0.9) -> 2300.9506 | AC28: =AB28*(1+$C28) -> 2369.9792 | AD28: =AC28*(1+$C28) -> 2441.0785 | AE28: =AD28*(1+$C28) -> 2514.3109 | AF28: =AE28*(0.9) -> 2262.8798 | AG28: =AF28*(1+$C28) -> 2330.7662 | AH28: =AG28*(1+$C28) -> 2400.6892 | AI28: =AH28*(0.9) -> 2160.6203 | AJ28: =AI28*(0.9) -> 1944.5582 | AK28: =AJ28*(1+$C28) -> 2002.895 | AL28: =AK28*(1+$C28) -> 2062.9818 | AM28: =AL28*(1+$C28) -> 2124.8713 | AN28: =AM28*(1+$C28) -> 2188.6174
B29: Total Professional Services | E29: =SUM(E28, E27, E26, E25 + E24) -> 2500 | F29: =SUM(F28, F27, F26, F25 + F24) -> 2575 | G29: =SUM(G28, G27, G26, G25 + G24) -> 2652.25 | H29: =SUM(H28, H27, H26, H25 + H24) -> 2731.8175 | I29: =SUM(I28, I27, I26, I25 + I24) -> 2529.663 | J29: =SUM(J28, J27, J26, J25 + J24) -> 2605.5529 | K29: =SUM(K28, K27, K26, K25 + K24) -> 2683.7195 | L29: =SUM(L28, L27, L26, L25 + L24) -> 2764.2311 | ... AN29: =SUM(AN28, AN27, AN26, AN25 + AN24) -> 3595.5487
B30: Payroll Expenses | C30: 0.03 | E30: 0 | F30: =E30*(1+$C30) -> 0 | G30: =F30*(1+$C30) -> 0 | H30: =G30*(1+$C30) -> 0 | I30: =H30*(1+$C30) -> 0 | J30: =I30*(1+$C30) -> 0 | K30: =J30*(1+$C30) -> 0 | L30: =K30*(1+$C30) -> 0 | M30: =L30*(1+$C30) -> 0 | ... AN30: =AM30*(1+$C30) -> 0
B31: Salary & Wages | C31: 0.03 | E31: 6000 | F31: =E31*(1+$C31) -> 6180 | G31: =F31*(0.9) -> 5562 | H31: =G31*(1+$C31) -> 5728.86 | I31: =H31*(1+$C31) -> 5900.7258 | J31: =I31*(1+$C31) -> 6077.7476 | K31: =J31*(1+$C31) -> 6260.08 | L31: =K31*(1+$C31) -> 6447.8824 | M31: =L31*(1+$C31) -> 6641.3189 | N31: =M31*(1+$C31) -> 6840.5584 | O31: =N31*(1+$C31) -> 7045.7752 | P31: =O31*(0.9) -> 6341.1977 | Q31: =P31*(1+$C31) -> 6531.4336 | R31: =Q31*(1+$C31) -> 6727.3766 | S31: =R31*(1+$C31) -> 6929.1979 | T31: =S31*(1+$C31) -> 7137.0738 | U31: =T31*(1+$C31) -> 7351.1861 | V31: =U31*(1+$C31) -> 7571.7216 | W31: =V31*(0.9) -> 6814.5495 | X31: =W31*(1+$C31) -> 7018.986 | Y31: =X31*(1+$C31) -> 7229.5555 | Z31: =Y31*(1+$C31) -> 7446.4422 | AA31: =Z31*(1+$C31) -> 7669.8355 | AB31: =AA31*(1+$C31) -> 7899.9305 | AC31: =AB31*(1+$C31) -> 8136.9285 | AD31: =AC31*(0.9) -> 7323.2356 | AE31: =AD31*(0.9) -> 6590.912 | AF31: =AE31*(1+$C31) -> 6788.6394 | AG31: =AF31*(1+$C31) -> 6992.2986 | AH31: =AG31*(1+$C31) -> 7202.0676 | AI31: =AH31*(1+$C31) -> 7418.1296 | AJ31: =AI31*(0.9) -> 6676.3166 | AK31: =AJ31*(1+$C31) -> 6876.6061 | AL31: =AK31*(1+$C31) -> 7082.9043 | AM31: =AL31*(1+$C31) -> 7295.3914 | AN31: =AM31*(1+$C31) -> 7514.2532
B32: Payroll Taxes | C32: 0.03 | E32: =E31*0.08 -> 480 | F32: =E32*(1+$C32) -> 494.4 | G32: =F32*(0.9) -> 444.96 | H32: =G32*(1+$C32) -> 458.3088 | I32: =H32*(1+$C32) -> 472.05806 | J32: =I32*(1+$C32) -> 486.21981 | K32: =J32*(1+$C32) -> 500.8064 | L32: =K32*(1+$C32) -> 515.83059 | M32: =L32*(1+$C32) -> 531.30551 | N32: =M32*(1+$C32) -> 547.24468 | O32: =N32*(1+$C32) -> 563.66202 | P32: =O32*(0.9) -> 507.29581 | Q32: =P32*(1+$C32) -> 522.51469 | R32: =Q32*(1+$C32) -> 538.19013 | S32: =R32*(1+$C32) -> 554.33583 | T32: =S32*(1+$C32) -> 570.96591 | U32: =T32*(1+$C32) -> 588.09489 | V32: =U32*(1+$C32) -> 605.73773 | W32: =V32*(0.9) -> 545.16396 | X32: =W32*(1+$C32) -> 561.51888 | Y32: =X32*(1+$C32) -> 578.36444 | Z32: =Y32*(1+$C32) -> 595.71538 | AA32: =Z32*(1+$C32) -> 613.58684 | AB32: =AA32*(1+$C32) -> 631.99444 | AC32: =AB32*(1+$C32) -> 650.95428 | AD32: =AC32*(0.9) -> 585.85885 | AE32: =AD32*(0.9) -> 527.27296 | AF32: =AE32*(1+$C32) -> 543.09115 | AG32: =AF32*(1+$C32) -> 559.38389 | AH32: =AG32*(1+$C32) -> 576.1654 | AI32: =AH32*(1+$C32) -> 593.45037 | AJ32: =AI32*(0.9) -> 534.10533 | AK32: =AJ32*(1+$C32) -> 550.12849 | AL32: =AK32*(1+$C32) -> 566.63234 | AM32: =AL32*(1+$C32) -> 583.63131 | AN32: =AM32*(1+$C32) -> 601.14025
B33: Health Insurance | C33: 0.03 | E33: =E31*1 -> 6000 | F33: =E33*(1+$C33) -> 6180 | G33: =F33*(0.9) -> 5562 | H33: =G33*(1+$C33) -> 5728.86 | I33: =H33*(1+$C33) -> 5900.7258 | J33: =I33*(1+$C33) -> 6077.7476 | K33: =J33*(1+$C33) -> 6260.08 | L33: =K33*(1+$C33) -> 6447.8824 | M33: =L33*(1+$C33) -> 6641.3189 | N33: =M33*(1+$C33) -> 6840.5584 | O33: =N33*(1+$C33) -> 7045.7752 | P33: =O33*(0.9) -> 6341.1977 | Q33: =P33*(1+$C33) -> 6531.4336 | R33: =Q33*(1+$C33) -> 6727.3766 | S33: =R33*(1+$C33) -> 6929.1979 | T33: =S33*(1+$C33) -> 7137.0738 | U33: =T33*(1+$C33) -> 7351.1861 | V33: =U33*(1+$C33) -> 7571.7216 | W33: =V33*(0.9) -> 6814.5495 | X33: =W33*(1+$C33) -> 7018.986 | Y33: =X33*(1+$C33) -> 7229.5555 | Z33: =Y33*(1+$C33) -> 7446.4422 | AA33: =Z33*(1+$C33) -> 7669.8355 | AB33: =AA33*(1+$C33) -> 7899.9305 | AC33: =AB33*(1+$C33) -> 8136.9285 | AD33: =AC33*(0.9) -> 7323.2356 | AE33: =AD33*(0.9) -> 6590.912 | AF33: =AE33*(1+$C33) -> 6788.6394 | AG33: =AF33*(1+$C33) -> 6992.2986 | AH33: =AG33*(1+$C33) -> 7202.0676 | AI33: =AH33*(1+$C33) -> 7418.1296 | AJ33: =AI33*(0.9) -> 6676.3166 | AK33: =AJ33*(1+$C33) -> 6876.6061 | AL33: =AK33*(1+$C33) -> 7082.9043 | AM33: =AL33*(1+$C33) -> 7295.3914 | AN33: =AM33*(1+$C33) -> 7514.2532
B34: Payroll Processing Fees | C34: 0.03 | E34: =E31*0.005 -> 30 | F34: =E34*(1+$C34) -> 30.9 | G34: =F34*(0.9) -> 27.81 | H34: =G34*(1+$C34) -> 28.6443 | I34: =H34*(1+$C34) -> 29.503629 | J34: =I34*(1+$C34) -> 30.388738 | K34: =J34*(1+$C34) -> 31.3004 | L34: =K34*(1+$C34) -> 32.239412 | M34: =L34*(1+$C34) -> 33.206594 | N34: =M34*(1+$C34) -> 34.202792 | O34: =N34*(1+$C34) -> 35.228876 | P34: =O34*(0.9) -> 31.705988 | Q34: =P34*(1+$C34) -> 32.657168 | R34: =Q34*(1+$C34) -> 33.636883 | S34: =R34*(1+$C34) -> 34.64599 | T34: =S34*(1+$C34) -> 35.685369 | U34: =T34*(1+$C34) -> 36.75593 | V34: =U34*(1+$C34) -> 37.858608 | W34: =V34*(0.9) -> 34.072747 | X34: =W34*(1+$C34) -> 35.09493 | Y34: =X34*(1+$C34) -> 36.147778 | Z34: =Y34*(1+$C34) -> 37.232211 | AA34: =Z34*(1+$C34) -> 38.349177 | AB34: =AA34*(1+$C34) -> 39.499653 | AC34: =AB34*(1+$C34) -> 40.684642 | AD34: =AC34*(0.9) -> 36.616178 | AE34: =AD34*(0.9) -> 32.95456 | AF34: =AE34*(1+$C34) -> 33.943197 | AG34: =AF34*(1+$C34) -> 34.961493 | AH34: =AG34*(1+$C34) -> 36.010338 | AI34: =AH34*(1+$C34) -> 37.090648 | AJ34: =AI34*(0.9) -> 33.381583 | AK34: =AJ34*(1+$C34) -> 34.383031 | AL34: =AK34*(1+$C34) -> 35.414522 | AM34: =AL34*(1+$C34) -> 36.476957 | AN34: =AM34*(1+$C34) -> 37.571266
B35: Commissions Expense | C35: 0.03 | E35: 0 | F35: =E35*(1+$C35) -> 0 | G35: =F35*(0.9) -> 0 | H35: =G35*(1+$C35) -> 0 | I35: =H35*(1+$C35) -> 0 | J35: =I35*(1+$C35) -> 0 | K35: =J35*(1+$C35) -> 0 | L35: =K35*(1+$C35) -> 0 | M35: =L35*(1+$C35) -> 0 | N35: =M35*(1+$C35) -> 0 | O35: =N35*(1+$C35) -> 0 | P35: =O35*(0.9) -> 0 | Q35: =P35*(1+$C35) -> 0 | R35: =Q35*(1+$C35) -> 0 | S35: =R35*(1+$C35) -> 0 | T35: =S35*(1+$C35) -> 0 | U35: =T35*(1+$C35) -> 0 | V35: =U35*(1+$C35) -> 0 | W35: =V35*(0.9) -> 0 | X35: =W35*(1+$C35) -> 0 | Y35: =X35*(1+$C35) -> 0 | Z35: =Y35*(1+$C35) -> 0 | AA35: =Z35*(1+$C35) -> 0 | AB35: =AA35*(1+$C35) -> 0 | AC35: =AB35*(1+$C35) -> 0 | AD35: =AC35*(0.9) -> 0 | AE35: =AD35*(0.9) -> 0 | AF35: =AE35*(1+$C35) -> 0 | AG35: =AF35*(1+$C35) -> 0 | AH35: =AG35*(1+$C35) -> 0 | AI35: =AH35*(1+$C35) -> 0 | AJ35: =AI35*(0.9) -> 0 | AK35: =AJ35*(1+$C35) -> 0 | AL35: =AK35*(1+$C35) -> 0 | AM35: =AL35*(1+$C35) -> 0 | AN35: =AM35*(1+$C35) -> 0
B36: Total Payroll Expenses | E36: =SUM(E35, E34, E33, E32, E31 + E30) -> 12510 | F36: =SUM(F35, F34, F33, F32, F31 + F30) -> 12885.3 | G36: =SUM(G35, G34, G33, G32, G31 + G30) -> 11596.77 | H36: =SUM(H35, H34, H33, H32, H31 + H30) -> 11944.673 | I36: =SUM(I35, I34, I33, I32, I31 + I30) -> 12303.013 | J36: =SUM(J35, J34, J33, J32, J31 + J30) -> 12672.104 | K36: =SUM(K35, K34, K33, K32, K31 + K30) -> 13052.267 | L36: =SUM(L35, L34, L33, L32, L31 + L30) -> 13443.835 | ... AN36: =SUM(AN35, AN34, AN33, AN32, AN31 + AN30) -> 15667.218
B37: Taxes & Licenses | C37: 0.03 | E37: 0 | F37: 0 | G37: 0 | H37: 0 | I37: 0 | J37: 0 | K37: 0 | L37: 0 | M37: 0 | N37: 0 | O37: 0 | P37: 0 | Q37: 0 | R37: 0 | S37: 0 | T37: 0 | U37: 0 | V37: 0 | W37: 0 | X37: 0 | Y37: 0 | Z37: 0 | AA37: 0 | AB37: 0 | AC37: 0 | AD37: 0 | AE37: 0 | AF37: 0 | AG37: 0 | AH37: 0 | AI37: 0 | AJ37: 0 | AK37: 0 | AL37: 0 | AM37: 0 | AN37: 0
B38: Travel, Meals & Entertainment | C38: 0.03 | E38: 0 | F38: =E38*(1+$C38) -> 0 | G38: =F38*(1+$C38) -> 0 | H38: =G38*(1+$C38) -> 0 | I38: =H38*(1+$C38) -> 0 | J38: =I38*(1+$C38) -> 0 | K38: =J38*(1+$C38) -> 0 | L38: =K38*(1+$C38) -> 0 | M38: =L38*(1+$C38) -> 0 | ... AN38: =AM38*(1+$C38) -> 0
B39: Lodging | C39: 0.03 | E39: 400 | F39: =E39*(1+$C39) -> 412 | G39: =F39*(1+$C39) -> 424.36 | H39: =G39*(1+$C39) -> 437.0908 | I39: =H39*(1+$C39) -> 450.20352 | J39: =I39*(1+$C39) -> 463.70963 | K39: =J39*(1+$C39) -> 477.62092 | L39: =K39*(1+$C39) -> 491.94955 | M39: =L39*(1+$C39) -> 506.70803 | ... AN39: =AM39*(1+$C39) -> 1125.545
B40: Meals & Entertainment | C40: 0.03 | E40: 250 | F40: =E40*(1+$C40) -> 257.5 | G40: =F40*(1+$C40) -> 265.225 | H40: =G40*(1+$C40) -> 273.18175 | I40: =H40*(1+$C40) -> 281.3772 | J40: =I40*(1+$C40) -> 289.81852 | K40: =J40*(1+$C40) -> 298.51307 | L40: =K40*(1+$C40) -> 307.46847 | M40: =L40*(1+$C40) -> 316.69252 | ... AN40: =AM40*(1+$C40) -> 703.46561
B41: Travel | C41: 0.03 | E41: 250 | F41: =E41*(1+$C41) -> 257.5 | G41: =F41*(1+$C41) -> 265.225 | H41: =G41*(1+$C41) -> 273.18175 | I41: =H41*(1+$C41) -> 281.3772 | J41: =I41*(1+$C41) -> 289.81852 | K41: =J41*(1+$C41) -> 298.51307 | L41: =K41*(1+$C41) -> 307.46847 | M41: =L41*(1+$C41) -> 316.69252 | ... AN41: =AM41*(1+$C41) -> 703.46561
B42: Total Travel, Meals & Entertainment | E42: =SUM(E41, E40, E39 + E38) -> 900 | F42: =E42*(1+$C42) -> 900 | G42: =F42*(1+$C42) -> 900 | H42: =G42*(1+$C42) -> 900 | I42: =H42*(1+$C42) -> 900 | J42: =I42*(1+$C42) -> 900 | K42: =J42*(1+$C42) -> 900 | L42: =K42*(1+$C42) -> 900 | M42: =L42*(1+$C42) -> 900 | ... AN42: =AM42*(1+$C42) -> 900
B43: Total Expenses | E43: =SUM(E41, E40, E39, E38, E37, E35, E34, E33, E32, E31, E30, E28, E27, E26, E25, E24, E22, E21, E20, E19, E18, E17, E16, E15, E14 + E13) -> 19060 | F43: =SUM(F41, F40, F39, F38, F37, F35, F34, F33, F32, F31, F30, F28, F27, F26, F25, F24, F22, F21, F20, F19, F18, F17, F16, F15, F14 + F13) -> 19631.8 | G43: =SUM(G41, G40, G39, G38, G37, G35, G34, G33, G32, G31, G30, G28, G27, G26, G25, G24, G22, G21, G20, G19, G18, G17, G16, G15, G14 + G13) -> 18197.525 | H43: =SUM(H41, H40, H39, H38, H37, H35, H34, H33, H32, H31, H30, H28, H27, H26, H25, H24, H22, H21, H20, H19, H18, H17, H16, H15, H14 + H13) -> 18743.451 | I43: =SUM(I41, I40, I39, I38, I37, I35, I34, I33, I32, I31, I30, I28, I27, I26, I25, I24, I22, I21, I20, I19, I18, I17, I16, I15, I14 + I13) -> 19021.645 | J43: =SUM(J41, J40, J39, J38, J37, J35, J34, J33, J32, J31, J30, J28, J27, J26, J25, J24, J22, J21, J20, J19, J18, J17, J16, J15, J14 + J13) -> 19592.295 | K43: =SUM(K41, K40, K39, K38, K37, K35, K34, K33, K32, K31, K30, K28, K27, K26, K25, K24, K22, K21, K20, K19, K18, K17, K16, K15, K14 + K13) -> 19837.684 | L43: =SUM(L41, L40, L39, L38, L37, L35, L34, L33, L32, L31, L30, L28, L27, L26, L25, L24, L22, L21, L20, L19, L18, L17, L16, L15, L14 + L13) -> 20124.672 | ... AN43: =SUM(AN41, AN40, AN39, AN38, AN37, AN35, AN34, AN33, AN32, AN31, AN30, AN28, AN27, AN26, AN25, AN24, AN22, AN21, AN20, AN19, AN18, AN17, AN16, AN15, AN14 + AN13) -> 24792.105
B44: Net Operating Income | E44: =E12-E43 -> -19060 | F44: =F12-F43 -> -19631.8 | G44: =G12-G43 -> -18197.525 | H44: =H12-H43 -> -18743.451 | I44: =I12-I43 -> -19021.645 | J44: =J12-J43 -> -19592.295 | K44: =K12-K43 -> -19837.684 | L44: =L12-L43 -> -20124.672 | ... AN44: =AN12-AN43 -> -24792.105
B45: Other Income | C45: 0.1
B46: Interest Income | C46: 0.1 | E46: 0 | F46: =E46*(1+$C46) -> 0 | G46: =F46*(1+$C46) -> 0 | H46: =G46*(1+$C46) -> 0 | I46: =H46*(1+$C46) -> 0 | J46: =I46*(1+$C46) -> 0 | K46: =J46*(1+$C46) -> 0 | L46: =K46*(1+$C46) -> 0 | M46: =L46*(1+$C46) -> 0 | ... AN46: =AM46*(1+$C46) -> 0
B47: Total Other Income | E47: =SUM(E46 + E45) -> 0 | F47: =SUM(F46 + F45) -> 0 | G47: =SUM(G46 + G45) -> 0 | H47: =SUM(H46 + H45) -> 0 | I47: =SUM(I46 + I45) -> 0 | J47: =SUM(J46 + J45) -> 0 | K47: =SUM(K46 + K45) -> 0 | L47: =SUM(L46 + L45) -> 0 | ... AN47: =SUM(AN46 + AN45) -> 0
B48: Other Expenses | C48: 0.1
B49: Depreciation Expense | C49: 0.1 | E49: 0 | F49: 0 | G49: 0 | H49: 0 | I49: 0 | J49: 0 | K49: 0 | L49: 0 | M49: 0 | N49: 0 | O49: 0 | P49: 0 | Q49: 0 | R49: 0 | S49: 0 | T49: 0 | U49: 0 | V49: 0 | W49: 0 | X49: 0 | Y49: 0 | Z49: 0 | AA49: 0 | AB49: 0 | AC49: 0 | AD49: 0 | AE49: 0 | AF49: 0 | AG49: 0 | AH49: 0 | AI49: 0 | AJ49: 0 | AK49: 0 | AL49: 0 | AM49: 0 | AN49: 0
B50: Interest Expense | C50: 0.1 | E50: 0 | F50: 0 | G50: 0 | H50: 0 | I50: 0 | J50: 0 | K50: 0 | L50: 0 | M50: 0 | N50: 0 | O50: 0 | P50: 0 | Q50: 0 | R50: 0 | S50: 0 | T50: 0 | U50: 0 | V50: 0 | W50: 0 | X50: 0 | Y50: 0 | Z50: 0 | AA50: 0 | AB50: 0 | AC50: 0 | AD50: 0 | AE50: 0 | AF50: 0 | AG50: 0 | AH50: 0 | AI50: 0 | AJ50: 0 | AK50: 0 | AL50: 0 | AM50: 0 | AN50: 0
B51: Total Other Expenses | E51: =SUM(E50, E49 + E48) -> 0 | F51: =SUM(F50, F49 + F48) -> 0 | G51: =SUM(G50, G49 + G48) -> 0 | H51: =SUM(H50, H49 + H48) -> 0 | I51: =SUM(I50, I49 + I48) -> 0 | J51: =SUM(J50, J49 + J48) -> 0 | K51: =SUM(K50, K49 + K48) -> 0 | L51: =SUM(L50, L49 + L48) -> 0 | ... AN51: =SUM(AN50, AN49 + AN48) -> 0
B52: Net Other Income | E52: =E47-E51 -> 0 | F52: =F47-F51 -> 0 | G52: =G47-G51 -> 0 | H52: =H47-H51 -> 0 | I52: =I47-I51 -> 0 | J52: =J47-J51 -> 0 | K52: =K47-K51 -> 0 | L52: =L47-L51 -> 0 | ... AN52: =AN47-AN51 -> 0
B53: Net Income | E53: =E44+E52 -> -19060 | F53: =F44+F52 -> -19631.8 | G53: =G44+G52 -> -18197.525 | H53: =H44+H52 -> -18743.451 | I53: =I44+I52 -> -19021.645 | J53: =J44+J52 -> -19592.295 | K53: =K44+K52 -> -19837.684 | L53: =L44+L52 -> -20124.672 | ... AN53: =AN44+AN52 -> -24792.105
NSC267: 74
NSC268: 75
NSC269: 76
NSC270: 77
NSC271: 78
NRN272: Value Row | NSC272: 79 | NSE272: Value Row | NTQ272: Value Row
NRN273: Value Row | NSC273: 80 | NSE273: Value Row | NTQ273: Value Row
NRN274: Value Row | NSC274: 81 | NSE274: Value Row | NTQ274: Value Row
NRN275: Value Row | NSC275: 82 | NSE275: Value Row | NTQ275: Value Row
NRN276: Value Row | NSC276: 83 | NSE276: Value Row | NTO276: 74 | NTQ276: Value Row
NRN277: Value Row | NSC277: 84 | NSE277: Value Row | NTO277: 75 | NTQ277: Value Row
NSC278: 85 | NTO278: 76
NRN279: Value Row | NSC279: 86 | NSE279: Value Row | NTO279: 77 | NTQ279: Value Row
NRN280: Value Row | NSC280: 87 | NSE280: Value Row | NTO280: 78 | NTQ280: Value Row
NRN281: Value Row | NSC281: 88 | NSE281: Value Row | NTO281: 79 | NTQ281: Value Row
NRN282: Value Row | NSC282: 89 | NSE282: Value Row | NTO282: 80 | NTQ282: Value Row
NRN283: Value Row | NSC283: 90 | NSE283: Value Row | NTO283: 81 | NTQ283: Value Row
NRN284: Summation Row | NSC284: 91 | NSE284: Summation Row | NTO284: 82 | NTQ284: Summation Row
NSC285: 92 | NTO285: 83
NRN286: Value Row | NSC286: 93 | NSE286: Value Row | NTO286: 84 | NTQ286: Value Row
NRN287: Value Row | NSC287: 94 | NSE287: Value Row | NTO287: 85 | NTQ287: Value Row
NRN288: Value Row | NSE288: Value Row | NTO288: 86 | NTQ288: Value Row
NRN289: Value Row | NSE289: Value Row | NTO289: 87 | NTQ289: Value Row
NRN290: Summation Row | NSE290: Summation Row | NTO290: 88 | NTQ290: Summation Row
NRN291: Value Row | NSE291: Value Row | NTO291: 89 | NTQ291: Value Row
NRN292: Value Row | NSE292: Value Row | NTO292: 90 | NTQ292: Value Row
NRN293: Value Row | NSE293: Value Row | NTO293: 91 | NTQ293: Value Row
NTO294: 92
NRN295: Value Row | NSE295: Value Row | NTO295: 93 | NTQ295: Value Row
NSE296: Value Row | NTO296: 94 | NTQ296: Value Row
NSE297: Summation Row | NTO297: 95 | NTQ297: Summation Row
NTO298: 96
NTO299: 97
NTO300: 98
NTO301: 99
NTO302: 100
NTO303: 101
NTO304: 102

Sheet CS
A1: Income Statement
A2: Your CFO Guy
A3: Customer Support
C4: Growth | E4: 44957 | F4: =EOMONTH(E4,1) -> 44985 | G4: =EOMONTH(F4,1) -> 45016 | H4: =EOMONTH(G4,1) -> 45046 | I4: =EOMONTH(H4,1) -> 45077 | J4: =EOMONTH(I4,1) -> 45107 | K4: =EOMONTH(J4,1) -> 45138 | L4: =EOMONTH(K4,1) -> 45169 | M4: =EOMONTH(L4,1) -> 45199 | ... AN4: =EOMONTH(AM4,1) -> 46022
B5: Revenue
B6: Sales | C6: 0.1 | E6: 0 | F6: 0 | G6: 0 | H6: 0 | I6: 0 | J6: 0 | K6: 0 | L6: 0 | M6: 0 | N6: 0 | O6: 0 | P6: 0 | Q6: 0 | R6: 0 | S6: 0 | T6: 0 | U6: 0 | V6: 0 | W6: 0 | X6: 0 | Y6: 0 | Z6: 0 | AA6: 0 | AB6: 0 | AC6: 0 | AD6: 0 | AE6: 0 | AF6: 0 | AG6: 0 | AH6: 0 | AI6: 0 | AJ6: 0 | AK6: 0 | AL6: 0 | AM6: 0 | AN6: 0
B7: Total Revenue | E7: =SUM(E6 + E5) -> 0 | F7: =SUM(F6 + F5) -> 0 | G7: =SUM(G6 + G5) -> 0 | H7: =SUM(H6 + H5) -> 0 | I7: =SUM(I6 + I5) -> 0 | J7: =SUM(J6 + J5) -> 0 | K7: =SUM(K6 + K5) -> 0 | L7: =SUM(L6 + L5) -> 0 | ... AN7: =SUM(AN6 + AN5) -> 0
B8: Cost of Goods Sold
B9: Web Domain & Hosting Fees | C9: 0.03 | E9: 0 | F9: 0 | G9: 0 | H9: 0 | I9: 0 | J9: 0 | K9: 0 | L9: 0 | M9: 0 | N9: 0 | O9: 0 | P9: 0 | Q9: 0 | R9: 0 | S9: 0 | T9: 0 | U9: 0 | V9: 0 | W9: 0 | X9: 0 | Y9: 0 | Z9: 0 | AA9: 0 | AB9: 0 | AC9: 0 | AD9: 0 | AE9: 0 | AF9: 0 | AG9: 0 | AH9: 0 | AI9: 0 | AJ9: 0 | AK9: 0 | AL9: 0 | AM9: 0 | AN9: 0
B10: Merchant Account Fees | C10: 0.03 | E10: 0 | F10: 0 | G10: 0 | H10: 0 | I10: 0 | J10: 0 | K10: 0 | L10: 0 | M10: 0 | N10: 0 | O10: 0 | P10: 0 | Q10: 0 | R10: 0 | S10: 0 | T10: 0 | U10: 0 | V10: 0 | W10: 0 | X10: 0 | Y10: 0 | Z10: 0 | AA10: 0 | AB10: 0 | AC10: 0 | AD10: 0 | AE10: 0 | AF10: 0 | AG10: 0 | AH10: 0 | AI10: 0 | AJ10: 0 | AK10: 0 | AL10: 0 | AM10: 0 | AN10: 0
B11: Total Cost of Goods Sold | E11: =SUM(E10, E9 + E8) -> 0 | F11: =SUM(F10, F9 + F8) -> 0 | G11: =SUM(G10, G9 + G8) -> 0 | H11: =SUM(H10, H9 + H8) -> 0 | I11: =SUM(I10, I9 + I8) -> 0 | J11: =SUM(J10, J9 + J8) -> 0 | K11: =SUM(K10, K9 + K8) -> 0 | L11: =SUM(L10, L9 + L8) -> 0 | ... AN11: =SUM(AN10, AN9 + AN8) -> 0
B12: Gross Profit | E12: =E7-E11 -> 0 | F12: =F7-F11 -> 0 | G12: =G7-G11 -> 0 | H12: =H7-H11 -> 0 | I12: =I7-I11 -> 0 | J12: =J7-J11 -> 0 | K12: =K7-K11 -> 0 | L12: =L7-L11 -> 0 | ... AN12: =AN7-AN11 -> 0
B13: Expenses
B14: Advertising & Marketing | C14: 0.03 | E14: 0 | F14: 0 | G14: 0 | H14: 0 | I14: 0 | J14: 0 | K14: 0 | L14: 0 | M14: 0 | N14: 0 | O14: 0 | P14: 0 | Q14: 0 | R14: 0 | S14: 0 | T14: 0 | U14: 0 | V14: 0 | W14: 0 | X14: 0 | Y14: 0 | Z14: 0 | AA14: 0 | AB14: 0 | AC14: 0 | AD14: 0 | AE14: 0 | AF14: 0 | AG14: 0 | AH14: 0 | AI14: 0 | AJ14: 0 | AK14: 0 | AL14: 0 | AM14: 0 | AN14: 0
B15: Bank Charges & Fees | C15: 0.03 | E15: 0 | F15: 0 | G15: 0 | H15: 0 | I15: 0 | J15: 0 | K15: 0 | L15: 0 | M15: 0 | N15: 0 | O15: 0 | P15: 0 | Q15: 0 | R15: 0 | S15: 0 | T15: 0 | U15: 0 | V15: 0 | W15: 0 | X15: 0 | Y15: 0 | Z15: 0 | AA15: 0 | AB15: 0 | AC15: 0 | AD15: 0 | AE15: 0 | AF15: 0 | AG15: 0 | AH15: 0 | AI15: 0 | AJ15: 0 | AK15: 0 | AL15: 0 | AM15: 0 | AN15: 0
B16: Conferences & Events | C16: 0.03 | E16: 650 | F16: =E16*(1+$C16) -> 669.5 | G16: =F16*(1+$C16) -> 689.585 | H16: =G16*(0.92) -> 634.4182 | I16: =H16*(1+$C16) -> 653.45075 | J16: =I16*(1+$C16) -> 673.05427 | K16: =J16*(1+$C16) -> 693.2459 | L16: =K16*(1+$C16) -> 714.04327 | M16: =L16*(1+$C16) -> 735.46457 | N16: =M16*(1+$C16) -> 757.52851 | O16: =N16*(1+$C16) -> 780.25436 | P16: =O16*(0.92) -> 717.83401 | Q16: =P16*(1+$C16) -> 739.36904 | R16: =Q16*(1+$C16) -> 761.55011 | S16: =R16*(1+$C16) -> 784.39661 | T16: =S16*(1+$C16) -> 807.92851 | U16: =T16*(1+$C16) -> 832.16636 | V16: =U16*(0.92) -> 765.59305 | W16: =V16*(0.92) -> 704.34561 | X16: =W16*(1+$C16) -> 725.47598 | Y16: =X16*(1+$C16) -> 747.24026 | Z16: =Y16*(0.92) -> 687.46104 | AA16: =Z16*(0.92) -> 632.46415 | AB16: =AA16*(1+$C16) -> 651.43808 | AC16: =AB16*(1+$C16) -> 670.98122 | AD16: =AC16*(0.92) -> 617.30272 | AE16: =AD16*(0.92) -> 567.91851 | AF16: =AE16*(1+$C16) -> 584.95606 | AG16: =AF16*(1+$C16) -> 602.50474 | AH16: =AG16*(1+$C16) -> 620.57988 | AI16: =AH16*(1+$C16) -> 639.19728 | AJ16: =AI16*(1+$C16) -> 658.3732 | AK16: =AJ16*(0.92) -> 605.70334 | AL16: =AK16*(1+$C16) -> 623.87444 | AM16: =AL16*(1+$C16) -> 642.59068 | AN16: =AM16*(1+$C16) -> 661.8684
B17: Software & Apps | C17: 0.03 | E17: 2500 | F17: =E17*(1+$C17) -> 2575 | G17: =F17*(1+$C17) -> 2652.25 | H17: =G17*(1+$C17) -> 2731.8175 | I17: =H17*(0.92) -> 2513.2721 | J17: =I17*(0.92) -> 2312.2103 | K17: =J17*(1+$C17) -> 2381.5766 | L17: =K17*(1+$C17) -> 2453.0239 | M17: =L17*(1+$C17) -> 2526.6147 | N17: =M17*(1+$C17) -> 2602.4131 | O17: =N17*(1+$C17) -> 2680.4855 | P17: =O17*(1+$C17) -> 2760.9001 | Q17: =P17*(1+$C17) -> 2843.7271 | R17: =Q17*(1+$C17) -> 2929.0389 | S17: =R17*(0.92) -> 2694.7158 | T17: =S17*(0.92) -> 2479.1385 | U17: =T17*(1+$C17) -> 2553.5127 | V17: =U17*(1+$C17) -> 2630.118 | W17: =V17*(1+$C17) -> 2709.0216 | X17: =W17*(1+$C17) -> 2790.2922 | Y17: =X17*(1+$C17) -> 2874.001 | Z17: =Y17*(1+$C17) -> 2960.221 | AA17: =Z17*(1+$C17) -> 3049.0276 | AB17: =AA17*(1+$C17) -> 3140.4985 | AC17: =AB17*(0.92) -> 2889.2586 | AD17: =AC17*(0.92) -> 2658.1179 | AE17: =AD17*(1+$C17) -> 2737.8615 | AF17: =AE17*(1+$C17) -> 2819.9973 | AG17: =AF17*(1+$C17) -> 2904.5972 | AH17: =AG17*(1+$C17) -> 2991.7351 | AI17: =AH17*(0.92) -> 2752.3963 | AJ17: =AI17*(1+$C17) -> 2834.9682 | AK17: =AJ17*(1+$C17) -> 2920.0173 | AL17: =AK17*(1+$C17) -> 3007.6178 | AM17: =AL17*(1+$C17) -> 3097.8463 | AN17: =AM17*(1+$C17) -> 3190.7817
B18: Insurance | C18: 0.03 | E18: 0 | F18: 0 | G18: 0 | H18: 0 | I18: 0 | J18: 0 | K18: 0 | L18: 0 | M18: 0 | N18: 0 | O18: 0 | P18: 0 | Q18: 0 | R18: 0 | S18: 0 | T18: 0 | U18: 0 | V18: 0 | W18: 0 | X18: 0 | Y18: 0 | Z18: 0 | AA18: 0 | AB18: 0 | AC18: 0 | AD18: 0 | AE18: 0 | AF18: 0 | AG18: 0 | AH18: 0 | AI18: 0 | AJ18: 0 | AK18: 0 | AL18: 0 | AM18: 0 | AN18: 0
B19: Office Expenses | C19: 0.03 | E19: 0 | F19: =E19*(1+$C19) -> 0 | G19: =F19*(1+$C19) -> 0 | H19: =G19*(1+$C19) -> 0 | I19: =H19*(1+$C19) -> 0 | J19: =I19*(1+$C19) -> 0 | K19: =J19*(1+$C19) -> 0 | L19: =K19*(1+$C19) -> 0 | M19: =L19*(1+$C19) -> 0 | ... AN19: =AM19*(1+$C19) -> 0
B20: Office Supplies | C20: 0.03 | E20: 250 | F20: =E20*(1+$C20) -> 257.5 | G20: =F20*(0.92) -> 236.9 | H20: =G20*(0.92) -> 217.948 | I20: =H20*(1+$C20) -> 224.48644 | J20: =I20*(1+$C20) -> 231.22103 | K20: =J20*(1+$C20) -> 238.15766 | L20: =K20*(1+$C20) -> 245.30239 | M20: =L20*(1+$C20) -> 252.66147 | N20: =M20*(1+$C20) -> 260.24131 | O20: =N20*(1+$C20) -> 268.04855 | P20: =O20*(1+$C20) -> 276.09001 | ... AN20: =AM20*(1+$C20) -> 561.23414
B21: Rent & Lease | C21: 0.03 | E21: 0 | F21: 0 | G21: 0 | H21: 0 | I21: 0 | J21: 0 | K21: 0 | L21: 0 | M21: 0 | N21: 0 | O21: 0 | P21: 0 | Q21: 0 | R21: 0 | S21: 0 | T21: 0 | U21: 0 | V21: 0 | W21: 0 | X21: 0 | Y21: 0 | Z21: 0 | AA21: 0 | AB21: 0 | AC21: 0 | AD21: 0 | AE21: 0 | AF21: 0 | AG21: 0 | AH21: 0 | AI21: 0 | AJ21: 0 | AK21: 0 | AL21: 0 | AM21: 0 | AN21: 0
B22: Utilities | C22: 0.03 | E22: 0 | F22: 0 | G22: 0 | H22: 0 | I22: 0 | J22: 0 | K22: 0 | L22: 0 | M22: 0 | N22: 0 | O22: 0 | P22: 0 | Q22: 0 | R22: 0 | S22: 0 | T22: 0 | U22: 0 | V22: 0 | W22: 0 | X22: 0 | Y22: 0 | Z22: 0 | AA22: 0 | AB22: 0 | AC22: 0 | AD22: 0 | AE22: 0 | AF22: 0 | AG22: 0 | AH22: 0 | AI22: 0 | AJ22: 0 | AK22: 0 | AL22: 0 | AM22: 0 | AN22: 0
B23: Total Office Expenses | E23: =SUM(E22, E21, E20 + E19) -> 250 | F23: =SUM(F22, F21, F20 + F19) -> 257.5 | G23: =SUM(G22, G21, G20 + G19) -> 236.9 | H23: =SUM(H22, H21, H20 + H19) -> 217.948 | I23: =SUM(I22, I21, I20 + I19) -> 224.48644 | J23: =SUM(J22, J21, J20 + J19) -> 231.22103 | K23: =SUM(K22, K21, K20 + K19) -> 238.15766 | L23: =SUM(L22, L21, L20 + L19) -> 245.30239 | ... AN23: =SUM(AN22, AN21, AN20 + AN19) -> 561.23414
B24: Professional Services | E24: 0 | F24: =E24*(1+$C24) -> 0 | G24: =F24*(1+$C24) -> 0 | H24: =G24*(1+$C24) -> 0 | I24: =H24*(1+$C24) -> 0 | J24: =I24*(1+$C24) -> 0 | K24: =J24*(1+$C24) -> 0 | L24: =K24*(1+$C24) -> 0 | M24: =L24*(1+$C24) -> 0 | ... AN24: =AM24*(1+$C24) -> 0
B25: Accounting Fees | C25: 0.03 | E25: 0 | F25: 0 | G25: 0 | H25: 0 | I25: 0 | J25: 0 | K25: 0 | L25: 0 | M25: 0 | N25: 0 | O25: 0 | P25: 0 | Q25: 0 | R25: 0 | S25: 0 | T25: 0 | U25: 0 | V25: 0 | W25: 0 | X25: 0 | Y25: 0 | Z25: 0 | AA25: 0 | AB25: 0 | AC25: 0 | AD25: 0 | AE25: 0 | AF25: 0 | AG25: 0 | AH25: 0 | AI25: 0 | AJ25: 0 | AK25: 0 | AL25: 0 | AM25: 0 | AN25: 0
B26: Consulting Fees | C26: 0.03 | E26: 0 | F26: =E26*(1+$C26) -> 0 | G26: =F26*(1+$C26) -> 0 | H26: =G26*(1+$C26) -> 0 | I26: =H26*(1+$C26) -> 0 | J26: =I26*(1+$C26) -> 0 | K26: =J26*(1+$C26) -> 0 | L26: =K26*(1+$C26) -> 0 | M26: =L26*(1+$C26) -> 0 | ... AN26: =AM26*(1+$C26) -> 0
B27: Legal Fees | C27: 0.03 | E27: 0 | F27: =E27*(1+$C27) -> 0 | G27: =F27*(1+$C27) -> 0 | H27: =G27*(1+$C27) -> 0 | I27: =H27*(1+$C27) -> 0 | J27: =I27*(1+$C27) -> 0 | K27: =J27*(1+$C27) -> 0 | L27: =K27*(1+$C27) -> 0 | M27: =L27*(1+$C27) -> 0 | ... AN27: =AM27*(1+$C27) -> 0
B28: Recruiting Fees | C28: 0.03 | E28: 2000 | F28: =E28*(1+$C28) -> 2060 | G28: =F28*(1+$C28) -> 2121.8 | H28: =G28*(1+$C28) -> 2185.454 | I28: =H28*(1+$C28) -> 2251.0176 | J28: =I28*(1+$C28) -> 2318.5481 | K28: =J28*(1+$C28) -> 2388.1046 | L28: =K28*(1+$C28) -> 2459.7477 | M28: =L28*(0.92) -> 2262.9679 | N28: =M28*(0.92) -> 2081.9305 | O28: =N28*(0.92) -> 1915.376 | P28: =O28*(1+$C28) -> 1972.8373 | Q28: =P28*(1+$C28) -> 2032.0224 | R28: =Q28*(1+$C28) -> 2092.9831 | S28: =R28*(1+$C28) -> 2155.7726 | T28: =S28*(1+$C28) -> 2220.4458 | U28: =T28*(1+$C28) -> 2287.0592 | V28: =U28*(1+$C28) -> 2355.6709 | W28: =V28*(1+$C28) -> 2426.3411 | ... Y28: =X28*(1+$C28) -> 2574.1052 | Z28: =Y28*(0.92) -> 2368.1768 | AA28: =Z28*(0.92) -> 2178.7227 | AB28: =AA28*(1+$C28) -> 2244.0844 | AC28: =AB28*(1+$C28) -> 2311.4069 | AD28: =AC28*(1+$C28) -> 2380.7491 | AE28: =AD28*(1+$C28) -> 2452.1716 | AF28: =AE28*(1+$C28) -> 2525.7367 | AG28: =AF28*(0.92) -> 2323.6778 | AH28: =AG28*(1+$C28) -> 2393.3881 | AI28: =AH28*(1+$C28) -> 2465.1897 | AJ28: =AI28*(1+$C28) -> 2539.1454 | AK28: =AJ28*(1+$C28) -> 2615.3198 | AL28: =AK28*(0.92) -> 2406.0942 | AM28: =AL28*(0.92) -> 2213.6067 | AN28: =AM28*(1+$C28) -> 2280.0149
B29: Total Professional Services | E29: =SUM(E28, E27, E26, E25 + E24) -> 2000 | F29: =SUM(F28, F27, F26, F25 + F24) -> 2060 | G29: =SUM(G28, G27, G26, G25 + G24) -> 2121.8 | H29: =SUM(H28, H27, H26, H25 + H24) -> 2185.454 | I29: =SUM(I28, I27, I26, I25 + I24) -> 2251.0176 | J29: =SUM(J28, J27, J26, J25 + J24) -> 2318.5481 | K29: =SUM(K28, K27, K26, K25 + K24) -> 2388.1046 | L29: =SUM(L28, L27, L26, L25 + L24) -> 2459.7477 | ... AN29: =SUM(AN28, AN27, AN26, AN25 + AN24) -> 2280.0149
B30: Payroll Expenses | C30: 0.03 | E30: 0 | F30: =E30*(1+$C30) -> 0 | G30: =F30*(1+$C30) -> 0 | H30: =G30*(1+$C30) -> 0 | I30: =H30*(1+$C30) -> 0 | J30: =I30*(1+$C30) -> 0 | K30: =J30*(1+$C30) -> 0 | L30: =K30*(1+$C30) -> 0 | M30: =L30*(1+$C30) -> 0 | ... AN30: =AM30*(1+$C30) -> 0
B31: Salary & Wages | C31: 0.03 | E31: 3500 | F31: =E31*(1+$C31) -> 3605 | G31: =F31*(1+$C31) -> 3713.15 | H31: =G31*(0.92) -> 3416.098 | I31: =H31*(0.92) -> 3142.8102 | J31: =I31*(0.92) -> 2891.3853 | K31: =J31*(1+$C31) -> 2978.1269 | L31: =K31*(1+$C31) -> 3067.4707 | M31: =L31*(1+$C31) -> 3159.4948 | N31: =M31*(1+$C31) -> 3254.2797 | O31: =N31*(1+$C31) -> 3351.9081 | P31: =O31*(1+$C31) -> 3452.4653 | Q31: =P31*(1+$C31) -> 3556.0393 | R31: =Q31*(1+$C31) -> 3662.7205 | ... U31: =T31*(1+$C31) -> 4002.3535 | V31: =U31*(0.92) -> 3682.1652 | W31: =V31*(0.92) -> 3387.592 | X31: =W31*(1+$C31) -> 3489.2198 | Y31: =X31*(1+$C31) -> 3593.8964 | Z31: =Y31*(1+$C31) -> 3701.7133 | AA31: =Z31*(0.92) -> 3405.5762 | AB31: =AA31*(0.92) -> 3133.1301 | AC31: =AB31*(1+$C31) -> 3227.124 | AD31: =AC31*(1+$C31) -> 3323.9377 | AE31: =AD31*(1+$C31) -> 3423.6559 | AF31: =AE31*(1+$C31) -> 3526.3655 | AG31: =AF31*(1+$C31) -> 3632.1565 | AH31: =AG31*(1+$C31) -> 3741.1212 | AI31: =AH31*(1+$C31) -> 3853.3548 | AJ31: =AI31*(1+$C31) -> 3968.9555 | ... AN31: =AM31*(1+$C31) -> 4467.0944
B32: Payroll Taxes | C32: 0.03 | E32: 350 | F32: =E32*(1+$C32) -> 360.5 | G32: =F32*(1+$C32) -> 371.315 | H32: =G32*(1+$C32) -> 382.45445 | I32: =H32*(1+$C32) -> 393.92808 | J32: =I32*(1+$C32) -> 405.74593 | K32: =J32*(1+$C32) -> 417.9183 | L32: =K32*(1+$C32) -> 430.45585 | M32: =L32*(1+$C32) -> 443.36953 | ... AN32: =AM32*(1+$C32) -> 984.85186
B33: Health Insurance | C33: 0.03 | E33: 350 | F33: =E33*(1+$C33) -> 360.5 | G33: =F33*(1+$C33) -> 371.315 | H33: =G33*(1+$C33) -> 382.45445 | I33: =H33*(1+$C33) -> 393.92808 | J33: =I33*(1+$C33) -> 405.74593 | K33: =J33*(1+$C33) -> 417.9183 | L33: =K33*(1+$C33) -> 430.45585 | M33: =L33*(1+$C33) -> 443.36953 | ... AN33: =AM33*(1+$C33) -> 984.85186
B34: Payroll Processing Fees | C34: 0.03 | E34: 25 | F34: =E34*(1+$C34) -> 25.75 | G34: =F34*(1+$C34) -> 26.5225 | H34: =G34*(1+$C34) -> 27.318175 | I34: =H34*(1+$C34) -> 28.13772 | J34: =I34*(1+$C34) -> 28.981852 | K34: =J34*(1+$C34) -> 29.851307 | L34: =K34*(1+$C34) -> 30.746847 | M34: =L34*(1+$C34) -> 31.669252 | ... AN34: =AM34*(1+$C34) -> 70.346561
B35: Commissions Expense | C35: 0.03 | E35: 0 | F35: =E35*(1+$C35) -> 0 | G35: =F35*(1+$C35) -> 0 | H35: =G35*(1+$C35) -> 0 | I35: =H35*(1+$C35) -> 0 | J35: =I35*(1+$C35) -> 0 | K35: =J35*(1+$C35) -> 0 | L35: =K35*(1+$C35) -> 0 | M35: =L35*(1+$C35) -> 0 | ... AN35: =AM35*(1+$C35) -> 0
B36: Total Payroll Expenses | E36: =SUM(E35, E34, E33, E32, E31 + E30) -> 4225 | F36: =SUM(F35, F34, F33, F32, F31 + F30) -> 4351.75 | G36: =SUM(G35, G34, G33, G32, G31 + G30) -> 4482.3025 | H36: =SUM(H35, H34, H33, H32, H31 + H30) -> 4208.3251 | I36: =SUM(I35, I34, I33, I32, I31 + I30) -> 3958.804 | J36: =SUM(J35, J34, J33, J32, J31 + J30) -> 3731.8591 | K36: =SUM(K35, K34, K33, K32, K31 + K30) -> 3843.8148 | L36: =SUM(L35, L34, L33, L32, L31 + L30) -> 3959.1293 | ... AN36: =SUM(AN35, AN34, AN33, AN32, AN31 + AN30) -> 6507.1447
B37: Taxes & Licenses | C37: 0.03 | E37: 0 | F37: 0 | G37: 0 | H37: 0 | I37: 0 | J37: 0 | K37: 0 | L37: 0 | M37: 0 | N37: 0 | O37: 0 | P37: 0 | Q37: 0 | R37: 0 | S37: 0 | T37: 0 | U37: 0 | V37: 0 | W37: 0 | X37: 0 | Y37: 0 | Z37: 0 | AA37: 0 | AB37: 0 | AC37: 0 | AD37: 0 | AE37: 0 | AF37: 0 | AG37: 0 | AH37: 0 | AI37: 0 | AJ37: 0 | AK37: 0 | AL37: 0 | AM37: 0 | AN37: 0
B38: Travel, Meals & Entertainment | C38: 0.03 | E38: 0 | F38: =E38*(1+$C38) -> 0 | G38: =F38*(1+$C38) -> 0 | H38: =G38*(1+$C38) -> 0 | I38: =H38*(1+$C38) -> 0 | J38: =I38*(1+$C38) -> 0 | K38: =J38*(1+$C38) -> 0 | L38: =K38*(1+$C38) -> 0 | M38: =L38*(1+$C38) -> 0 | ... AN38: =AM38*(1+$C38) -> 0
B39: Lodging | C39: 0.03 | E39: 300 | F39: =E39*(1+$C39) -> 309 | G39: =F39*(1+$C39) -> 318.27 | H39: =G39*(1+$C39) -> 327.8181 | I39: =H39*(1+$C39) -> 337.65264 | J39: =I39*(1+$C39) -> 347.78222 | K39: =J39*(1+$C39) -> 358.21569 | L39: =K39*(1+$C39) -> 368.96216 | M39: =L39*(1+$C39) -> 380.03102 | ... AN39: =AM39*(1+$C39) -> 844.15874
B40: Meals & Entertainment | C40: 0.03 | E40: 200 | F40: =E40*(0.92) -> 184 | G40: =F40*(0.92) -> 169.28 | H40: =G40*(0.92) -> 155.7376 | I40: =H40*(1+$C40) -> 160.40973 | J40: =I40*(1+$C40) -> 165.22202 | K40: =J40*(1+$C40) -> 170.17868 | L40: =K40*(1+$C40) -> 175.28404 | M40: =L40*(1+$C40) -> 180.54256 | N40: =M40*(1+$C40) -> 185.95884 | O40: =N40*(1+$C40) -> 191.5376 | P40: =O40*(1+$C40) -> 197.28373 | ... AN40: =AM40*(1+$C40) -> 401.03721
B41: Travel | C41: 0.03 | E41: 200 | F41: =E41*(1+$C41) -> 206 | G41: =F41*(1+$C41) -> 212.18 | H41: =G41*(1+$C41) -> 218.5454 | I41: =H41*(1+$C41) -> 225.10176 | J41: =I41*(1+$C41) -> 231.85481 | K41: =J41*(1+$C41) -> 238.81046 | L41: =K41*(1+$C41) -> 245.97477 | M41: =L41*(1+$C41) -> 253.35402 | ... AN41: =AM41*(1+$C41) -> 562.77249
B42: Total Travel, Meals & Entertainment | E42: =SUM(E41, E40, E39 + E38) -> 700 | F42: =E42*(1+$C42) -> 700 | G42: =F42*(1+$C42) -> 700 | H42: =G42*(1+$C42) -> 700 | I42: =H42*(1+$C42) -> 700 | J42: =I42*(1+$C42) -> 700 | K42: =J42*(1+$C42) -> 700 | L42: =K42*(1+$C42) -> 700 | M42: =L42*(1+$C42) -> 700 | ... AN42: =AM42*(1+$C42) -> 700
B43: Total Expenses | E43: =SUM(E41, E40, E39, E38, E37, E35, E34, E33, E32, E31, E30, E28, E27, E26, E25, E24, E22, E21, E20, E19, E18, E17, E16, E15, E14 + E13) -> 10325 | F43: =SUM(F41, F40, F39, F38, F37, F35, F34, F33, F32, F31, F30, F28, F27, F26, F25, F24, F22, F21, F20, F19, F18, F17, F16, F15, F14 + F13) -> 10612.75 | G43: =SUM(G41, G40, G39, G38, G37, G35, G34, G33, G32, G31, G30, G28, G27, G26, G25, G24, G22, G21, G20, G19, G18, G17, G16, G15, G14 + G13) -> 10882.568 | H43: =SUM(H41, H40, H39, H38, H37, H35, H34, H33, H32, H31, H30, H28, H27, H26, H25, H24, H22, H21, H20, H19, H18, H17, H16, H15, H14 + H13) -> 10680.064 | I43: =SUM(I41, I40, I39, I38, I37, I35, I34, I33, I32, I31, I30, I28, I27, I26, I25, I24, I22, I21, I20, I19, I18, I17, I16, I15, I14 + I13) -> 10324.195 | J43: =SUM(J41, J40, J39, J38, J37, J35, J34, J33, J32, J31, J30, J28, J27, J26, J25, J24, J22, J21, J20, J19, J18, J17, J16, J15, J14 + J13) -> 10011.752 | K43: =SUM(K41, K40, K39, K38, K37, K35, K34, K33, K32, K31, K30, K28, K27, K26, K25, K24, K22, K21, K20, K19, K18, K17, K16, K15, K14 + K13) -> 10312.104 | L43: =SUM(L41, L40, L39, L38, L37, L35, L34, L33, L32, L31, L30, L28, L27, L26, L25, L24, L22, L21, L20, L19, L18, L17, L16, L15, L14 + L13) -> 10621.468 | ... AN43: =SUM(AN41, AN40, AN39, AN38, AN37, AN35, AN34, AN33, AN32, AN31, AN30, AN28, AN27, AN26, AN25, AN24, AN22, AN21, AN20, AN19, AN18, AN17, AN16, AN15, AN14 + AN13) -> 15009.012
B44: Net Operating Income | E44: =E12-E43 -> -10325 | F44: =F12-F43 -> -10612.75 | G44: =G12-G43 -> -10882.568 | H44: =H12-H43 -> -10680.064 | I44: =I12-I43 -> -10324.195 | J44: =J12-J43 -> -10011.752 | K44: =K12-K43 -> -10312.104 | L44: =L12-L43 -> -10621.468 | ... AN44: =AN12-AN43 -> -15009.012
B45: Other Income | C45: 0.03
B46: Interest Income | C46: 0.03 | E46: 0 | F46: =E46*(1+$C46) -> 0 | G46: =F46*(1+$C46) -> 0 | H46: =G46*(1+$C46) -> 0 | I46: =H46*(1+$C46) -> 0 | J46: =I46*(1+$C46) -> 0 | K46: =J46*(1+$C46) -> 0 | L46: =K46*(1+$C46) -> 0 | M46: =L46*(1+$C46) -> 0 | ... AN46: =AM46*(1+$C46) -> 0
B47: Total Other Income | E47: =SUM(E46 + E45) -> 0 | F47: =SUM(F46 + F45) -> 0 | G47: =SUM(G46 + G45) -> 0 | H47: =SUM(H46 + H45) -> 0 | I47: =SUM(I46 + I45) -> 0 | J47: =SUM(J46 + J45) -> 0 | K47: =SUM(K46 + K45) -> 0 | L47: =SUM(L46 + L45) -> 0 | ... AN47: =SUM(AN46 + AN45) -> 0
B48: Other Expenses | C48: 0.03
B49: Depreciation Expense | C49: 0.03 | E49: 0 | F49: 0 | G49: 0 | H49: 0 | I49: 0 | J49: 0 | K49: 0 | L49: 0 | M49: 0 | N49: 0 | O49: 0 | P49: 0 | Q49: 0 | R49: 0 | S49: 0 | T49: 0 | U49: 0 | V49: 0 | W49: 0 | X49: 0 | Y49: 0 | Z49: 0 | AA49: 0 | AB49: 0 | AC49: 0 | AD49: 0 | AE49: 0 | AF49: 0 | AG49: 0 | AH49: 0 | AI49: 0 | AJ49: 0 | AK49: 0 | AL49: 0 | AM49: 0 | AN49: 0
B50: Interest Expense | C50: 0.03 | E50: 0 | F50: 0 | G50: 0 | H50: 0 | I50: 0 | J50: 0 | K50: 0 | L50: 0 | M50: 0 | N50: 0 | O50: 0 | P50: 0 | Q50: 0 | R50: 0 | S50: 0 | T50: 0 | U50: 0 | V50: 0 | W50: 0 | X50: 0 | Y50: 0 | Z50: 0 | AA50: 0 | AB50: 0 | AC50: 0 | AD50: 0 | AE50: 0 | AF50: 0 | AG50: 0 | AH50: 0 | AI50: 0 | AJ50: 0 | AK50: 0 | AL50: 0 | AM50: 0 | AN50: 0
B51: Total Other Expenses | E51: =SUM(E50, E49 + E48) -> 0 | F51: =SUM(F50, F49 + F48) -> 0 | G51: =SUM(G50, G49 + G48) -> 0 | H51: =SUM(H50, H49 + H48) -> 0 | I51: =SUM(I50, I49 + I48) -> 0 | J51: =SUM(J50, J49 + J48) -> 0 | K51: =SUM(K50, K49 + K48) -> 0 | L51: =SUM(L50, L49 + L48) -> 0 | ... AN51: =SUM(AN50, AN49 + AN48) -> 0
B52: Net Other Income | E52: =E47-E51 -> 0 | F52: =F47-F51 -> 0 | G52: =G47-G51 -> 0 | H52: =H47-H51 -> 0 | I52: =I47-I51 -> 0 | J52: =J47-J51 -> 0 | K52: =K47-K51 -> 0 | L52: =L47-L51 -> 0 | ... AN52: =AN47-AN51 -> 0
B53: Net Income | E53: =E44+E52 -> -10325 | F53: =F44+F52 -> -10612.75 | G53: =G44+G52 -> -10882.568 | H53: =H44+H52 -> -10680.064 | I53: =I44+I52 -> -10324.195 | J53: =J44+J52 -> -10011.752 | K53: =K44+K52 -> -10312.104 | L53: =L44+L52 -> -10621.468 | ... AN53: =AN44+AN52 -> -15009.012
NSC267: 74
NSC268: 75
NSC269: 76
NSC270: 77
NSC271: 78
NRN272: Value Row | NSC272: 79 | NSE272: Value Row | NTQ272: Value Row
NRN273: Value Row | NSC273: 80 | NSE273: Value Row | NTQ273: Value Row
NRN274: Value Row | NSC274: 81 | NSE274: Value Row | NTQ274: Value Row
NRN275: Value Row | NSC275: 82 | NSE275: Value Row | NTQ275: Value Row
NRN276: Value Row | NSC276: 83 | NSE276: Value Row | NTO276: 74 | NTQ276: Value Row
NRN277: Value Row | NSC277: 84 | NSE277: Value Row | NTO277: 75 | NTQ277: Value Row
NSC278: 85 | NTO278: 76
NRN279: Value Row | NSC279: 86 | NSE279: Value Row | NTO279: 77 | NTQ279: Value Row
NRN280: Value Row | NSC280: 87 | NSE280: Value Row | NTO280: 78 | NTQ280: Value Row
NRN281: Value Row | NSC281: 88 | NSE281: Value Row | NTO281: 79 | NTQ281: Value Row
NRN282: Value Row | NSC282: 89 | NSE282: Value Row | NTO282: 80 | NTQ282: Value Row
NRN283: Value Row | NSC283: 90 | NSE283: Value Row | NTO283: 81 | NTQ283: Value Row
NRN284: Summation Row | NSC284: 91 | NSE284: Summation Row | NTO284: 82 | NTQ284: Summation Row
NSC285: 92 | NTO285: 83
NRN286: Value Row | NSC286: 93 | NSE286: Value Row | NTO286: 84 | NTQ286: Value Row
NRN287: Value Row | NSC287: 94 | NSE287: Value Row | NTO287: 85 | NTQ287: Value Row
NRN288: Value Row | NSE288: Value Row | NTO288: 86 | NTQ288: Value Row
NRN289: Value Row | NSE289: Value Row | NTO289: 87 | NTQ289: Value Row
NRN290: Summation Row | NSE290: Summation Row | NTO290: 88 | NTQ290: Summation Row
NRN291: Value Row | NSE291: Value Row | NTO291: 89 | NTQ291: Value Row
NRN292: Value Row | NSE292: Value Row | NTO292: 90 | NTQ292: Value Row
NRN293: Value Row | NSE293: Value Row | NTO293: 91 | NTQ293: Value Row
NTO294: 92
NRN295: Value Row | NSE295: Value Row | NTO295: 93 | NTQ295: Value Row
NSE296: Value Row | NTO296: 94 | NTQ296: Value Row
NSE297: Summation Row | NTO297: 95 | NTQ297: Summation Row
NTO298: 96
NTO299: 97
NTO300: 98
NTO301: 99
NTO302: 100
NTO303: 101
NTO304: 102

Sheet S&M
A1: Income Statement
A2: Your CFO Guy
A3: Sales & Marketing
C4: Growth | E4: 44957 | F4: =EOMONTH(E4,1) -> 44985 | G4: =EOMONTH(F4,1) -> 45016 | H4: =EOMONTH(G4,1) -> 45046 | I4: =EOMONTH(H4,1) -> 45077 | J4: =EOMONTH(I4,1) -> 45107 | K4: =EOMONTH(J4,1) -> 45138 | L4: =EOMONTH(K4,1) -> 45169 | M4: =EOMONTH(L4,1) -> 45199 | ... AN4: =EOMONTH(AM4,1) -> 46022
B5: Revenue
B6: Sales | C6: 0.1 | E6: 0 | F6: 0 | G6: 0 | H6: 0 | I6: 0 | J6: 0 | K6: 0 | L6: 0 | M6: 0 | N6: 0 | O6: 0 | P6: 0 | Q6: 0 | R6: 0 | S6: 0 | T6: 0 | U6: 0 | V6: 0 | W6: 0 | X6: 0 | Y6: 0 | Z6: 0 | AA6: 0 | AB6: 0 | AC6: 0 | AD6: 0 | AE6: 0 | AF6: 0 | AG6: 0 | AH6: 0 | AI6: 0 | AJ6: 0 | AK6: 0 | AL6: 0 | AM6: 0 | AN6: 0
B7: Total Revenue | E7: =SUM(E6 + E5) -> 0 | F7: =SUM(F6 + F5) -> 0 | G7: =SUM(G6 + G5) -> 0 | H7: =SUM(H6 + H5) -> 0 | I7: =SUM(I6 + I5) -> 0 | J7: =SUM(J6 + J5) -> 0 | K7: =SUM(K6 + K5) -> 0 | L7: =SUM(L6 + L5) -> 0 | ... AN7: =SUM(AN6 + AN5) -> 0
B8: Cost of Goods Sold
B9: Web Domain & Hosting Fees | C9: 0.1 | E9: 0 | F9: 0 | G9: 0 | H9: 0 | I9: 0 | J9: 0 | K9: 0 | L9: 0 | M9: 0 | N9: 0 | O9: 0 | P9: 0 | Q9: 0 | R9: 0 | S9: 0 | T9: 0 | U9: 0 | V9: 0 | W9: 0 | X9: 0 | Y9: 0 | Z9: 0 | AA9: 0 | AB9: 0 | AC9: 0 | AD9: 0 | AE9: 0 | AF9: 0 | AG9: 0 | AH9: 0 | AI9: 0 | AJ9: 0 | AK9: 0 | AL9: 0 | AM9: 0 | AN9: 0
B10: Merchant Account Fees | C10: 0.1 | E10: 0 | F10: 0 | G10: 0 | H10: 0 | I10: 0 | J10: 0 | K10: 0 | L10: 0 | M10: 0 | N10: 0 | O10: 0 | P10: 0 | Q10: 0 | R10: 0 | S10: 0 | T10: 0 | U10: 0 | V10: 0 | W10: 0 | X10: 0 | Y10: 0 | Z10: 0 | AA10: 0 | AB10: 0 | AC10: 0 | AD10: 0 | AE10: 0 | AF10: 0 | AG10: 0 | AH10: 0 | AI10: 0 | AJ10: 0 | AK10: 0 | AL10: 0 | AM10: 0 | AN10: 0
B11: Total Cost of Goods Sold | E11: =SUM(E10, E9 + E8) -> 0 | F11: =SUM(F10, F9 + F8) -> 0 | G11: =SUM(G10, G9 + G8) -> 0 | H11: =SUM(H10, H9 + H8) -> 0 | I11: =SUM(I10, I9 + I8) -> 0 | J11: =SUM(J10, J9 + J8) -> 0 | K11: =SUM(K10, K9 + K8) -> 0 | L11: =SUM(L10, L9 + L8) -> 0 | ... AN11: =SUM(AN10, AN9 + AN8) -> 0
B12: Gross Profit | E12: =E7-E11 -> 0 | F12: =F7-F11 -> 0 | G12: =G7-G11 -> 0 | H12: =H7-H11 -> 0 | I12: =I7-I11 -> 0 | J12: =J7-J11 -> 0 | K12: =K7-K11 -> 0 | L12: =L7-L11 -> 0 | ... AN12: =AN7-AN11 -> 0
B13: Expenses
B14: Advertising & Marketing | C14: 0.03 | E14: 15000 | F14: =E14*(0.85) -> 12750 | G14: =F14*(1+$C14) -> 13132.5 | H14: =G14*(1+$C14) -> 13526.475 | I14: =H14*(1+$C14) -> 13932.269 | J14: =I14*(1+$C14) -> 14350.237 | K14: =J14*(1+$C14) -> 14780.744 | L14: =K14*(1+$C14) -> 15224.167 | M14: =L14*(1+$C14) -> 15680.892 | N14: =M14*(0.85) -> 13328.758 | O14: =N14*(0.85) -> 11329.444 | P14: =O14*(1+$C14) -> 11669.328 | Q14: =P14*(1+$C14) -> 12019.407 | R14: =Q14*(1+$C14) -> 12379.99 | S14: =R14*(1+$C14) -> 12751.389 | T14: =S14*(1+$C14) -> 13133.931 | U14: =T14*(0.85) -> 11163.841 | V14: =U14*(0.85) -> 9489.2652 | W14: =V14*(1+$C14) -> 9773.9432 | X14: =W14*(1+$C14) -> 10067.161 | Y14: =X14*(1+$C14) -> 10369.176 | Z14: =Y14*(1+$C14) -> 10680.252 | AA14: =Z14*(0.85) -> 9078.2138 | AB14: =AA14*(0.85) -> 7716.4818 | AC14: =AB14*(1+$C14) -> 7947.9762 | AD14: =AC14*(1+$C14) -> 8186.4155 | AE14: =AD14*(1+$C14) -> 8432.008 | AF14: =AE14*(0.85) -> 7167.2068 | AG14: =AF14*(0.85) -> 6092.1258 | AH14: =AG14*(1+$C14) -> 6274.8895 | AI14: =AH14*(1+$C14) -> 6463.1362 | AJ14: =AI14*(1+$C14) -> 6657.0303 | AK14: =AJ14*(1+$C14) -> 6856.7412 | AL14: =AK14*(1+$C14) -> 7062.4435 | AM14: =AL14*(0.85) -> 6003.0769 | AN14: =AM14*(0.85) -> 5102.6154
B15: Bank Charges & Fees | C15: 0.03 | E15: 0 | F15: 0 | G15: 0 | H15: 0 | I15: 0 | J15: 0 | K15: 0 | L15: 0 | M15: 0 | N15: 0 | O15: 0 | P15: 0 | Q15: 0 | R15: 0 | S15: 0 | T15: 0 | U15: 0 | V15: 0 | W15: 0 | X15: 0 | Y15: 0 | Z15: 0 | AA15: 0 | AB15: 0 | AC15: 0 | AD15: 0 | AE15: 0 | AF15: 0 | AG15: 0 | AH15: 0 | AI15: 0 | AJ15: 0 | AK15: 0 | AL15: 0 | AM15: 0 | AN15: 0
B16: Conferences & Events | C16: 0.03 | E16: 5000 | F16: =E16*(1+$C16) -> 5150 | G16: =F16*(1+$C16) -> 5304.5 | H16: =G16*(0.9) -> 4774.05 | I16: =H16*(1+$C16) -> 4917.2715 | J16: =I16*(1+$C16) -> 5064.7896 | K16: =J16*(1+$C16) -> 5216.7333 | L16: =K16*(1+$C16) -> 5373.2353 | M16: =L16*(1+$C16) -> 5534.4324 | N16: =M16*(1+$C16) -> 5700.4654 | O16: =N16*(0.9) -> 5130.4188 | P16: =O16*(1+$C16) -> 5284.3314 | Q16: =P16*(1+$C16) -> 5442.8613 | R16: =Q16*(1+$C16) -> 5606.1472 | S16: =R16*(0.9) -> 5045.5325 | T16: =S16*(0.9) -> 4540.9792 | U16: =T16*(1+$C16) -> 4677.2086 | V16: =U16*(1+$C16) -> 4817.5248 | W16: =V16*(1+$C16) -> 4962.0506 | X16: =W16*(0.9) -> 4465.8455 | Y16: =X16*(0.9) -> 4019.261 | Z16: =Y16*(1+$C16) -> 4139.8388 | AA16: =Z16*(1+$C16) -> 4264.034 | AB16: =AA16*(1+$C16) -> 4391.955 | AC16: =AB16*(1+$C16) -> 4523.7136 | AD16: =AC16*(0.9) -> 4071.3423 | AE16: =AD16*(0.9) -> 3664.2081 | AF16: =AE16*(1+$C16) -> 3774.1343 | AG16: =AF16*(1+$C16) -> 3887.3583 | AH16: =AG16*(0.9) -> 3498.6225 | AI16: =AH16*(0.9) -> 3148.7602 | AJ16: =AI16*(1+$C16) -> 3243.223 | AK16: =AJ16*(1+$C16) -> 3340.5197 | AL16: =AK16*(1+$C16) -> 3440.7353 | AM16: =AL16*(0.9) -> 3096.6618 | AN16: =AM16*(1+$C16) -> 3189.5617
B17: Software & Apps | C17: 0.03 | E17: 2500 | F17: =E17*(1+$C17) -> 2575 | G17: =F17*(0.9) -> 2317.5 | H17: =G17*(1+$C17) -> 2387.025 | I17: =H17*(1+$C17) -> 2458.6358 | J17: =I17*(0.9) -> 2212.7722 | K17: =J17*(1+$C17) -> 2279.1553 | L17: =K17*(1+$C17) -> 2347.53 | M17: =L17*(1+$C17) -> 2417.9559 | N17: =M17*(1+$C17) -> 2490.4946 | O17: =N17*(1+$C17) -> 2565.2094 | P17: =O17*(1+$C17) -> 2642.1657 | Q17: =P17*(1+$C17) -> 2721.4307 | R17: =Q17*(1+$C17) -> 2803.0736 | S17: =R17*(0.9) -> 2522.7662 | T17: =S17*(1+$C17) -> 2598.4492 | U17: =T17*(1+$C17) -> 2676.4027 | V17: =U17*(1+$C17) -> 2756.6948 | W17: =V17*(1+$C17) -> 2839.3956 | X17: =W17*(0.9) -> 2555.4561 | Y17: =X17*(0.9) -> 2299.9104 | Z17: =Y17*(1+$C17) -> 2368.9078 | AA17: =Z17*(1+$C17) -> 2439.975 | AB17: =AA17*(1+$C17) -> 2513.1742 | AC17: =AB17*(0.9) -> 2261.8568 | AD17: =AC17*(0.9) -> 2035.6711 | AE17: =AD17*(1+$C17) -> 2096.7413 | AF17: =AE17*(1+$C17) -> 2159.6435 | AG17: =AF17*(1+$C17) -> 2224.4328 | AH17: =AG17*(1+$C17) -> 2291.1658 | AI17: =AH17*(0.9) -> 2062.0492 | AJ17: =AI17*(1+$C17) -> 2123.9107 | AK17: =AJ17*(1+$C17) -> 2187.628 | AL17: =AK17*(1+$C17) -> 2253.2569 | AM17: =AL17*(1+$C17) -> 2320.8546 | AN17: =AM17*(0.9) -> 2088.7691
B18: Insurance | C18: 0.03 | E18: 0 | F18: 0 | G18: 0 | H18: 0 | I18: 0 | J18: 0 | K18: 0 | L18: 0 | M18: 0 | N18: 0 | O18: 0 | P18: 0 | Q18: 0 | R18: 0 | S18: 0 | T18: 0 | U18: 0 | V18: 0 | W18: 0 | X18: 0 | Y18: 0 | Z18: 0 | AA18: 0 | AB18: 0 | AC18: 0 | AD18: 0 | AE18: 0 | AF18: 0 | AG18: 0 | AH18: 0 | AI18: 0 | AJ18: 0 | AK18: 0 | AL18: 0 | AM18: 0 | AN18: 0
B19: Office Expenses | C19: 0.03 | E19: 0 | F19: =E19*(1+$C19) -> 0 | G19: =F19*(1+$C19) -> 0 | H19: =G19*(1+$C19) -> 0 | I19: =H19*(1+$C19) -> 0 | J19: =I19*(1+$C19) -> 0 | K19: =J19*(1+$C19) -> 0 | L19: =K19*(1+$C19) -> 0 | M19: =L19*(1+$C19) -> 0 | ... AN19: =AM19*(1+$C19) -> 0
B20: Office Supplies | C20: 0.03 | E20: 650 | F20: =E20*(1+$C20) -> 669.5 | G20: =F20*(1+$C20) -> 689.585 | H20: =G20*(1+$C20) -> 710.27255 | I20: =H20*(1+$C20) -> 731.58073 | J20: =I20*(1+$C20) -> 753.52815 | K20: =J20*(1+$C20) -> 776.13399 | L20: =K20*(1+$C20) -> 799.41801 | M20: =L20*(1+$C20) -> 823.40055 | ... AN20: =AM20*(1+$C20) -> 1829.0106
B21: Rent & Lease | C21: 0.03 | E21: 0 | F21: 0 | G21: 0 | H21: 0 | I21: 0 | J21: 0 | K21: 0 | L21: 0 | M21: 0 | N21: 0 | O21: 0 | P21: 0 | Q21: 0 | R21: 0 | S21: 0 | T21: 0 | U21: 0 | V21: 0 | W21: 0 | X21: 0 | Y21: 0 | Z21: 0 | AA21: 0 | AB21: 0 | AC21: 0 | AD21: 0 | AE21: 0 | AF21: 0 | AG21: 0 | AH21: 0 | AI21: 0 | AJ21: 0 | AK21: 0 | AL21: 0 | AM21: 0 | AN21: 0
B22: Utilities | C22: 0.03 | E22: 0 | F22: 0 | G22: 0 | H22: 0 | I22: 0 | J22: 0 | K22: 0 | L22: 0 | M22: 0 | N22: 0 | O22: 0 | P22: 0 | Q22: 0 | R22: 0 | S22: 0 | T22: 0 | U22: 0 | V22: 0 | W22: 0 | X22: 0 | Y22: 0 | Z22: 0 | AA22: 0 | AB22: 0 | AC22: 0 | AD22: 0 | AE22: 0 | AF22: 0 | AG22: 0 | AH22: 0 | AI22: 0 | AJ22: 0 | AK22: 0 | AL22: 0 | AM22: 0 | AN22: 0
B23: Total Office Expenses | E23: =SUM(E22, E21, E20 + E19) -> 650 | F23: =SUM(F22, F21, F20 + F19) -> 669.5 | G23: =SUM(G22, G21, G20 + G19) -> 689.585 | H23: =SUM(H22, H21, H20 + H19) -> 710.27255 | I23: =SUM(I22, I21, I20 + I19) -> 731.58073 | J23: =SUM(J22, J21, J20 + J19) -> 753.52815 | K23: =SUM(K22, K21, K20 + K19) -> 776.13399 | L23: =SUM(L22, L21, L20 + L19) -> 799.41801 | ... AN23: =SUM(AN22, AN21, AN20 + AN19) -> 1829.0106
B24: Professional Services | E24: 0 | F24: =E24*(1+$C24) -> 0 | G24: =F24*(1+$C24) -> 0 | H24: =G24*(1+$C24) -> 0 | I24: =H24*(1+$C24) -> 0 | J24: =I24*(1+$C24) -> 0 | K24: =J24*(1+$C24) -> 0 | L24: =K24*(1+$C24) -> 0 | M24: =L24*(1+$C24) -> 0 | ... AN24: =AM24*(1+$C24) -> 0
B25: Accounting Fees | C25: 0.03 | E25: 0 | F25: 0 | G25: 0 | H25: 0 | I25: 0 | J25: 0 | K25: 0 | L25: 0 | M25: 0 | N25: 0 | O25: 0 | P25: 0 | Q25: 0 | R25: 0 | S25: 0 | T25: 0 | U25: 0 | V25: 0 | W25: 0 | X25: 0 | Y25: 0 | Z25: 0 | AA25: 0 | AB25: 0 | AC25: 0 | AD25: 0 | AE25: 0 | AF25: 0 | AG25: 0 | AH25: 0 | AI25: 0 | AJ25: 0 | AK25: 0 | AL25: 0 | AM25: 0 | AN25: 0
B26: Consulting Fees | C26: 0.03 | E26: 0 | F26: =E26*(1+$C26) -> 0 | G26: =F26*(1+$C26) -> 0 | H26: =G26*(1+$C26) -> 0 | I26: =H26*(1+$C26) -> 0 | J26: =I26*(1+$C26) -> 0 | K26: =J26*(1+$C26) -> 0 | L26: =K26*(1+$C26) -> 0 | M26: =L26*(1+$C26) -> 0 | ... AN26: =AM26*(1+$C26) -> 0
B27: Legal Fees | C27: 0.03 | E27: 0 | F27: 0 | G27: 0 | H27: 0 | I27: 0 | J27: 0 | K27: 0 | L27: 0 | M27: 0 | N27: 0 | O27: 0 | P27: 0 | Q27: 0 | R27: 0 | S27: 0 | T27: 0 | U27: 0 | V27: 0 | W27: 0 | X27: 0 | Y27: 0 | Z27: 0 | AA27: 0 | AB27: 0 | AC27: 0 | AD27: 0 | AE27: 0 | AF27: 0 | AG27: 0 | AH27: 0 | AI27: 0 | AJ27: 0 | AK27: 0 | AL27: 0 | AM27: 0 | AN27: 0
B28: Recruiting Fees | C28: 0.03 | E28: 1000 | F28: =E28*(1+$C28) -> 1030 | G28: =F28*(1+$C28) -> 1060.9 | H28: =G28*(1+$C28) -> 1092.727 | I28: =H28*(0.9) -> 983.4543 | J28: =I28*(1+$C28) -> 1012.9579 | K28: =J28*(1+$C28) -> 1043.3467 | L28: =K28*(1+$C28) -> 1074.6471 | M28: =L28*(1+$C28) -> 1106.8865 | N28: =M28*(1+$C28) -> 1140.0931 | O28: =N28*(1+$C28) -> 1174.2959 | P28: =O28*(1+$C28) -> 1209.5247 | Q28: =P28*(1+$C28) -> 1245.8105 | R28: =Q28*(0.9) -> 1121.2294 | S28: =R28*(1+$C28) -> 1154.8663 | T28: =S28*(1+$C28) -> 1189.5123 | U28: =T28*(1+$C28) -> 1225.1977 | V28: =U28*(1+$C28) -> 1261.9536 | W28: =V28*(1+$C28) -> 1299.8122 | X28: =W28*(1+$C28) -> 1338.8066 | Y28: =X28*(1+$C28) -> 1378.9708 | Z28: =Y28*(1+$C28) -> 1420.3399 | AA28: =Z28*(0.9) -> 1278.3059 | AB28: =AA28*(1+$C28) -> 1316.6551 | AC28: =AB28*(1+$C28) -> 1356.1547 | AD28: =AC28*(1+$C28) -> 1396.8394 | AE28: =AD28*(1+$C28) -> 1438.7446 | AF28: =AE28*(1+$C28) -> 1481.9069 | AG28: =AF28*(0.9) -> 1333.7162 | AH28: =AG28*(1+$C28) -> 1373.7277 | AI28: =AH28*(1+$C28) -> 1414.9395 | AJ28: =AI28*(1+$C28) -> 1457.3877 | AK28: =AJ28*(1+$C28) -> 1501.1093 | AL28: =AK28*(1+$C28) -> 1546.1426 | AM28: =AL28*(0.9) -> 1391.5284 | AN28: =AM28*(1+$C28) -> 1433.2742
B29: Total Professional Services | E29: =SUM(E28, E27, E26, E25 + E24) -> 1000 | F29: =SUM(F28, F27, F26, F25 + F24) -> 1030 | G29: =SUM(G28, G27, G26, G25 + G24) -> 1060.9 | H29: =SUM(H28, H27, H26, H25 + H24) -> 1092.727 | I29: =SUM(I28, I27, I26, I25 + I24) -> 983.4543 | J29: =SUM(J28, J27, J26, J25 + J24) -> 1012.9579 | K29: =SUM(K28, K27, K26, K25 + K24) -> 1043.3467 | L29: =SUM(L28, L27, L26, L25 + L24) -> 1074.6471 | ... AN29: =SUM(AN28, AN27, AN26, AN25 + AN24) -> 1433.2742
B30: Payroll Expenses | C30: 0.03 | E30: 0 | F30: =E30*(1+$C30) -> 0 | G30: =F30*(1+$C30) -> 0 | H30: =G30*(1+$C30) -> 0 | I30: =H30*(1+$C30) -> 0 | J30: =I30*(1+$C30) -> 0 | K30: =J30*(1+$C30) -> 0 | L30: =K30*(1+$C30) -> 0 | M30: =L30*(1+$C30) -> 0 | ... AN30: =AM30*(1+$C30) -> 0
B31: Salary & Wages | C31: 0.03 | E31: 15000 | F31: =E31*(1+$C31) -> 15450 | G31: =F31*(0.7) -> 10815 | H31: =G31*(1+$C31) -> 11139.45 | I31: =H31*(1+$C31) -> 11473.634 | J31: =I31*(1+$C31) -> 11817.843 | K31: =J31*(1+$C31) -> 12172.378 | L31: =K31*(1+$C31) -> 12537.549 | M31: =L31*(1+$C31) -> 12913.676 | N31: =M31*(0.7) -> 9039.5729 | O31: =N31*(1+$C31) -> 9310.7601 | P31: =O31*(1+$C31) -> 9590.0829 | Q31: =P31*(1+$C31) -> 9877.7854 | R31: =Q31*(1+$C31) -> 10174.119 | S31: =R31*(1+$C31) -> 10479.343 | T31: =S31*(1+$C31) -> 10793.723 | U31: =T31*(1+$C31) -> 11117.534 | V31: =U31*(1+$C31) -> 11451.061 | W31: =V31*(1+$C31) -> 11794.592 | X31: =W31*(0.7) -> 8256.2146 | Y31: =X31*(1+$C31) -> 8503.9011 | Z31: =Y31*(1+$C31) -> 8759.0181 | AA31: =Z31*(1+$C31) -> 9021.7886 | AB31: =AA31*(1+$C31) -> 9292.4423 | AC31: =AB31*(1+$C31) -> 9571.2156 | AD31: =AC31*(1+$C31) -> 9858.352 | AE31: =AD31*(1+$C31) -> 10154.103 | AF31: =AE31*(1+$C31) -> 10458.726 | ... AH31: =AG31*(1+$C31) -> 11095.662 | AI31: =AH31*(0.7) -> 7766.9635 | AJ31: =AI31*(1+$C31) -> 7999.9724 | AK31: =AJ31*(1+$C31) -> 8239.9715 | AL31: =AK31*(1+$C31) -> 8487.1707 | AM31: =AL31*(1+$C31) -> 8741.7858 | AN31: =AM31*(0.7) -> 6119.2501
B32: Payroll Taxes | C32: 0.03 | E32: 1500 | F32: =E32*(1+$C32) -> 1545 | G32: =F32*(1+$C32) -> 1591.35 | H32: =G32*(1+$C32) -> 1639.0905 | I32: =H32*(0.7) -> 1147.3634 | J32: =I32*(1+$C32) -> 1181.7843 | K32: =J32*(1+$C32) -> 1217.2378 | L32: =K32*(1+$C32) -> 1253.7549 | M32: =L32*(1+$C32) -> 1291.3676 | N32: =M32*(0.7) -> 903.95729 | O32: =N32*(1+$C32) -> 931.07601 | P32: =O32*(1+$C32) -> 959.00829 | Q32: =P32*(1+$C32) -> 987.77854 | R32: =Q32*(1+$C32) -> 1017.4119 | S32: =R32*(1+$C32) -> 1047.9343 | T32: =S32*(1+$C32) -> 1079.3723 | U32: =T32*(0.7) -> 755.5606 | V32: =U32*(1+$C32) -> 778.22741 | W32: =V32*(1+$C32) -> 801.57424 | X32: =W32*(0.7) -> 561.10197 | Y32: =X32*(1+$C32) -> 577.93502 | Z32: =Y32*(1+$C32) -> 595.27307 | AA32: =Z32*(1+$C32) -> 613.13127 | AB32: =AA32*(1+$C32) -> 631.52521 | AC32: =AB32*(1+$C32) -> 650.47096 | AD32: =AC32*(1+$C32) -> 669.98509 | AE32: =AD32*(1+$C32) -> 690.08464 | AF32: =AE32*(1+$C32) -> 710.78718 | ... AN32: =AM32*(1+$C32) -> 900.40394
B33: Health Insurance | C33: 0.03 | E33: 1450 | F33: =E33*(1+$C33) -> 1493.5 | G33: =F33*(1+$C33) -> 1538.305 | H33: =G33*(1+$C33) -> 1584.4542 | I33: =H33*(1+$C33) -> 1631.9878 | J33: =I33*(1+$C33) -> 1680.9474 | K33: =J33*(0.7) -> 1176.6632 | L33: =K33*(1+$C33) -> 1211.9631 | M33: =L33*(1+$C33) -> 1248.322 | N33: =M33*(1+$C33) -> 1285.7716 | O33: =N33*(1+$C33) -> 1324.3448 | P33: =O33*(0.7) -> 927.04135 | Q33: =P33*(1+$C33) -> 954.85259 | R33: =Q33*(1+$C33) -> 983.49817 | S33: =R33*(1+$C33) -> 1013.0031 | T33: =S33*(1+$C33) -> 1043.3932 | U33: =T33*(0.7) -> 730.37524 | V33: =U33*(1+$C33) -> 752.2865 | W33: =V33*(1+$C33) -> 774.85509 | X33: =W33*(1+$C33) -> 798.10075 | Y33: =X33*(0.7) -> 558.67052 | Z33: =Y33*(1+$C33) -> 575.43064 | AA33: =Z33*(1+$C33) -> 592.69356 | AB33: =AA33*(1+$C33) -> 610.47436 | AC33: =AB33*(1+$C33) -> 628.7886 | AD33: =AC33*(1+$C33) -> 647.65225 | AE33: =AD33*(1+$C33) -> 667.08182 | AF33: =AE33*(1+$C33) -> 687.09428 | AG33: =AF33*(1+$C33) -> 707.7071 | ... AN33: =AM33*(1+$C33) -> 870.39047
B34: Payroll Processing Fees | C34: 0.03 | E34: 50 | F34: =E34*(1+$C34) -> 51.5 | G34: =F34*(1+$C34) -> 53.045 | H34: =G34*(1+$C34) -> 54.63635 | I34: =H34*(1+$C34) -> 56.275441 | J34: =I34*(1+$C34) -> 57.963704 | K34: =J34*(1+$C34) -> 59.702615 | L34: =K34*(1+$C34) -> 61.493693 | M34: =L34*(1+$C34) -> 63.338504 | ... AN34: =AM34*(1+$C34) -> 140.69312
B35: Commissions Expense | C35: 0.03 | E35: 0 | F35: =E35*(1+$C35) -> 0 | G35: =F35*(1+$C35) -> 0 | H35: =G35*(1+$C35) -> 0 | I35: =H35*(1+$C35) -> 0 | J35: =I35*(1+$C35) -> 0 | K35: =J35*(1+$C35) -> 0 | L35: =K35*(1+$C35) -> 0 | M35: =L35*(1+$C35) -> 0 | ... AN35: =AM35*(1+$C35) -> 0
B36: Total Payroll Expenses | E36: =SUM(E35, E34, E33, E32, E31 + E30) -> 18000 | F36: =SUM(F35, F34, F33, F32, F31 + F30) -> 18540 | G36: =SUM(G35, G34, G33, G32, G31 + G30) -> 13997.7 | H36: =SUM(H35, H34, H33, H32, H31 + H30) -> 14417.631 | I36: =SUM(I35, I34, I33, I32, I31 + I30) -> 14309.26 | J36: =SUM(J35, J34, J33, J32, J31 + J30) -> 14738.538 | K36: =SUM(K35, K34, K33, K32, K31 + K30) -> 14625.981 | L36: =SUM(L35, L34, L33, L32, L31 + L30) -> 15064.761 | ... AN36: =SUM(AN35, AN34, AN33, AN32, AN31 + AN30) -> 8030.7376
B37: Taxes & Licenses | C37: 0.03 | E37: 0 | F37: 0 | G37: 0 | H37: 0 | I37: 0 | J37: 0 | K37: 0 | L37: 0 | M37: 0 | N37: 0 | O37: 0 | P37: 0 | Q37: 0 | R37: 0 | S37: 0 | T37: 0 | U37: 0 | V37: 0 | W37: 0 | X37: 0 | Y37: 0 | Z37: 0 | AA37: 0 | AB37: 0 | AC37: 0 | AD37: 0 | AE37: 0 | AF37: 0 | AG37: 0 | AH37: 0 | AI37: 0 | AJ37: 0 | AK37: 0 | AL37: 0 | AM37: 0 | AN37: 0
B38: Travel, Meals & Entertainment | C38: 0.03 | E38: 0 | F38: =E38*(1+$C38) -> 0 | G38: =F38*(1+$C38) -> 0 | H38: =G38*(1+$C38) -> 0 | I38: =H38*(1+$C38) -> 0 | J38: =I38*(1+$C38) -> 0 | K38: =J38*(1+$C38) -> 0 | L38: =K38*(1+$C38) -> 0 | M38: =L38*(1+$C38) -> 0 | ... AN38: =AM38*(1+$C38) -> 0
B39: Lodging | C39: 0.03 | E39: 850 | F39: =E39*(1+$C39) -> 875.5 | G39: =F39*(1+$C39) -> 901.765 | H39: =G39*(1+$C39) -> 928.81795 | I39: =H39*(1+$C39) -> 956.68249 | J39: =I39*(1+$C39) -> 985.38296 | K39: =J39*(1+$C39) -> 1014.9445 | L39: =K39*(1+$C39) -> 1045.3928 | M39: =L39*(1+$C39) -> 1076.7546 | ... AN39: =AM39*(1+$C39) -> 2391.7831
B40: Meals & Entertainment | C40: 0.03 | E40: 600 | F40: =E40*(1+$C40) -> 618 | G40: =F40*(1+$C40) -> 636.54 | H40: =G40*(1+$C40) -> 655.6362 | I40: =H40*(1+$C40) -> 675.30529 | J40: =I40*(1+$C40) -> 695.56444 | K40: =J40*(1+$C40) -> 716.43138 | L40: =K40*(1+$C40) -> 737.92432 | M40: =L40*(1+$C40) -> 760.06205 | ... AN40: =AM40*(1+$C40) -> 1688.3175
B41: Travel | C41: 0.03 | E41: 250 | F41: =E41*(1+$C41) -> 257.5 | G41: =F41*(1+$C41) -> 265.225 | H41: =G41*(1+$C41) -> 273.18175 | I41: =H41*(1+$C41) -> 281.3772 | J41: =I41*(1+$C41) -> 289.81852 | K41: =J41*(1+$C41) -> 298.51307 | L41: =K41*(1+$C41) -> 307.46847 | M41: =L41*(1+$C41) -> 316.69252 | ... AN41: =AM41*(1+$C41) -> 703.46561
B42: Total Travel, Meals & Entertainment | E42: =SUM(E41, E40, E39 + E38) -> 1700 | F42: =E42*(1+$C42) -> 1700 | G42: =F42*(1+$C42) -> 1700 | H42: =G42*(1+$C42) -> 1700 | I42: =H42*(1+$C42) -> 1700 | J42: =I42*(1+$C42) -> 1700 | K42: =J42*(1+$C42) -> 1700 | L42: =K42*(1+$C42) -> 1700 | M42: =L42*(1+$C42) -> 1700 | ... AN42: =AM42*(1+$C42) -> 1700
B43: Total Expenses | E43: =SUM(E41, E40, E39, E38, E37, E35, E34, E33, E32, E31, E30, E28, E27, E26, E25, E24, E22, E21, E20, E19, E18, E17, E16, E15, E14 + E13) -> 43850 | F43: =SUM(F41, F40, F39, F38, F37, F35, F34, F33, F32, F31, F30, F28, F27, F26, F25, F24, F22, F21, F20, F19, F18, F17, F16, F15, F14 + F13) -> 42465.5 | G43: =SUM(G41, G40, G39, G38, G37, G35, G34, G33, G32, G31, G30, G28, G27, G26, G25, G24, G22, G21, G20, G19, G18, G17, G16, G15, G14 + G13) -> 38306.215 | H43: =SUM(H41, H40, H39, H38, H37, H35, H34, H33, H32, H31, H30, H28, H27, H26, H25, H24, H22, H21, H20, H19, H18, H17, H16, H15, H14 + H13) -> 38765.816 | I43: =SUM(I41, I40, I39, I38, I37, I35, I34, I33, I32, I31, I30, I28, I27, I26, I25, I24, I22, I21, I20, I19, I18, I17, I16, I15, I14 + I13) -> 39245.837 | J43: =SUM(J41, J40, J39, J38, J37, J35, J34, J33, J32, J31, J30, J28, J27, J26, J25, J24, J22, J21, J20, J19, J18, J17, J16, J15, J14 + J13) -> 40103.589 | K43: =SUM(K41, K40, K39, K38, K37, K35, K34, K33, K32, K31, K30, K28, K27, K26, K25, K24, K22, K21, K20, K19, K18, K17, K16, K15, K14 + K13) -> 40751.984 | L43: =SUM(L41, L40, L39, L38, L37, L35, L34, L33, L32, L31, L30, L28, L27, L26, L25, L24, L22, L21, L20, L19, L18, L17, L16, L15, L14 + L13) -> 41974.544 | ... AN43: =SUM(AN41, AN40, AN39, AN38, AN37, AN35, AN34, AN33, AN32, AN31, AN30, AN28, AN27, AN26, AN25, AN24, AN22, AN21, AN20, AN19, AN18, AN17, AN16, AN15, AN14 + AN13) -> 26457.535
B44: Net Operating Income | E44: =E12-E43 -> -43850 | F44: =F12-F43 -> -42465.5 | G44: =G12-G43 -> -38306.215 | H44: =H12-H43 -> -38765.816 | I44: =I12-I43 -> -39245.837 | J44: =J12-J43 -> -40103.589 | K44: =K12-K43 -> -40751.984 | L44: =L12-L43 -> -41974.544 | ... AN44: =AN12-AN43 -> -26457.535
B45: Other Income | C45: 0.1
B46: Interest Income | C46: 0.1 | E46: 0 | F46: =E46*(1+$C46) -> 0 | G46: =F46*(1+$C46) -> 0 | H46: =G46*(1+$C46) -> 0 | I46: =H46*(1+$C46) -> 0 | J46: =I46*(1+$C46) -> 0 | K46: =J46*(1+$C46) -> 0 | L46: =K46*(1+$C46) -> 0 | M46: =L46*(1+$C46) -> 0 | ... AN46: =AM46*(1+$C46) -> 0
B47: Total Other Income | E47: =SUM(E46 + E45) -> 0 | F47: =SUM(F46 + F45) -> 0 | G47: =SUM(G46 + G45) -> 0 | H47: =SUM(H46 + H45) -> 0 | I47: =SUM(I46 + I45) -> 0 | J47: =SUM(J46 + J45) -> 0 | K47: =SUM(K46 + K45) -> 0 | L47: =SUM(L46 + L45) -> 0 | ... AN47: =SUM(AN46 + AN45) -> 0
B48: Other Expenses | C48: 0.1
B49: Depreciation Expense | C49: 0.1 | E49: 0 | F49: 0 | G49: 0 | H49: 0 | I49: 0 | J49: 0 | K49: 0 | L49: 0 | M49: 0 | N49: 0 | O49: 0 | P49: 0 | Q49: 0 | R49: 0 | S49: 0 | T49: 0 | U49: 0 | V49: 0 | W49: 0 | X49: 0 | Y49: 0 | Z49: 0 | AA49: 0 | AB49: 0 | AC49: 0 | AD49: 0 | AE49: 0 | AF49: 0 | AG49: 0 | AH49: 0 | AI49: 0 | AJ49: 0 | AK49: 0 | AL49: 0 | AM49: 0 | AN49: 0
B50: Interest Expense | C50: 0.1 | E50: 0 | F50: 0 | G50: 0 | H50: 0 | I50: 0 | J50: 0 | K50: 0 | L50: 0 | M50: 0 | N50: 0 | O50: 0 | P50: 0 | Q50: 0 | R50: 0 | S50: 0 | T50: 0 | U50: 0 | V50: 0 | W50: 0 | X50: 0 | Y50: 0 | Z50: 0 | AA50: 0 | AB50: 0 | AC50: 0 | AD50: 0 | AE50: 0 | AF50: 0 | AG50: 0 | AH50: 0 | AI50: 0 | AJ50: 0 | AK50: 0 | AL50: 0 | AM50: 0 | AN50: 0
B51: Total Other Expenses | E51: =SUM(E50, E49 + E48) -> 0 | F51: =SUM(F50, F49 + F48) -> 0 | G51: =SUM(G50, G49 + G48) -> 0 | H51: =SUM(H50, H49 + H48) -> 0 | I51: =SUM(I50, I49 + I48) -> 0 | J51: =SUM(J50, J49 + J48) -> 0 | K51: =SUM(K50, K49 + K48) -> 0 | L51: =SUM(L50, L49 + L48) -> 0 | ... AN51: =SUM(AN50, AN49 + AN48) -> 0
B52: Net Other Income | E52: =E47-E51 -> 0 | F52: =F47-F51 -> 0 | G52: =G47-G51 -> 0 | H52: =H47-H51 -> 0 | I52: =I47-I51 -> 0 | J52: =J47-J51 -> 0 | K52: =K47-K51 -> 0 | L52: =L47-L51 -> 0 | ... AN52: =AN47-AN51 -> 0
B53: Net Income | E53: =E44+E52 -> -43850 | F53: =F44+F52 -> -42465.5 | G53: =G44+G52 -> -38306.215 | H53: =H44+H52 -> -38765.816 | I53: =I44+I52 -> -39245.837 | J53: =J44+J52 -> -40103.589 | K53: =K44+K52 -> -40751.984 | L53: =L44+L52 -> -41974.544 | ... AN53: =AN44+AN52 -> -26457.535
NSC267: 74
NSC268: 75
NSC269: 76
NSC270: 77
NSC271: 78
NRN272: Value Row | NSC272: 79 | NSE272: Value Row | NTQ272: Value Row
NRN273: Value Row | NSC273: 80 | NSE273: Value Row | NTQ273: Value Row
NRN274: Value Row | NSC274: 81 | NSE274: Value Row | NTQ274: Value Row
NRN275: Value Row | NSC275: 82 | NSE275: Value Row | NTQ275: Value Row
NRN276: Value Row | NSC276: 83 | NSE276: Value Row | NTO276: 74 | NTQ276: Value Row
NRN277: Value Row | NSC277: 84 | NSE277: Value Row | NTO277: 75 | NTQ277: Value Row
NSC278: 85 | NTO278: 76
NRN279: Value Row | NSC279: 86 | NSE279: Value Row | NTO279: 77 | NTQ279: Value Row
NRN280: Value Row | NSC280: 87 | NSE280: Value Row | NTO280: 78 | NTQ280: Value Row
NRN281: Value Row | NSC281: 88 | NSE281: Value Row | NTO281: 79 | NTQ281: Value Row
NRN282: Value Row | NSC282: 89 | NSE282: Value Row | NTO282: 80 | NTQ282: Value Row
NRN283: Value Row | NSC283: 90 | NSE283: Value Row | NTO283: 81 | NTQ283: Value Row
NRN284: Summation Row | NSC284: 91 | NSE284: Summation Row | NTO284: 82 | NTQ284: Summation Row
NSC285: 92 | NTO285: 83
NRN286: Value Row | NSC286: 93 | NSE286: Value Row | NTO286: 84 | NTQ286: Value Row
NRN287: Value Row | NSC287: 94 | NSE287: Value Row | NTO287: 85 | NTQ287: Value Row
NRN288: Value Row | NSE288: Value Row | NTO288: 86 | NTQ288: Value Row
NRN289: Value Row | NSE289: Value Row | NTO289: 87 | NTQ289: Value Row
NRN290: Summation Row | NSE290: Summation Row | NTO290: 88 | NTQ290: Summation Row
NRN291: Value Row | NSE291: Value Row | NTO291: 89 | NTQ291: Value Row
NRN292: Value Row | NSE292: Value Row | NTO292: 90 | NTQ292: Value Row
NRN293: Value Row | NSE293: Value Row | NTO293: 91 | NTQ293: Value Row
NTO294: 92
NRN295: Value Row | NSE295: Value Row | NTO295: 93 | NTQ295: Value Row
NSE296: Value Row | NTO296: 94 | NTQ296: Value Row
NSE297: Summation Row | NTO297: 95 | NTQ297: Summation Row
NTO298: 96
NTO299: 97
NTO300: 98
NTO301: 99
NTO302: 100
NTO303: 101
NTO304: 102

Sheet G&A_Budget
A1: Income Statement
A2: Your CFO Guy
A3: General & Admnistrative
C4: Growth | E4: 44957 | F4: =EOMONTH(E4,1) -> 44985 | G4: =EOMONTH(F4,1) -> 45016 | H4: =EOMONTH(G4,1) -> 45046 | I4: =EOMONTH(H4,1) -> 45077 | J4: =EOMONTH(I4,1) -> 45107 | K4: =EOMONTH(J4,1) -> 45138 | L4: =EOMONTH(K4,1) -> 45169 | M4: =EOMONTH(L4,1) -> 45199 | ... AN4: =EOMONTH(AM4,1) -> 46022
B5: Revenue
B6: Sales | C6: 0.03 | E6: 95000 | F6: =E6*(1+$C6) -> 97850 | G6: =F6*(0.96) -> 93936 | H6: =G6*(1+$C6) -> 96754.08 | I6: =H6*(1+$C6) -> 99656.702 | J6: =I6*(1+$C6) -> 102646.4 | K6: =J6*(1+$C6) -> 105725.8 | L6: =K6*(0.96) -> 101496.76 | M6: =L6*(1+$C6) -> 104541.67 | N6: =M6*(1+$C6) -> 107677.92 | O6: =N6*(1+$C6) -> 110908.25 | P6: =O6*(0.96) -> 106471.92 | Q6: =P6*(1+$C6) -> 109666.08 | R6: =Q6*(1+$C6) -> 112956.06 | S6: =R6*(1+$C6) -> 116344.75 | T6: =S6*(0.96) -> 111690.96 | U6: =T6*(1+$C6) -> 115041.68 | V6: =U6*(1+$C6) -> 118492.94 | W6: =V6*(1+$C6) -> 122047.72 | X6: =W6*(1+$C6) -> 125709.16 | Y6: =X6*(1+$C6) -> 129480.43 | Z6: =Y6*(1+$C6) -> 133364.84 | AA6: =Z6*(1+$C6) -> 137365.79 | AB6: =AA6*(0.96) -> 131871.16 | AC6: =AB6*(1+$C6) -> 135827.29 | AD6: =AC6*(1+$C6) -> 139902.11 | AE6: =AD6*(1+$C6) -> 144099.17 | AF6: =AE6*(0.96) -> 138335.21 | AG6: =AF6*(1+$C6) -> 142485.26 | AH6: =AG6*(1+$C6) -> 146759.82 | AI6: =AH6*(0.96) -> 140889.43 | AJ6: =AI6*(1+$C6) -> 145116.11 | AK6: =AJ6*(1+$C6) -> 149469.59 | AL6: =AK6*(1+$C6) -> 153953.68 | AM6: =AL6*(0.96) -> 147795.53 | AN6: =AM6*(1+$C6) -> 152229.4
B7: Total Revenue | E7: =SUM(E6 + E5) -> 95000 | F7: =SUM(F6 + F5) -> 97850 | G7: =SUM(G6 + G5) -> 93936 | H7: =SUM(H6 + H5) -> 96754.08 | I7: =SUM(I6 + I5) -> 99656.702 | J7: =SUM(J6 + J5) -> 102646.4 | K7: =SUM(K6 + K5) -> 105725.8 | L7: =SUM(L6 + L5) -> 101496.76 | ... AN7: =SUM(AN6 + AN5) -> 152229.4
B8: Cost of Goods Sold
B9: Web Domain & Hosting Fees | C9: 0.04 | E9: 800 | F9: =E9*(1+$C9) -> 832 | G9: =F9*(1+$C9) -> 865.28 | H9: =G9*(1+$C9) -> 899.8912 | I9: =H9*(1+$C9) -> 935.88685 | J9: =I9*(1+$C9) -> 973.32232 | K9: =J9*(1+$C9) -> 1012.2552 | L9: =K9*(1+$C9) -> 1052.7454 | M9: =L9*(1+$C9) -> 1094.8552 | ... AN9: =AM9*(1+$C9) -> 3156.8712
B10: Merchant Account Fees | C10: 0.04 | E10: 250 | F10: =E10*(1+$C10) -> 260 | G10: =F10*(1+$C10) -> 270.4 | H10: =G10*(1+$C10) -> 281.216 | I10: =H10*(1+$C10) -> 292.46464 | J10: =I10*(1+$C10) -> 304.16323 | K10: =J10*(1+$C10) -> 316.32975 | L10: =K10*(1+$C10) -> 328.98294 | M10: =L10*(1+$C10) -> 342.14226 | ... AN10: =AM10*(1+$C10) -> 986.52225
B11: Total Cost of Goods Sold | E11: =SUM(E10, E9 + E8) -> 1050 | F11: =SUM(F10, F9 + F8) -> 1092 | G11: =SUM(G10, G9 + G8) -> 1135.68 | H11: =SUM(H10, H9 + H8) -> 1181.1072 | I11: =SUM(I10, I9 + I8) -> 1228.3515 | J11: =SUM(J10, J9 + J8) -> 1277.4855 | K11: =SUM(K10, K9 + K8) -> 1328.585 | L11: =SUM(L10, L9 + L8) -> 1381.7284 | ... AN11: =SUM(AN10, AN9 + AN8) -> 4143.3934
B12: Gross Profit | E12: =E7-E11 -> 93950 | F12: =F7-F11 -> 96758 | G12: =G7-G11 -> 92800.32 | H12: =H7-H11 -> 95572.973 | I12: =I7-I11 -> 98428.351 | J12: =J7-J11 -> 101368.92 | K12: =K7-K11 -> 104397.21 | L12: =L7-L11 -> 100115.04 | ... AN12: =AN7-AN11 -> 148086.01
B13: Expenses
B14: Advertising & Marketing | C14: 0.04 | E14: 0 | F14: 0 | G14: 0 | H14: 0 | I14: 0 | J14: 0 | K14: 0 | L14: 0 | M14: 0 | N14: 0 | O14: 0 | P14: 0 | Q14: 0 | R14: 0 | S14: 0 | T14: 0 | U14: 0 | V14: 0 | W14: 0 | X14: 0 | Y14: 0 | Z14: 0 | AA14: 0 | AB14: 0 | AC14: 0 | AD14: 0 | AE14: 0 | AF14: 0 | AG14: 0 | AH14: 0 | AI14: 0 | AJ14: 0 | AK14: 0 | AL14: 0 | AM14: 0 | AN14: 0
B15: Bank Charges & Fees | C15: 0.04 | E15: 350 | F15: =E15*(1+$C15) -> 364 | G15: =F15*(1+$C15) -> 378.56 | H15: =G15*(1+$C15) -> 393.7024 | I15: =H15*(1+$C15) -> 409.4505 | J15: =I15*(1+$C15) -> 425.82852 | K15: =J15*(1+$C15) -> 442.86166 | L15: =K15*(1+$C15) -> 460.57612 | M15: =L15*(1+$C15) -> 478.99917 | ... AN15: =AM15*(1+$C15) -> 1381.1311
B16: Conferences & Events | C16: 0.05 | E16: 8000 | F16: =E16*(1+$C16) -> 8400 | G16: =F16*(0.95) -> 7980 | H16: =G16*(1+$C16) -> 8379 | I16: =H16*(1+$C16) -> 8797.95 | J16: =I16*(1+$C16) -> 9237.8475 | K16: =J16*(0.95) -> 8775.9551 | L16: =K16*(0.95) -> 8337.1574 | M16: =L16*(1+$C16) -> 8754.0152 | N16: =M16*(1+$C16) -> 9191.716 | O16: =N16*(0.95) -> 8732.1302 | P16: =O16*(0.95) -> 8295.5237 | Q16: =P16*(1+$C16) -> 8710.2999 | R16: =Q16*(1+$C16) -> 9145.8149 | S16: =R16*(0.95) -> 8688.5241 | T16: =S16*(0.95) -> 8254.0979 | U16: =T16*(1+$C16) -> 8666.8028 | V16: =U16*(0.95) -> 8233.4627 | W16: =V16*(0.95) -> 7821.7895 | X16: =W16*(1+$C16) -> 8212.879 | Y16: =X16*(0.95) -> 7802.2351 | Z16: =Y16*(0.95) -> 7412.1233 | AA16: =Z16*(1+$C16) -> 7782.7295 | AB16: =AA16*(0.95) -> 7393.593 | AC16: =AB16*(0.95) -> 7023.9134 | AD16: =AC16*(1+$C16) -> 7375.109 | AE16: =AD16*(0.95) -> 7006.3536 | AF16: =AE16*(0.95) -> 6656.0359 | AG16: =AF16*(1+$C16) -> 6988.8377 | AH16: =AG16*(1+$C16) -> 7338.2796 | AI16: =AH16*(1+$C16) -> 7705.1935 | AJ16: =AI16*(0.95) -> 7319.9339 | AK16: =AJ16*(1+$C16) -> 7685.9306 | AL16: =AK16*(1+$C16) -> 8070.2271 | AM16: =AL16*(1+$C16) -> 8473.7384 | AN16: =AM16*(0.95) -> 8050.0515
B17: Software & Apps | C17: 0.04 | E17: 6000 | F17: =E17*(0.9) -> 5400 | G17: =F17*(1+$C17) -> 5616 | H17: =G17*(1+$C17) -> 5840.64 | I17: =H17*(1+$C17) -> 6074.2656 | J17: =I17*(1+$C17) -> 6317.2362 | K17: =J17*(1+$C17) -> 6569.9257 | L17: =K17*(0.9) -> 5912.9331 | M17: =L17*(1+$C17) -> 6149.4504 | N17: =M17*(1+$C17) -> 6395.4284 | O17: =N17*(1+$C17) -> 6651.2456 | P17: =O17*(1+$C17) -> 6917.2954 | Q17: =P17*(1+$C17) -> 7193.9872 | R17: =Q17*(0.9) -> 6474.5885 | S17: =R17*(1+$C17) -> 6733.572 | T17: =S17*(1+$C17) -> 7002.9149 | U17: =T17*(1+$C17) -> 7283.0315 | V17: =U17*(1+$C17) -> 7574.3528 | W17: =V17*(1+$C17) -> 7877.3269 | X17: =W17*(0.9) -> 7089.5942 | Y17: =X17*(1+$C17) -> 7373.178 | Z17: =Y17*(1+$C17) -> 7668.1051 | AA17: =Z17*(1+$C17) -> 7974.8293 | AB17: =AA17*(1+$C17) -> 8293.8225 | AC17: =AB17*(0.9) -> 7464.4402 | AD17: =AC17*(1+$C17) -> 7763.0178 | AE17: =AD17*(1+$C17) -> 8073.5385 | AF17: =AE17*(0.9) -> 7266.1847 | AG17: =AF17*(1+$C17) -> 7556.8321 | AH17: =AG17*(1+$C17) -> 7859.1054 | AI17: =AH17*(0.9) -> 7073.1948 | AJ17: =AI17*(1+$C17) -> 7356.1226 | AK17: =AJ17*(1+$C17) -> 7650.3675 | AL17: =AK17*(1+$C17) -> 7956.3822 | AM17: =AL17*(1+$C17) -> 8274.6375 | AN17: =AM17*(1+$C17) -> 8605.623
B18: Insurance | C18: 0.04 | E18: 250 | F18: =E18*(1+$C18) -> 260 | G18: =F18*(1+$C18) -> 270.4 | H18: =G18*(1+$C18) -> 281.216 | I18: =H18*(1+$C18) -> 292.46464 | J18: =I18*(1+$C18) -> 304.16323 | K18: =J18*(1+$C18) -> 316.32975 | L18: =K18*(1+$C18) -> 328.98294 | M18: =L18*(1+$C18) -> 342.14226 | ... AN18: =AM18*(1+$C18) -> 986.52225
B19: Office Expenses | C19: 0.04 | E19: 0 | F19: =E19*(1+$C19) -> 0 | G19: =F19*(1+$C19) -> 0 | H19: =G19*(1+$C19) -> 0 | I19: =H19*(1+$C19) -> 0 | J19: =I19*(1+$C19) -> 0 | K19: =J19*(1+$C19) -> 0 | L19: =K19*(1+$C19) -> 0 | M19: =L19*(1+$C19) -> 0 | ... AN19: =AM19*(1+$C19) -> 0
B20: Office Supplies | C20: 0.02 | E20: 800 | F20: =E20*(1+$C20) -> 816 | G20: =F20*(1+$C20) -> 832.32 | H20: =G20*(1+$C20) -> 848.9664 | I20: =H20*(1+$C20) -> 865.94573 | J20: =I20*(1+$C20) -> 883.26464 | K20: =J20*(1+$C20) -> 900.92994 | L20: =K20*(1+$C20) -> 918.94853 | M20: =L20*(1+$C20) -> 937.3275 | ... AN20: =AM20*(1+$C20) -> 1599.9116
B21: Rent & Lease | C21: 0.04 | E21: 3500 | F21: =E21*(0.7) -> 2450 | G21: =F21*(1+$C21) -> 2548 | H21: =G21*(1+$C21) -> 2649.92 | I21: =H21*(1+$C21) -> 2755.9168 | J21: =I21*(1+$C21) -> 2866.1535 | K21: =J21*(0.7) -> 2006.3074 | L21: =K21*(1+$C21) -> 2086.5597 | M21: =L21*(1+$C21) -> 2170.0221 | N21: =M21*(1+$C21) -> 2256.823 | O21: =N21*(1+$C21) -> 2347.0959 | P21: =O21*(1+$C21) -> 2440.9798 | Q21: =P21*(1+$C21) -> 2538.6189 | R21: =Q21*(0.7) -> 1777.0333 | S21: =R21*(0.7) -> 1243.9233 | T21: =S21*(1+$C21) -> 1293.6802 | U21: =T21*(1+$C21) -> 1345.4274 | V21: =U21*(1+$C21) -> 1399.2445 | W21: =V21*(1+$C21) -> 1455.2143 | X21: =W21*(1+$C21) -> 1513.4229 | Y21: =X21*(0.7) -> 1059.396 | Z21: =Y21*(1+$C21) -> 1101.7719 | AA21: =Z21*(1+$C21) -> 1145.8427 | AB21: =AA21*(1+$C21) -> 1191.6764 | AC21: =AB21*(0.7) -> 834.17351 | AD21: =AC21*(1+$C21) -> 867.54045 | AE21: =AD21*(1+$C21) -> 902.24206 | AF21: =AE21*(1+$C21) -> 938.33175 | AG21: =AF21*(0.7) -> 656.83222 | AH21: =AG21*(1+$C21) -> 683.10551 | AI21: =AH21*(1+$C21) -> 710.42973 | AJ21: =AI21*(0.7) -> 497.30081 | AK21: =AJ21*(1+$C21) -> 517.19284 | AL21: =AK21*(1+$C21) -> 537.88056 | AM21: =AL21*(1+$C21) -> 559.39578 | AN21: =AM21*(0.7) -> 391.57705
B22: Utilities | C22: 0.04 | E22: 350 | F22: =E22*(1+$C22) -> 364 | G22: =F22*(1+$C22) -> 378.56 | H22: =G22*(1+$C22) -> 393.7024 | I22: =H22*(1+$C22) -> 409.4505 | J22: =I22*(1+$C22) -> 425.82852 | K22: =J22*(1+$C22) -> 442.86166 | L22: =K22*(1+$C22) -> 460.57612 | M22: =L22*(1+$C22) -> 478.99917 | ... AN22: =AM22*(1+$C22) -> 1381.1311
B23: Total Office Expenses | E23: =SUM(E22, E21, E20 + E19) -> 4650 | F23: =SUM(F22, F21, F20 + F19) -> 3630 | G23: =SUM(G22, G21, G20 + G19) -> 3758.88 | H23: =SUM(H22, H21, H20 + H19) -> 3892.5888 | I23: =SUM(I22, I21, I20 + I19) -> 4031.313 | J23: =SUM(J22, J21, J20 + J19) -> 4175.2466 | K23: =SUM(K22, K21, K20 + K19) -> 3350.099 | L23: =SUM(L22, L21, L20 + L19) -> 3466.0844 | ... AN23: =SUM(AN22, AN21, AN20 + AN19) -> 3372.6198
B24: Professional Services | E24: 0 | F24: =E24*(1+$C24) -> 0 | G24: =F24*(1+$C24) -> 0 | H24: =G24*(1+$C24) -> 0 | I24: =H24*(1+$C24) -> 0 | J24: =I24*(1+$C24) -> 0 | K24: =J24*(1+$C24) -> 0 | L24: =K24*(1+$C24) -> 0 | M24: =L24*(1+$C24) -> 0 | ... AN24: =AM24*(1+$C24) -> 0
B25: Accounting Fees | C25: 0.04 | E25: 1000 | F25: =E25*(1+$C25) -> 1040 | G25: =F25*(1+$C25) -> 1081.6 | H25: =G25*(1+$C25) -> 1124.864 | I25: =H25*(1+$C25) -> 1169.8586 | J25: =I25*(1+$C25) -> 1216.6529 | K25: =J25*(0.7) -> 851.65703 | L25: =K25*(1+$C25) -> 885.72331 | M25: =L25*(1+$C25) -> 921.15225 | N25: =M25*(1+$C25) -> 957.99834 | O25: =N25*(1+$C25) -> 996.31827 | P25: =O25*(1+$C25) -> 1036.171 | Q25: =P25*(1+$C25) -> 1077.6178 | R25: =Q25*(1+$C25) -> 1120.7226 | S25: =R25*(1+$C25) -> 1165.5515 | ... W25: =V25*(1+$C25) -> 1363.5303 | X25: =W25*(0.7) -> 954.47124 | Y25: =X25*(1+$C25) -> 992.65009 | Z25: =Y25*(1+$C25) -> 1032.3561 | AA25: =Z25*(1+$C25) -> 1073.6503 | AB25: =AA25*(1+$C25) -> 1116.5964 | AC25: =AB25*(1+$C25) -> 1161.2602 | AD25: =AC25*(0.7) -> 812.88215 | AE25: =AD25*(1+$C25) -> 845.39743 | AF25: =AE25*(1+$C25) -> 879.21333 | AG25: =AF25*(1+$C25) -> 914.38186 | AH25: =AG25*(1+$C25) -> 950.95714 | AI25: =AH25*(1+$C25) -> 988.99542 | AJ25: =AI25*(1+$C25) -> 1028.5552 | AK25: =AJ25*(0.7) -> 719.98867 | AL25: =AK25*(1+$C25) -> 748.78821 | AM25: =AL25*(1+$C25) -> 778.73974 | AN25: =AM25*(1+$C25) -> 809.88933
B26: Consulting Fees | C26: 0.02 | E26: 0 | F26: =E26*(1+$C26) -> 0 | G26: =F26*(1+$C26) -> 0 | H26: =G26*(1+$C26) -> 0 | I26: =H26*(1+$C26) -> 0 | J26: =I26*(1+$C26) -> 0 | K26: =J26*(1+$C26) -> 0 | L26: =K26*(1+$C26) -> 0 | M26: =L26*(1+$C26) -> 0 | ... AN26: =AM26*(1+$C26) -> 0
B27: Legal Fees | C27: 0.02 | E27: 1500 | F27: =E27*(1+$C27) -> 1530 | G27: =F27*(1+$C27) -> 1560.6 | H27: =G27*(1+$C27) -> 1591.812 | I27: =H27*(1+$C27) -> 1623.6482 | J27: =I27*(0.7) -> 1136.5538 | K27: =J27*(1+$C27) -> 1159.2848 | L27: =K27*(1+$C27) -> 1182.4705 | M27: =L27*(1+$C27) -> 1206.12 | N27: =M27*(1+$C27) -> 1230.2424 | O27: =N27*(1+$C27) -> 1254.8472 | P27: =O27*(1+$C27) -> 1279.9441 | Q27: =P27*(0.7) -> 895.9609 | R27: =Q27*(1+$C27) -> 913.88012 | S27: =R27*(1+$C27) -> 932.15772 | T27: =S27*(1+$C27) -> 950.80087 | U27: =T27*(1+$C27) -> 969.81689 | V27: =U27*(1+$C27) -> 989.21323 | W27: =V27*(0.7) -> 692.44926 | X27: =W27*(1+$C27) -> 706.29825 | Y27: =X27*(1+$C27) -> 720.42421 | Z27: =Y27*(1+$C27) -> 734.83269 | AA27: =Z27*(0.7) -> 514.38289 | AB27: =AA27*(1+$C27) -> 524.67054 | AC27: =AB27*(1+$C27) -> 535.16395 | AD27: =AC27*(1+$C27) -> 545.86723 | AE27: =AD27*(1+$C27) -> 556.78458 | AF27: =AE27*(1+$C27) -> 567.92027 | AG27: =AF27*(1+$C27) -> 579.27868 | AH27: =AG27*(1+$C27) -> 590.86425 | AI27: =AH27*(1+$C27) -> 602.68153 | ... AN27: =AM27*(1+$C27) -> 665.40911
B28: Recruiting Fees | C28: 0.04 | E28: 2000 | F28: =E28*(0.6) -> 1200 | G28: =F28*(1+$C28) -> 1248 | H28: =G28*(1+$C28) -> 1297.92 | I28: =H28*(1+$C28) -> 1349.8368 | J28: =I28*(1+$C28) -> 1403.8303 | K28: =J28*(1+$C28) -> 1459.9835 | L28: =K28*(1+$C28) -> 1518.3828 | M28: =L28*(0.6) -> 911.02969 | N28: =M28*(1+$C28) -> 947.47088 | O28: =N28*(1+$C28) -> 985.36972 | P28: =O28*(1+$C28) -> 1024.7845 | Q28: =P28*(1+$C28) -> 1065.7759 | R28: =Q28*(1+$C28) -> 1108.4069 | S28: =R28*(1+$C28) -> 1152.7432 | T28: =S28*(1+$C28) -> 1198.8529 | U28: =T28*(1+$C28) -> 1246.807 | ... W28: =V28*(1+$C28) -> 1348.5465 | X28: =W28*(0.6) -> 809.1279 | Y28: =X28*(1+$C28) -> 841.49301 | Z28: =Y28*(1+$C28) -> 875.15273 | AA28: =Z28*(1+$C28) -> 910.15884 | AB28: =AA28*(1+$C28) -> 946.5652 | AC28: =AB28*(1+$C28) -> 984.42781 | AD28: =AC28*(1+$C28) -> 1023.8049 | AE28: =AD28*(1+$C28) -> 1064.7571 | AF28: =AE28*(0.6) -> 638.85427 | AG28: =AF28*(1+$C28) -> 664.40844 | AH28: =AG28*(1+$C28) -> 690.98478 | AI28: =AH28*(1+$C28) -> 718.62417 | AJ28: =AI28*(1+$C28) -> 747.36913 | AK28: =AJ28*(1+$C28) -> 777.2639 | AL28: =AK28*(1+$C28) -> 808.35446 | AM28: =AL28*(1+$C28) -> 840.68863 | AN28: =AM28*(1+$C28) -> 874.31618
B29: Total Professional Services | E29: =SUM(E28, E27, E26, E25 + E24) -> 4500 | F29: =SUM(F28, F27, F26, F25 + F24) -> 3770 | G29: =SUM(G28, G27, G26, G25 + G24) -> 3890.2 | H29: =SUM(H28, H27, H26, H25 + H24) -> 4014.596 | I29: =SUM(I28, I27, I26, I25 + I24) -> 4143.3436 | J29: =SUM(J28, J27, J26, J25 + J24) -> 3757.0369 | K29: =SUM(K28, K27, K26, K25 + K24) -> 3470.9254 | L29: =SUM(L28, L27, L26, L25 + L24) -> 3586.5767 | ... AN29: =SUM(AN28, AN27, AN26, AN25 + AN24) -> 2349.6146
B30: Payroll Expenses | C30: 0.04 | E30: 0 | F30: =E30*(1+$C30) -> 0 | G30: =F30*(1+$C30) -> 0 | H30: =G30*(1+$C30) -> 0 | I30: =H30*(1+$C30) -> 0 | J30: =I30*(1+$C30) -> 0 | K30: =J30*(1+$C30) -> 0 | L30: =K30*(1+$C30) -> 0 | M30: =L30*(1+$C30) -> 0 | ... AN30: =AM30*(1+$C30) -> 0
B31: Salary & Wages | C31: 0.02 | E31: 6500 | F31: =E31*(1+$C31) -> 6630 | G31: =F31*(0.9) -> 5967 | H31: =G31*(1+$C31) -> 6086.34 | I31: =H31*(1+$C31) -> 6208.0668 | J31: =I31*(1+$C31) -> 6332.2281 | K31: =J31*(1+$C31) -> 6458.8727 | L31: =K31*(1+$C31) -> 6588.0502 | M31: =L31*(0.9) -> 5929.2451 | N31: =M31*(1+$C31) -> 6047.83 | O31: =N31*(1+$C31) -> 6168.7866 | P31: =O31*(1+$C31) -> 6292.1624 | Q31: =P31*(1+$C31) -> 6418.0056 | R31: =Q31*(1+$C31) -> 6546.3657 | S31: =R31*(1+$C31) -> 6677.293 | T31: =S31*(1+$C31) -> 6810.8389 | U31: =T31*(1+$C31) -> 6947.0557 | V31: =U31*(0.9) -> 6252.3501 | W31: =V31*(1+$C31) -> 6377.3971 | X31: =W31*(1+$C31) -> 6504.9451 | Y31: =X31*(1+$C31) -> 6635.044 | Z31: =Y31*(1+$C31) -> 6767.7448 | AA31: =Z31*(1+$C31) -> 6903.0997 | AB31: =AA31*(1+$C31) -> 7041.1617 | AC31: =AB31*(0.9) -> 6337.0456 | AD31: =AC31*(1+$C31) -> 6463.7865 | AE31: =AD31*(1+$C31) -> 6593.0622 | AF31: =AE31*(1+$C31) -> 6724.9234 | AG31: =AF31*(1+$C31) -> 6859.4219 | AH31: =AG31*(1+$C31) -> 6996.6104 | AI31: =AH31*(1+$C31) -> 7136.5426 | AJ31: =AI31*(1+$C31) -> 7279.2734 | AK31: =AJ31*(1+$C31) -> 7424.8589 | AL31: =AK31*(0.9) -> 6682.373 | AM31: =AL31*(1+$C31) -> 6816.0205 | AN31: =AM31*(1+$C31) -> 6952.3409
B32: Payroll Taxes | C32: 0.02 | E32: 918 | F32: =E32*(1+$C32) -> 936.36 | G32: =F32*(1+$C32) -> 955.0872 | H32: =G32*(1+$C32) -> 974.18894 | I32: =H32*(1+$C32) -> 993.67272 | J32: =I32*(1+$C32) -> 1013.5462 | K32: =J32*(1+$C32) -> 1033.8171 | L32: =K32*(1+$C32) -> 1054.4934 | M32: =L32*(1+$C32) -> 1075.5833 | ... AN32: =AM32*(1+$C32) -> 1835.8986
B33: Health Insurance | C33: 0.04 | E33: 700 | F33: =E33*(1+$C33) -> 728 | G33: =F33*(1+$C33) -> 757.12 | H33: =G33*(1+$C33) -> 787.4048 | I33: =H33*(1+$C33) -> 818.90099 | J33: =I33*(1+$C33) -> 851.65703 | K33: =J33*(1+$C33) -> 885.72331 | L33: =K33*(1+$C33) -> 921.15225 | M33: =L33*(1+$C33) -> 957.99834 | ... AN33: =AM33*(1+$C33) -> 2762.2623
B34: Payroll Processing Fees | C34: 0.04 | E34: 57.375 | F34: =E34*(1+$C34) -> 59.67 | G34: =F34*(1+$C34) -> 62.0568 | H34: =G34*(1+$C34) -> 64.539072 | I34: =H34*(1+$C34) -> 67.120635 | J34: =I34*(1+$C34) -> 69.80546 | K34: =J34*(1+$C34) -> 72.597679 | L34: =K34*(1+$C34) -> 75.501586 | M34: =L34*(1+$C34) -> 78.521649 | ... AN34: =AM34*(1+$C34) -> 226.40686
B35: Commissions Expense | C35: 0.04 | E35: 0 | F35: =E35*(1+$C35) -> 0 | G35: =F35*(1+$C35) -> 0 | H35: =G35*(1+$C35) -> 0 | I35: =H35*(1+$C35) -> 0 | J35: =I35*(1+$C35) -> 0 | K35: =J35*(1+$C35) -> 0 | L35: =K35*(1+$C35) -> 0 | M35: =L35*(1+$C35) -> 0 | ... AN35: =AM35*(1+$C35) -> 0
B36: Total Payroll Expenses | E36: =SUM(E35, E34, E33, E32, E31 + E30) -> 8175.375 | F36: =SUM(F35, F34, F33, F32, F31 + F30) -> 8354.03 | G36: =SUM(G35, G34, G33, G32, G31 + G30) -> 7741.264 | H36: =SUM(H35, H34, H33, H32, H31 + H30) -> 7912.4728 | I36: =SUM(I35, I34, I33, I32, I31 + I30) -> 8087.7611 | J36: =SUM(J35, J34, J33, J32, J31 + J30) -> 8267.2368 | K36: =SUM(K35, K34, K33, K32, K31 + K30) -> 8451.0108 | L36: =SUM(L35, L34, L33, L32, L31 + L30) -> 8639.1974 | ... AN36: =SUM(AN35, AN34, AN33, AN32, AN31 + AN30) -> 11776.909
B37: Taxes & Licenses | C37: 0.04 | E37: 150 | F37: =E37*(1+$C37) -> 156 | G37: =F37*(1+$C37) -> 162.24 | H37: =G37*(1+$C37) -> 168.7296 | I37: =H37*(1+$C37) -> 175.47878 | J37: =I37*(1+$C37) -> 182.49794 | K37: =J37*(1+$C37) -> 189.79785 | L37: =K37*(1+$C37) -> 197.38977 | M37: =L37*(1+$C37) -> 205.28536 | ... AN37: =AM37*(1+$C37) -> 591.91335
B38: Travel, Meals & Entertainment | C38: 0.04 | E38: 0 | F38: =E38*(1+$C38) -> 0 | G38: =F38*(1+$C38) -> 0 | H38: =G38*(1+$C38) -> 0 | I38: =H38*(1+$C38) -> 0 | J38: =I38*(1+$C38) -> 0 | K38: =J38*(1+$C38) -> 0 | L38: =K38*(1+$C38) -> 0 | M38: =L38*(1+$C38) -> 0 | ... AN38: =AM38*(1+$C38) -> 0
B39: Lodging | C39: 0.04 | E39: 850 | F39: =E39*(1+$C39) -> 884 | G39: =F39*(1+$C39) -> 919.36 | H39: =G39*(1+$C39) -> 956.1344 | I39: =H39*(1+$C39) -> 994.37978 | J39: =I39*(1+$C39) -> 1034.155 | K39: =J39*(1+$C39) -> 1075.5212 | L39: =K39*(1+$C39) -> 1118.542 | M39: =L39*(1+$C39) -> 1163.2837 | ... AN39: =AM39*(1+$C39) -> 3354.1756
B40: Meals & Entertainment | C40: 0.02 | E40: 600 | F40: =E40*(1+$C40) -> 612 | G40: =F40*(1+$C40) -> 624.24 | H40: =G40*(1+$C40) -> 636.7248 | I40: =H40*(1+$C40) -> 649.4593 | J40: =I40*(1+$C40) -> 662.44848 | K40: =J40*(1+$C40) -> 675.69745 | L40: =K40*(1+$C40) -> 689.2114 | M40: =L40*(1+$C40) -> 702.99563 | ... AN40: =AM40*(1+$C40) -> 1199.9337
B41: Travel | C41: 0.02 | E41: 250 | F41: =E41*(1+$C41) -> 255 | G41: =F41*(1+$C41) -> 260.1 | H41: =G41*(1+$C41) -> 265.302 | I41: =H41*(1+$C41) -> 270.60804 | J41: =I41*(1+$C41) -> 276.0202 | K41: =J41*(1+$C41) -> 281.5406 | L41: =K41*(1+$C41) -> 287.17142 | M41: =L41*(1+$C41) -> 292.91485 | ... AN41: =AM41*(1+$C41) -> 499.97239
B42: Total Travel, Meals & Entertainment | E42: =SUM(E41, E40, E39 + E38) -> 1700 | F42: =E42*(1+$C42) -> 1700 | G42: =F42*(1+$C42) -> 1700 | H42: =G42*(1+$C42) -> 1700 | I42: =H42*(1+$C42) -> 1700 | J42: =I42*(1+$C42) -> 1700 | K42: =J42*(1+$C42) -> 1700 | L42: =K42*(1+$C42) -> 1700 | M42: =L42*(1+$C42) -> 1700 | ... AN42: =AM42*(1+$C42) -> 1700
B43: Total Expenses | E43: =SUM(E41, E40, E39, E38, E37, E35, E34, E33, E32, E31, E30, E28, E27, E26, E25, E24, E22, E21, E20, E19, E18, E17, E16, E15, E14 + E13) -> 33775.375 | F43: =SUM(F41, F40, F39, F38, F37, F35, F34, F33, F32, F31, F30, F28, F27, F26, F25, F24, F22, F21, F20, F19, F18, F17, F16, F15, F14 + F13) -> 32085.03 | G43: =SUM(G41, G40, G39, G38, G37, G35, G34, G33, G32, G31, G30, G28, G27, G26, G25, G24, G22, G21, G20, G19, G18, G17, G16, G15, G14 + G13) -> 31601.244 | H43: =SUM(H41, H40, H39, H38, H37, H35, H34, H33, H32, H31, H30, H28, H27, H26, H25, H24, H22, H21, H20, H19, H18, H17, H16, H15, H14 + H13) -> 32741.107 | I43: =SUM(I41, I40, I39, I38, I37, I35, I34, I33, I32, I31, I30, I28, I27, I26, I25, I24, I22, I21, I20, I19, I18, I17, I16, I15, I14 + I13) -> 33926.474 | J43: =SUM(J41, J40, J39, J38, J37, J35, J34, J33, J32, J31, J30, J28, J27, J26, J25, J24, J22, J21, J20, J19, J18, J17, J16, J15, J14 + J13) -> 34639.717 | K43: =SUM(K41, K40, K39, K38, K37, K35, K34, K33, K32, K31, K30, K28, K27, K26, K25, K24, K22, K21, K20, K19, K18, K17, K16, K15, K14 + K13) -> 33599.664 | L43: =SUM(L41, L40, L39, L38, L37, L35, L34, L33, L32, L31, L30, L28, L27, L26, L25, L24, L22, L21, L20, L19, L18, L17, L16, L15, L14 + L13) -> 33023.823 | ... AN43: =SUM(AN41, AN40, AN39, AN38, AN37, AN35, AN34, AN33, AN32, AN31, AN30, AN28, AN27, AN26, AN25, AN24, AN22, AN21, AN20, AN19, AN18, AN17, AN16, AN15, AN14 + AN13) -> 42168.466
B44: Net Operating Income | E44: =E12-E43 -> 60174.625 | F44: =F12-F43 -> 64672.97 | G44: =G12-G43 -> 61199.076 | H44: =H12-H43 -> 62831.866 | I44: =I12-I43 -> 64501.877 | J44: =J12-J43 -> 66729.2 | K44: =K12-K43 -> 70797.546 | L44: =L12-L43 -> 67091.213 | ... AN44: =AN12-AN43 -> 105917.54
B45: Other Income | C45: 0.04
B46: Interest Income | C46: 0.04 | E46: 0 | F46: =E46*(1+$C46) -> 0 | G46: =F46*(1+$C46) -> 0 | H46: =G46*(1+$C46) -> 0 | I46: =H46*(1+$C46) -> 0 | J46: =I46*(1+$C46) -> 0 | K46: =J46*(1+$C46) -> 0 | L46: =K46*(1+$C46) -> 0 | M46: =L46*(1+$C46) -> 0 | ... AN46: =AM46*(1+$C46) -> 0
B47: Total Other Income | E47: =SUM(E46 + E45) -> 0 | F47: =SUM(F46 + F45) -> 0 | G47: =SUM(G46 + G45) -> 0 | H47: =SUM(H46 + H45) -> 0 | I47: =SUM(I46 + I45) -> 0 | J47: =SUM(J46 + J45) -> 0 | K47: =SUM(K46 + K45) -> 0 | L47: =SUM(L46 + L45) -> 0 | ... AN47: =SUM(AN46 + AN45) -> 0
B48: Other Expenses | C48: 0.04
B49: Depreciation Expense | C49: 0.04 | E49: 69.444444 | F49: =E49*(1+$C49) -> 72.222222 | G49: =F49*(1+$C49) -> 75.111111 | H49: =G49*(1+$C49) -> 78.115556 | I49: =H49*(1+$C49) -> 81.240178 | J49: =I49*(1+$C49) -> 84.489785 | K49: =J49*(1+$C49) -> 87.869376 | L49: =K49*(1+$C49) -> 91.384151 | M49: =L49*(1+$C49) -> 95.039517 | ... AN49: =AM49*(1+$C49) -> 274.03396
B50: Interest Expense | C50: 0.04 | E50: 2500 | F50: =E50*(1+$C50) -> 2600 | G50: =F50*(1+$C50) -> 2704 | H50: =G50*(1+$C50) -> 2812.16 | I50: =H50*(1+$C50) -> 2924.6464 | J50: =I50*(1+$C50) -> 3041.6323 | K50: =J50*(1+$C50) -> 3163.2975 | L50: =K50*(1+$C50) -> 3289.8294 | M50: =L50*(1+$C50) -> 3421.4226 | ... AN50: =AM50*(1+$C50) -> 9865.2225
B51: Total Other Expenses | E51: =SUM(E50, E49 + E48) -> 2569.4444 | F51: =SUM(F50, F49 + F48) -> 2672.2222 | G51: =SUM(G50, G49 + G48) -> 2779.1111 | H51: =SUM(H50, H49 + H48) -> 2890.2756 | I51: =SUM(I50, I49 + I48) -> 3005.8866 | J51: =SUM(J50, J49 + J48) -> 3126.122 | K51: =SUM(K50, K49 + K48) -> 3251.1669 | L51: =SUM(L50, L49 + L48) -> 3381.2136 | ... AN51: =SUM(AN50, AN49 + AN48) -> 10139.256
B52: Net Other Income | E52: =E47-E51 -> -2569.4444 | F52: =F47-F51 -> -2672.2222 | G52: =G47-G51 -> -2779.1111 | H52: =H47-H51 -> -2890.2756 | I52: =I47-I51 -> -3005.8866 | J52: =J47-J51 -> -3126.122 | K52: =K47-K51 -> -3251.1669 | L52: =L47-L51 -> -3381.2136 | ... AN52: =AN47-AN51 -> -10139.256
B53: Net Income | E53: =E44+E52 -> 57605.181 | F53: =F44+F52 -> 62000.748 | G53: =G44+G52 -> 58419.965 | H53: =H44+H52 -> 59941.59 | I53: =I44+I52 -> 61495.99 | J53: =J44+J52 -> 63603.078 | K53: =K44+K52 -> 67546.379 | L53: =L44+L52 -> 63709.999 | ... AN53: =AN44+AN52 -> 95778.284
NSC267: 74
NSC268: 75
NSC269: 76
NSC270: 77
NSC271: 78
NRN272: Value Row | NSC272: 79 | NSE272: Value Row | NTQ272: Value Row
NRN273: Value Row | NSC273: 80 | NSE273: Value Row | NTQ273: Value Row
NRN274: Value Row | NSC274: 81 | NSE274: Value Row | NTQ274: Value Row
NRN275: Value Row | NSC275: 82 | NSE275: Value Row | NTQ275: Value Row
NRN276: Value Row | NSC276: 83 | NSE276: Value Row | NTO276: 74 | NTQ276: Value Row
NRN277: Value Row | NSC277: 84 | NSE277: Value Row | NTO277: 75 | NTQ277: Value Row
NSC278: 85 | NTO278: 76
NRN279: Value Row | NSC279: 86 | NSE279: Value Row | NTO279: 77 | NTQ279: Value Row
NRN280: Value Row | NSC280: 87 | NSE280: Value Row | NTO280: 78 | NTQ280: Value Row
NRN281: Value Row | NSC281: 88 | NSE281: Value Row | NTO281: 79 | NTQ281: Value Row
NRN282: Value Row | NSC282: 89 | NSE282: Value Row | NTO282: 80 | NTQ282: Value Row
NRN283: Value Row | NSC283: 90 | NSE283: Value Row | NTO283: 81 | NTQ283: Value Row
NRN284: Summation Row | NSC284: 91 | NSE284: Summation Row | NTO284: 82 | NTQ284: Summation Row
NSC285: 92 | NTO285: 83
NRN286: Value Row | NSC286: 93 | NSE286: Value Row | NTO286: 84 | NTQ286: Value Row
NRN287: Value Row | NSC287: 94 | NSE287: Value Row | NTO287: 85 | NTQ287: Value Row
NRN288: Value Row | NSE288: Value Row | NTO288: 86 | NTQ288: Value Row
NRN289: Value Row | NSE289: Value Row | NTO289: 87 | NTQ289: Value Row
NRN290: Summation Row | NSE290: Summation Row | NTO290: 88 | NTQ290: Summation Row
NRN291: Value Row | NSE291: Value Row | NTO291: 89 | NTQ291: Value Row
NRN292: Value Row | NSE292: Value Row | NTO292: 90 | NTQ292: Value Row
NRN293: Value Row | NSE293: Value Row | NTO293: 91 | NTQ293: Value Row
NTO294: 92
NRN295: Value Row | NSE295: Value Row | NTO295: 93 | NTQ295: Value Row
NSE296: Value Row | NTO296: 94 | NTQ296: Value Row
NSE297: Summation Row | NTO297: 95 | NTQ297: Summation Row
NTO298: 96
NTO299: 97
NTO300: 98
NTO301: 99
NTO302: 100
NTO303: 101
NTO304: 102

Sheet R&D_Budget
A1: Income Statement
A2: Your CFO Guy
A3: Research & Development
C4: Growth | E4: 44957 | F4: =EOMONTH(E4,1) -> 44985 | G4: =EOMONTH(F4,1) -> 45016 | H4: =EOMONTH(G4,1) -> 45046 | I4: =EOMONTH(H4,1) -> 45077 | J4: =EOMONTH(I4,1) -> 45107 | K4: =EOMONTH(J4,1) -> 45138 | L4: =EOMONTH(K4,1) -> 45169 | M4: =EOMONTH(L4,1) -> 45199 | ... AN4: =EOMONTH(AM4,1) -> 46022
B5: Revenue
B6: Sales | C6: 0.1 | E6: 0 | F6: 0 | G6: 0 | H6: 0 | I6: 0 | J6: 0 | K6: 0 | L6: 0 | M6: 0 | N6: 0 | O6: 0 | P6: 0 | Q6: 0 | R6: 0 | S6: 0 | T6: 0 | U6: 0 | V6: 0 | W6: 0 | X6: 0 | Y6: 0 | Z6: 0 | AA6: 0 | AB6: 0 | AC6: 0 | AD6: 0 | AE6: 0 | AF6: 0 | AG6: 0 | AH6: 0 | AI6: 0 | AJ6: 0 | AK6: 0 | AL6: 0 | AM6: 0 | AN6: 0
B7: Total Revenue | E7: =SUM(E6 + E5) -> 0 | F7: =SUM(F6 + F5) -> 0 | G7: =SUM(G6 + G5) -> 0 | H7: =SUM(H6 + H5) -> 0 | I7: =SUM(I6 + I5) -> 0 | J7: =SUM(J6 + J5) -> 0 | K7: =SUM(K6 + K5) -> 0 | L7: =SUM(L6 + L5) -> 0 | ... AN7: =SUM(AN6 + AN5) -> 0
B8: Cost of Goods Sold
B9: Web Domain & Hosting Fees | C9: 0.04 | E9: 800 | F9: =E9*(1+$C9) -> 832 | G9: =F9*(1+$C9) -> 865.28 | H9: =G9*(1+$C9) -> 899.8912 | I9: =H9*(1+$C9) -> 935.88685 | J9: =I9*(1+$C9) -> 973.32232 | K9: =J9*(1+$C9) -> 1012.2552 | L9: =K9*(1+$C9) -> 1052.7454 | M9: =L9*(1+$C9) -> 1094.8552 | ... AN9: =AM9*(1+$C9) -> 3156.8712
B10: Merchant Account Fees | C10: 0.04 | E10: 0 | F10: 0 | G10: 0 | H10: 0 | I10: 0 | J10: 0 | K10: 0 | L10: 0 | M10: 0 | N10: 0 | O10: 0 | P10: 0 | Q10: 0 | R10: 0 | S10: 0 | T10: 0 | U10: 0 | V10: 0 | W10: 0 | X10: 0 | Y10: 0 | Z10: 0 | AA10: 0 | AB10: 0 | AC10: 0 | AD10: 0 | AE10: 0 | AF10: 0 | AG10: 0 | AH10: 0 | AI10: 0 | AJ10: 0 | AK10: 0 | AL10: 0 | AM10: 0 | AN10: 0
B11: Total Cost of Goods Sold | E11: =SUM(E10, E9 + E8) -> 800 | F11: =SUM(F10, F9 + F8) -> 832 | G11: =SUM(G10, G9 + G8) -> 865.28 | H11: =SUM(H10, H9 + H8) -> 899.8912 | I11: =SUM(I10, I9 + I8) -> 935.88685 | J11: =SUM(J10, J9 + J8) -> 973.32232 | K11: =SUM(K10, K9 + K8) -> 1012.2552 | L11: =SUM(L10, L9 + L8) -> 1052.7454 | ... AN11: =SUM(AN10, AN9 + AN8) -> 3156.8712
B12: Gross Profit | E12: =E7-E11 -> -800 | F12: =F7-F11 -> -832 | G12: =G7-G11 -> -865.28 | H12: =H7-H11 -> -899.8912 | I12: =I7-I11 -> -935.88685 | J12: =J7-J11 -> -973.32232 | K12: =K7-K11 -> -1012.2552 | L12: =L7-L11 -> -1052.7454 | ... AN12: =AN7-AN11 -> -3156.8712
B13: Expenses
B14: Advertising & Marketing | C14: 0.04 | E14: 0 | F14: 0 | G14: 0 | H14: 0 | I14: 0 | J14: 0 | K14: 0 | L14: 0 | M14: 0 | N14: 0 | O14: 0 | P14: 0 | Q14: 0 | R14: 0 | S14: 0 | T14: 0 | U14: 0 | V14: 0 | W14: 0 | X14: 0 | Y14: 0 | Z14: 0 | AA14: 0 | AB14: 0 | AC14: 0 | AD14: 0 | AE14: 0 | AF14: 0 | AG14: 0 | AH14: 0 | AI14: 0 | AJ14: 0 | AK14: 0 | AL14: 0 | AM14: 0 | AN14: 0
B15: Bank Charges & Fees | C15: 0.04 | E15: 0 | F15: 0 | G15: 0 | H15: 0 | I15: 0 | J15: 0 | K15: 0 | L15: 0 | M15: 0 | N15: 0 | O15: 0 | P15: 0 | Q15: 0 | R15: 0 | S15: 0 | T15: 0 | U15: 0 | V15: 0 | W15: 0 | X15: 0 | Y15: 0 | Z15: 0 | AA15: 0 | AB15: 0 | AC15: 0 | AD15: 0 | AE15: 0 | AF15: 0 | AG15: 0 | AH15: 0 | AI15: 0 | AJ15: 0 | AK15: 0 | AL15: 0 | AM15: 0 | AN15: 0
B16: Conferences & Events | C16: 0.04 | E16: 4000 | F16: =E16*(1+$C16) -> 4160 | G16: =F16*(0.9) -> 3744 | H16: =G16*(1+$C16) -> 3893.76 | I16: =H16*(1+$C16) -> 4049.5104 | J16: =I16*(1+$C16) -> 4211.4908 | K16: =J16*(1+$C16) -> 4379.9504 | L16: =K16*(1+$C16) -> 4555.1485 | M16: =L16*(1+$C16) -> 4737.3544 | N16: =M16*(0.9) -> 4263.619 | O16: =N16*(0.9) -> 3837.2571 | P16: =O16*(1+$C16) -> 3990.7474 | Q16: =P16*(1+$C16) -> 4150.3772 | R16: =Q16*(1+$C16) -> 4316.3923 | S16: =R16*(0.9) -> 3884.7531 | T16: =S16*(1+$C16) -> 4040.1432 | U16: =T16*(1+$C16) -> 4201.749 | V16: =U16*(1+$C16) -> 4369.8189 | W16: =V16*(0.9) -> 3932.837 | X16: =W16*(0.9) -> 3539.5533 | Y16: =X16*(1+$C16) -> 3681.1355 | Z16: =Y16*(1+$C16) -> 3828.3809 | AA16: =Z16*(1+$C16) -> 3981.5161 | AB16: =AA16*(1+$C16) -> 4140.7767 | AC16: =AB16*(1+$C16) -> 4306.4078 | AD16: =AC16*(0.9) -> 3875.767 | AE16: =AD16*(1+$C16) -> 4030.7977 | AF16: =AE16*(1+$C16) -> 4192.0296 | AG16: =AF16*(1+$C16) -> 4359.7108 | AH16: =AG16*(0.9) -> 3923.7397 | AI16: =AH16*(1+$C16) -> 4080.6893 | AJ16: =AI16*(1+$C16) -> 4243.9169 | AK16: =AJ16*(1+$C16) -> 4413.6736 | AL16: =AK16*(1+$C16) -> 4590.2205 | AM16: =AL16*(1+$C16) -> 4773.8293 | AN16: =AM16*(0.9) -> 4296.4464
B17: Software & Apps | C17: 0.03 | E17: 6000 | F17: =E17*(1+$C17) -> 6180 | G17: =F17*(1+$C17) -> 6365.4 | H17: =G17*(0.9) -> 5728.86 | I17: =H17*(1+$C17) -> 5900.7258 | J17: =I17*(1+$C17) -> 6077.7476 | K17: =J17*(1+$C17) -> 6260.08 | L17: =K17*(1+$C17) -> 6447.8824 | M17: =L17*(1+$C17) -> 6641.3189 | N17: =M17*(1+$C17) -> 6840.5584 | O17: =N17*(0.9) -> 6156.5026 | P17: =O17*(1+$C17) -> 6341.1977 | Q17: =P17*(1+$C17) -> 6531.4336 | R17: =Q17*(1+$C17) -> 6727.3766 | S17: =R17*(0.9) -> 6054.639 | T17: =S17*(1+$C17) -> 6236.2781 | U17: =T17*(1+$C17) -> 6423.3665 | V17: =U17*(1+$C17) -> 6616.0675 | W17: =V17*(1+$C17) -> 6814.5495 | X17: =W17*(1+$C17) -> 7018.986 | Y17: =X17*(1+$C17) -> 7229.5555 | Z17: =Y17*(0.9) -> 6506.6 | AA17: =Z17*(1+$C17) -> 6701.798 | AB17: =AA17*(1+$C17) -> 6902.8519 | AC17: =AB17*(1+$C17) -> 7109.9375 | AD17: =AC17*(0.9) -> 6398.9437 | AE17: =AD17*(1+$C17) -> 6590.912 | AF17: =AE17*(1+$C17) -> 6788.6394 | AG17: =AF17*(1+$C17) -> 6992.2986 | AH17: =AG17*(0.9) -> 6293.0687 | AI17: =AH17*(1+$C17) -> 6481.8608 | AJ17: =AI17*(1+$C17) -> 6676.3166 | AK17: =AJ17*(1+$C17) -> 6876.6061 | AL17: =AK17*(1+$C17) -> 7082.9043 | AM17: =AL17*(0.9) -> 6374.6139 | AN17: =AM17*(1+$C17) -> 6565.8523
B18: Insurance | C18: 0.04 | E18: 0 | F18: 0 | G18: 0 | H18: 0 | I18: 0 | J18: 0 | K18: 0 | L18: 0 | M18: 0 | N18: 0 | O18: 0 | P18: 0 | Q18: 0 | R18: 0 | S18: 0 | T18: 0 | U18: 0 | V18: 0 | W18: 0 | X18: 0 | Y18: 0 | Z18: 0 | AA18: 0 | AB18: 0 | AC18: 0 | AD18: 0 | AE18: 0 | AF18: 0 | AG18: 0 | AH18: 0 | AI18: 0 | AJ18: 0 | AK18: 0 | AL18: 0 | AM18: 0 | AN18: 0
B19: Office Expenses | C19: 0.04 | E19: 0 | F19: 0 | G19: 0 | H19: 0 | I19: 0 | J19: 0 | K19: 0 | L19: 0 | M19: 0 | N19: 0 | O19: 0 | P19: 0 | Q19: 0 | R19: 0 | S19: 0 | T19: 0 | U19: 0 | V19: 0 | W19: 0 | X19: 0 | Y19: 0 | Z19: 0 | AA19: 0 | AB19: 0 | AC19: 0 | AD19: 0 | AE19: 0 | AF19: 0 | AG19: 0 | AH19: 0 | AI19: 0 | AJ19: 0 | AK19: 0 | AL19: 0 | AM19: 0 | AN19: 0
B20: Office Supplies | C20: 0.04 | E20: 0 | F20: 0 | G20: 0 | H20: 0 | I20: 0 | J20: 0 | K20: 0 | L20: 0 | M20: 0 | N20: 0 | O20: 0 | P20: 0 | Q20: 0 | R20: 0 | S20: 0 | T20: 0 | U20: 0 | V20: 0 | W20: 0 | X20: 0 | Y20: 0 | Z20: 0 | AA20: 0 | AB20: 0 | AC20: 0 | AD20: 0 | AE20: 0 | AF20: 0 | AG20: 0 | AH20: 0 | AI20: 0 | AJ20: 0 | AK20: 0 | AL20: 0 | AM20: 0 | AN20: 0
B21: Rent & Lease | C21: 0.04 | E21: 0 | F21: 0 | G21: 0 | H21: 0 | I21: 0 | J21: 0 | K21: 0 | L21: 0 | M21: 0 | N21: 0 | O21: 0 | P21: 0 | Q21: 0 | R21: 0 | S21: 0 | T21: 0 | U21: 0 | V21: 0 | W21: 0 | X21: 0 | Y21: 0 | Z21: 0 | AA21: 0 | AB21: 0 | AC21: 0 | AD21: 0 | AE21: 0 | AF21: 0 | AG21: 0 | AH21: 0 | AI21: 0 | AJ21: 0 | AK21: 0 | AL21: 0 | AM21: 0 | AN21: 0
B22: Utilities | C22: 0.04 | E22: 0 | F22: 0 | G22: 0 | H22: 0 | I22: 0 | J22: 0 | K22: 0 | L22: 0 | M22: 0 | N22: 0 | O22: 0 | P22: 0 | Q22: 0 | R22: 0 | S22: 0 | T22: 0 | U22: 0 | V22: 0 | W22: 0 | X22: 0 | Y22: 0 | Z22: 0 | AA22: 0 | AB22: 0 | AC22: 0 | AD22: 0 | AE22: 0 | AF22: 0 | AG22: 0 | AH22: 0 | AI22: 0 | AJ22: 0 | AK22: 0 | AL22: 0 | AM22: 0 | AN22: 0
B23: Total Office Expenses | E23: =SUM(E22, E21, E20 + E19) -> 0 | F23: =SUM(F22, F21, F20 + F19) -> 0 | G23: =SUM(G22, G21, G20 + G19) -> 0 | H23: =SUM(H22, H21, H20 + H19) -> 0 | I23: =SUM(I22, I21, I20 + I19) -> 0 | J23: =SUM(J22, J21, J20 + J19) -> 0 | K23: =SUM(K22, K21, K20 + K19) -> 0 | L23: =SUM(L22, L21, L20 + L19) -> 0 | ... AN23: =SUM(AN22, AN21, AN20 + AN19) -> 0
B24: Professional Services | E24: 0 | F24: =E24*(1+$C24) -> 0 | G24: =F24*(1+$C24) -> 0 | H24: =G24*(1+$C24) -> 0 | I24: =H24*(1+$C24) -> 0 | J24: =I24*(1+$C24) -> 0 | K24: =J24*(1+$C24) -> 0 | L24: =K24*(1+$C24) -> 0 | M24: =L24*(1+$C24) -> 0 | ... AN24: =AM24*(1+$C24) -> 0
B25: Accounting Fees | C25: 0.04 | E25: 0 | F25: 0 | G25: 0 | H25: 0 | I25: 0 | J25: 0 | K25: 0 | L25: 0 | M25: 0 | N25: 0 | O25: 0 | P25: 0 | Q25: 0 | R25: 0 | S25: 0 | T25: 0 | U25: 0 | V25: 0 | W25: 0 | X25: 0 | Y25: 0 | Z25: 0 | AA25: 0 | AB25: 0 | AC25: 0 | AD25: 0 | AE25: 0 | AF25: 0 | AG25: 0 | AH25: 0 | AI25: 0 | AJ25: 0 | AK25: 0 | AL25: 0 | AM25: 0 | AN25: 0
B26: Consulting Fees | C26: 0.04 | E26: 0 | F26: 0 | G26: 0 | H26: 0 | I26: 0 | J26: 0 | K26: 0 | L26: 0 | M26: 0 | N26: 0 | O26: 0 | P26: 0 | Q26: 0 | R26: 0 | S26: 0 | T26: 0 | U26: 0 | V26: 0 | W26: 0 | X26: 0 | Y26: 0 | Z26: 0 | AA26: 0 | AB26: 0 | AC26: 0 | AD26: 0 | AE26: 0 | AF26: 0 | AG26: 0 | AH26: 0 | AI26: 0 | AJ26: 0 | AK26: 0 | AL26: 0 | AM26: 0 | AN26: 0
B27: Legal Fees | C27: 0.04 | E27: 0 | F27: 0 | G27: 0 | H27: 0 | I27: 0 | J27: 0 | K27: 0 | L27: 0 | M27: 0 | N27: 0 | O27: 0 | P27: 0 | Q27: 0 | R27: 0 | S27: 0 | T27: 0 | U27: 0 | V27: 0 | W27: 0 | X27: 0 | Y27: 0 | Z27: 0 | AA27: 0 | AB27: 0 | AC27: 0 | AD27: 0 | AE27: 0 | AF27: 0 | AG27: 0 | AH27: 0 | AI27: 0 | AJ27: 0 | AK27: 0 | AL27: 0 | AM27: 0 | AN27: 0
B28: Recruiting Fees | C28: 0.01 | E28: 1500 | F28: =E28*(1+$C28) -> 1515 | G28: =F28*(1+$C28) -> 1530.15 | H28: =G28*(1+$C28) -> 1545.4515 | I28: =H28*(1+$C28) -> 1560.906 | J28: =I28*(1+$C28) -> 1576.5151 | K28: =J28*(1+$C28) -> 1592.2802 | L28: =K28*(1+$C28) -> 1608.203 | M28: =L28*(1+$C28) -> 1624.2851 | N28: =M28*(0.9) -> 1461.8566 | O28: =N28*(1+$C28) -> 1476.4751 | P28: =O28*(1+$C28) -> 1491.2399 | Q28: =P28*(1+$C28) -> 1506.1523 | R28: =Q28*(1+$C28) -> 1521.2138 | S28: =R28*(1+$C28) -> 1536.4259 | T28: =S28*(1+$C28) -> 1551.7902 | U28: =T28*(0.9) -> 1396.6112 | V28: =U28*(1+$C28) -> 1410.5773 | W28: =V28*(1+$C28) -> 1424.6831 | X28: =W28*(1+$C28) -> 1438.9299 | Y28: =X28*(1+$C28) -> 1453.3192 | Z28: =Y28*(0.9) -> 1307.9873 | AA28: =Z28*(1+$C28) -> 1321.0671 | AB28: =AA28*(1+$C28) -> 1334.2778 | AC28: =AB28*(1+$C28) -> 1347.6206 | AD28: =AC28*(1+$C28) -> 1361.0968 | AE28: =AD28*(0.9) -> 1224.9871 | AF28: =AE28*(1+$C28) -> 1237.237 | AG28: =AF28*(1+$C28) -> 1249.6094 | AH28: =AG28*(1+$C28) -> 1262.1054 | AI28: =AH28*(1+$C28) -> 1274.7265 | AJ28: =AI28*(1+$C28) -> 1287.4738 | AK28: =AJ28*(0.9) -> 1158.7264 | AL28: =AK28*(1+$C28) -> 1170.3137 | AM28: =AL28*(1+$C28) -> 1182.0168 | AN28: =AM28*(1+$C28) -> 1193.837
B29: Total Professional Services | E29: =SUM(E28, E27, E26, E25 + E24) -> 1500 | F29: =SUM(F28, F27, F26, F25 + F24) -> 1515 | G29: =SUM(G28, G27, G26, G25 + G24) -> 1530.15 | H29: =SUM(H28, H27, H26, H25 + H24) -> 1545.4515 | I29: =SUM(I28, I27, I26, I25 + I24) -> 1560.906 | J29: =SUM(J28, J27, J26, J25 + J24) -> 1576.5151 | K29: =SUM(K28, K27, K26, K25 + K24) -> 1592.2802 | L29: =SUM(L28, L27, L26, L25 + L24) -> 1608.203 | ... AN29: =SUM(AN28, AN27, AN26, AN25 + AN24) -> 1193.837
B30: Payroll Expenses | C30: 0.04 | E30: 0 | F30: =E30*(1+$C30) -> 0 | G30: =F30*(1+$C30) -> 0 | H30: =G30*(1+$C30) -> 0 | I30: =H30*(1+$C30) -> 0 | J30: =I30*(1+$C30) -> 0 | K30: =J30*(1+$C30) -> 0 | L30: =K30*(1+$C30) -> 0 | M30: =L30*(1+$C30) -> 0 | ... AN30: =AM30*(1+$C30) -> 0
B31: Salary & Wages | C31: 0.02 | E31: 8000 | F31: =E31*(1+$C31) -> 8160 | G31: =F31*(1+$C31) -> 8323.2 | H31: =G31*(1+$C31) -> 8489.664 | I31: =H31*(1+$C31) -> 8659.4573 | J31: =I31*(1+$C31) -> 8832.6464 | K31: =J31*(0.9) -> 7949.3818 | L31: =K31*(1+$C31) -> 8108.3694 | M31: =L31*(1+$C31) -> 8270.5368 | N31: =M31*(1+$C31) -> 8435.9475 | O31: =N31*(1+$C31) -> 8604.6665 | P31: =O31*(0.9) -> 7744.1998 | Q31: =P31*(1+$C31) -> 7899.0838 | R31: =Q31*(1+$C31) -> 8057.0655 | S31: =R31*(1+$C31) -> 8218.2068 | T31: =S31*(1+$C31) -> 8382.571 | U31: =T31*(1+$C31) -> 8550.2224 | V31: =U31*(1+$C31) -> 8721.2268 | W31: =V31*(0.9) -> 7849.1041 | X31: =W31*(1+$C31) -> 8006.0862 | Y31: =X31*(1+$C31) -> 8166.208 | Z31: =Y31*(1+$C31) -> 8329.5321 | AA31: =Z31*(1+$C31) -> 8496.1228 | AB31: =AA31*(1+$C31) -> 8666.0452 | AC31: =AB31*(1+$C31) -> 8839.3661 | AD31: =AC31*(0.9) -> 7955.4295 | AE31: =AD31*(1+$C31) -> 8114.5381 | AF31: =AE31*(1+$C31) -> 8276.8289 | AG31: =AF31*(1+$C31) -> 8442.3654 | AH31: =AG31*(1+$C31) -> 8611.2127 | AI31: =AH31*(1+$C31) -> 8783.437 | AJ31: =AI31*(0.9) -> 7905.0933 | AK31: =AJ31*(1+$C31) -> 8063.1952 | AL31: =AK31*(1+$C31) -> 8224.4591 | AM31: =AL31*(1+$C31) -> 8388.9482 | AN31: =AM31*(1+$C31) -> 8556.7272
B32: Payroll Taxes | C32: 0.04 | E32: 918 | F32: =E32*(1+$C32) -> 954.72 | G32: =F32*(1+$C32) -> 992.9088 | H32: =G32*(0.9) -> 893.61792 | I32: =H32*(1+$C32) -> 929.36264 | J32: =I32*(1+$C32) -> 966.53714 | K32: =J32*(1+$C32) -> 1005.1986 | L32: =K32*(1+$C32) -> 1045.4066 | M32: =L32*(1+$C32) -> 1087.2228 | N32: =M32*(1+$C32) -> 1130.7117 | O32: =N32*(1+$C32) -> 1175.9402 | P32: =O32*(1+$C32) -> 1222.9778 | Q32: =P32*(1+$C32) -> 1271.8969 | R32: =Q32*(0.9) -> 1144.7072 | S32: =R32*(1+$C32) -> 1190.4955 | T32: =S32*(1+$C32) -> 1238.1154 | U32: =T32*(1+$C32) -> 1287.64 | V32: =U32*(1+$C32) -> 1339.1456 | W32: =V32*(1+$C32) -> 1392.7114 | X32: =W32*(1+$C32) -> 1448.4199 | Y32: =X32*(0.9) -> 1303.5779 | Z32: =Y32*(1+$C32) -> 1355.721 | AA32: =Z32*(1+$C32) -> 1409.9498 | AB32: =AA32*(1+$C32) -> 1466.3478 | AC32: =AB32*(1+$C32) -> 1525.0017 | AD32: =AC32*(1+$C32) -> 1586.0018 | AE32: =AD32*(1+$C32) -> 1649.4419 | AF32: =AE32*(0.9) -> 1484.4977 | AG32: =AF32*(1+$C32) -> 1543.8776 | AH32: =AG32*(1+$C32) -> 1605.6327 | AI32: =AH32*(0.9) -> 1445.0694 | AJ32: =AI32*(1+$C32) -> 1502.8722 | AK32: =AJ32*(1+$C32) -> 1562.9871 | AL32: =AK32*(1+$C32) -> 1625.5066 | AM32: =AL32*(0.9) -> 1462.9559 | AN32: =AM32*(1+$C32) -> 1521.4741
B33: Health Insurance | C33: 0.04 | E33: 800 | F33: =E33*(1+$C33) -> 832 | G33: =F33*(1+$C33) -> 865.28 | H33: =G33*(1+$C33) -> 899.8912 | I33: =H33*(1+$C33) -> 935.88685 | J33: =I33*(1+$C33) -> 973.32232 | K33: =J33*(1+$C33) -> 1012.2552 | L33: =K33*(1+$C33) -> 1052.7454 | M33: =L33*(1+$C33) -> 1094.8552 | ... AN33: =AM33*(1+$C33) -> 3156.8712
B34: Payroll Processing Fees | C34: 0.04 | E34: 57.375 | F34: =E34*(1+$C34) -> 59.67 | G34: =F34*(1+$C34) -> 62.0568 | H34: =G34*(1+$C34) -> 64.539072 | I34: =H34*(1+$C34) -> 67.120635 | J34: =I34*(1+$C34) -> 69.80546 | K34: =J34*(1+$C34) -> 72.597679 | L34: =K34*(1+$C34) -> 75.501586 | M34: =L34*(1+$C34) -> 78.521649 | ... AN34: =AM34*(1+$C34) -> 226.40686
B35: Commissions Expense | C35: 0.04 | E35: 0 | F35: =E35*(1+$C35) -> 0 | G35: =F35*(1+$C35) -> 0 | H35: =G35*(1+$C35) -> 0 | I35: =H35*(1+$C35) -> 0 | J35: =I35*(1+$C35) -> 0 | K35: =J35*(1+$C35) -> 0 | L35: =K35*(1+$C35) -> 0 | M35: =L35*(1+$C35) -> 0 | ... AN35: =AM35*(1+$C35) -> 0
B36: Total Payroll Expenses | E36: =SUM(E35, E34, E33, E32, E31 + E30) -> 9775.375 | F36: =SUM(F35, F34, F33, F32, F31 + F30) -> 10006.39 | G36: =SUM(G35, G34, G33, G32, G31 + G30) -> 10243.446 | H36: =SUM(H35, H34, H33, H32, H31 + H30) -> 10347.712 | I36: =SUM(I35, I34, I33, I32, I31 + I30) -> 10591.827 | J36: =SUM(J35, J34, J33, J32, J31 + J30) -> 10842.311 | K36: =SUM(K35, K34, K33, K32, K31 + K30) -> 10039.433 | L36: =SUM(L35, L34, L33, L32, L31 + L30) -> 10282.023 | ... AN36: =SUM(AN35, AN34, AN33, AN32, AN31 + AN30) -> 13461.479
B37: Taxes & Licenses | C37: 0.04 | E37: 0 | F37: 0 | G37: 0 | H37: 0 | I37: 0 | J37: 0 | K37: 0 | L37: 0 | M37: 0 | N37: 0 | O37: 0 | P37: 0 | Q37: 0 | R37: 0 | S37: 0 | T37: 0 | U37: 0 | V37: 0 | W37: 0 | X37: 0 | Y37: 0 | Z37: 0 | AA37: 0 | AB37: 0 | AC37: 0 | AD37: 0 | AE37: 0 | AF37: 0 | AG37: 0 | AH37: 0 | AI37: 0 | AJ37: 0 | AK37: 0 | AL37: 0 | AM37: 0 | AN37: 0
B38: Travel, Meals & Entertainment | C38: 0.04 | E38: 0 | F38: =E38*(1+$C38) -> 0 | G38: =F38*(1+$C38) -> 0 | H38: =G38*(1+$C38) -> 0 | I38: =H38*(1+$C38) -> 0 | J38: =I38*(1+$C38) -> 0 | K38: =J38*(1+$C38) -> 0 | L38: =K38*(1+$C38) -> 0 | M38: =L38*(1+$C38) -> 0 | ... AN38: =AM38*(1+$C38) -> 0
B39: Lodging | C39: 0.08 | E39: 850 | F39: =E39*(1+$C39) -> 918 | G39: =F39*(1+$C39) -> 991.44 | H39: =G39*(1+$C39) -> 1070.7552 | I39: =H39*(0.85) -> 910.14192 | J39: =I39*(1+$C39) -> 982.95327 | K39: =J39*(1+$C39) -> 1061.5895 | L39: =K39*(1+$C39) -> 1146.5167 | M39: =L39*(1+$C39) -> 1238.238 | N39: =M39*(1+$C39) -> 1337.2971 | O39: =N39*(1+$C39) -> 1444.2808 | P39: =O39*(0.85) -> 1227.6387 | Q39: =P39*(1+$C39) -> 1325.8498 | R39: =Q39*(1+$C39) -> 1431.9178 | S39: =R39*(1+$C39) -> 1546.4712 | T39: =S39*(1+$C39) -> 1670.1889 | U39: =T39*(1+$C39) -> 1803.804 | V39: =U39*(1+$C39) -> 1948.1084 | W39: =V39*(0.85) -> 1655.8921 | X39: =W39*(1+$C39) -> 1788.3635 | Y39: =X39*(1+$C39) -> 1931.4325 | Z39: =Y39*(1+$C39) -> 2085.9472 | AA39: =Z39*(1+$C39) -> 2252.8229 | AB39: =AA39*(1+$C39) -> 2433.0488 | AC39: =AB39*(0.85) -> 2068.0914 | AD39: =AC39*(1+$C39) -> 2233.5388 | AE39: =AD39*(1+$C39) -> 2412.2219 | AF39: =AE39*(1+$C39) -> 2605.1996 | AG39: =AF39*(1+$C39) -> 2813.6156 | AH39: =AG39*(1+$C39) -> 3038.7048 | AI39: =AH39*(1+$C39) -> 3281.8012 | AJ39: =AI39*(1+$C39) -> 3544.3453 | AK39: =AJ39*(0.85) -> 3012.6935 | AL39: =AK39*(1+$C39) -> 3253.709 | AM39: =AL39*(1+$C39) -> 3514.0057 | AN39: =AM39*(1+$C39) -> 3795.1262
B40: Meals & Entertainment | C40: 0.04 | E40: 600 | F40: =E40*(1+$C40) -> 624 | G40: =F40*(1+$C40) -> 648.96 | H40: =G40*(1+$C40) -> 674.9184 | I40: =H40*(1+$C40) -> 701.91514 | J40: =I40*(1+$C40) -> 729.99174 | K40: =J40*(1+$C40) -> 759.19141 | L40: =K40*(1+$C40) -> 789.55907 | M40: =L40*(1+$C40) -> 821.14143 | ... AN40: =AM40*(1+$C40) -> 2367.6534
B41: Travel | C41: 0.04 | E41: 250 | F41: =E41*(1+$C41) -> 260 | G41: =F41*(1+$C41) -> 270.4 | H41: =G41*(1+$C41) -> 281.216 | I41: =H41*(1+$C41) -> 292.46464 | J41: =I41*(1+$C41) -> 304.16323 | K41: =J41*(1+$C41) -> 316.32975 | L41: =K41*(1+$C41) -> 328.98294 | M41: =L41*(1+$C41) -> 342.14226 | ... AN41: =AM41*(1+$C41) -> 986.52225
B42: Total Travel, Meals & Entertainment | E42: =SUM(E41, E40, E39 + E38) -> 1700 | F42: =E42*(1+$C42) -> 1700 | G42: =F42*(1+$C42) -> 1700 | H42: =G42*(1+$C42) -> 1700 | I42: =H42*(1+$C42) -> 1700 | J42: =I42*(1+$C42) -> 1700 | K42: =J42*(1+$C42) -> 1700 | L42: =K42*(1+$C42) -> 1700 | M42: =L42*(1+$C42) -> 1700 | ... AN42: =AM42*(1+$C42) -> 1700
B43: Total Expenses | E43: =SUM(E41, E40, E39, E38, E37, E35, E34, E33, E32, E31, E30, E28, E27, E26, E25, E24, E22, E21, E20, E19, E18, E17, E16, E15, E14 + E13) -> 22975.375 | F43: =SUM(F41, F40, F39, F38, F37, F35, F34, F33, F32, F31, F30, F28, F27, F26, F25, F24, F22, F21, F20, F19, F18, F17, F16, F15, F14 + F13) -> 23663.39 | G43: =SUM(G41, G40, G39, G38, G37, G35, G34, G33, G32, G31, G30, G28, G27, G26, G25, G24, G22, G21, G20, G19, G18, G17, G16, G15, G14 + G13) -> 23793.796 | H43: =SUM(H41, H40, H39, H38, H37, H35, H34, H33, H32, H31, H30, H28, H27, H26, H25, H24, H22, H21, H20, H19, H18, H17, H16, H15, H14 + H13) -> 23542.673 | I43: =SUM(I41, I40, I39, I38, I37, I35, I34, I33, I32, I31, I30, I28, I27, I26, I25, I24, I22, I21, I20, I19, I18, I17, I16, I15, I14 + I13) -> 24007.491 | J43: =SUM(J41, J40, J39, J38, J37, J35, J34, J33, J32, J31, J30, J28, J27, J26, J25, J24, J22, J21, J20, J19, J18, J17, J16, J15, J14 + J13) -> 24725.173 | K43: =SUM(K41, K40, K39, K38, K37, K35, K34, K33, K32, K31, K30, K28, K27, K26, K25, K24, K22, K21, K20, K19, K18, K17, K16, K15, K14 + K13) -> 24408.855 | L43: =SUM(L41, L40, L39, L38, L37, L35, L34, L33, L32, L31, L30, L28, L27, L26, L25, L24, L22, L21, L20, L19, L18, L17, L16, L15, L14 + L13) -> 25158.316 | ... AN43: =SUM(AN41, AN40, AN39, AN38, AN37, AN35, AN34, AN33, AN32, AN31, AN30, AN28, AN27, AN26, AN25, AN24, AN22, AN21, AN20, AN19, AN18, AN17, AN16, AN15, AN14 + AN13) -> 32666.917
B44: Net Operating Income | E44: =E12-E43 -> -23775.375 | F44: =F12-F43 -> -24495.39 | G44: =G12-G43 -> -24659.076 | H44: =H12-H43 -> -24442.564 | I44: =I12-I43 -> -24943.378 | J44: =J12-J43 -> -25698.495 | K44: =K12-K43 -> -25421.11 | L44: =L12-L43 -> -26211.061 | ... AN44: =AN12-AN43 -> -35823.788
B45: Other Income | C45: 0.1
B46: Interest Income | C46: 0.1 | E46: 0 | F46: =E46*(1+$C46) -> 0 | G46: =F46*(1+$C46) -> 0 | H46: =G46*(1+$C46) -> 0 | I46: =H46*(1+$C46) -> 0 | J46: =I46*(1+$C46) -> 0 | K46: =J46*(1+$C46) -> 0 | L46: =K46*(1+$C46) -> 0 | M46: =L46*(1+$C46) -> 0 | ... AN46: =AM46*(1+$C46) -> 0
B47: Total Other Income | E47: =SUM(E46 + E45) -> 0 | F47: =SUM(F46 + F45) -> 0 | G47: =SUM(G46 + G45) -> 0 | H47: =SUM(H46 + H45) -> 0 | I47: =SUM(I46 + I45) -> 0 | J47: =SUM(J46 + J45) -> 0 | K47: =SUM(K46 + K45) -> 0 | L47: =SUM(L46 + L45) -> 0 | ... AN47: =SUM(AN46 + AN45) -> 0
B48: Other Expenses | C48: 0.1
B49: Depreciation Expense | C49: 0.1 | E49: 0 | F49: 0 | G49: 0 | H49: 0 | I49: 0 | J49: 0 | K49: 0 | L49: 0 | M49: 0 | N49: 0 | O49: 0 | P49: 0 | Q49: 0 | R49: 0 | S49: 0 | T49: 0 | U49: 0 | V49: 0 | W49: 0 | X49: 0 | Y49: 0 | Z49: 0 | AA49: 0 | AB49: 0 | AC49: 0 | AD49: 0 | AE49: 0 | AF49: 0 | AG49: 0 | AH49: 0 | AI49: 0 | AJ49: 0 | AK49: 0 | AL49: 0 | AM49: 0 | AN49: 0
B50: Interest Expense | C50: 0.1 | E50: 0 | F50: 0 | G50: 0 | H50: 0 | I50: 0 | J50: 0 | K50: 0 | L50: 0 | M50: 0 | N50: 0 | O50: 0 | P50: 0 | Q50: 0 | R50: 0 | S50: 0 | T50: 0 | U50: 0 | V50: 0 | W50: 0 | X50: 0 | Y50: 0 | Z50: 0 | AA50: 0 | AB50: 0 | AC50: 0 | AD50: 0 | AE50: 0 | AF50: 0 | AG50: 0 | AH50: 0 | AI50: 0 | AJ50: 0 | AK50: 0 | AL50: 0 | AM50: 0 | AN50: 0
B51: Total Other Expenses | E51: =SUM(E50, E49 + E48) -> 0 | F51: =SUM(F50, F49 + F48) -> 0 | G51: =SUM(G50, G49 + G48) -> 0 | H51: =SUM(H50, H49 + H48) -> 0 | I51: =SUM(I50, I49 + I48) -> 0 | J51: =SUM(J50, J49 + J48) -> 0 | K51: =SUM(K50, K49 + K48) -> 0 | L51: =SUM(L50, L49 + L48) -> 0 | ... AN51: =SUM(AN50, AN49 + AN48) -> 0
B52: Net Other Income | E52: =E47-E51 -> 0 | F52: =F47-F51 -> 0 | G52: =G47-G51 -> 0 | H52: =H47-H51 -> 0 | I52: =I47-I51 -> 0 | J52: =J47-J51 -> 0 | K52: =K47-K51 -> 0 | L52: =L47-L51 -> 0 | ... AN52: =AN47-AN51 -> 0
B53: Net Income | E53: =E44+E52 -> -23775.375 | F53: =F44+F52 -> -24495.39 | G53: =G44+G52 -> -24659.076 | H53: =H44+H52 -> -24442.564 | I53: =I44+I52 -> -24943.378 | J53: =J44+J52 -> -25698.495 | K53: =K44+K52 -> -25421.11 | L53: =L44+L52 -> -26211.061 | ... AN53: =AN44+AN52 -> -35823.788
NSC267: 74
NSC268: 75
NSC269: 76
NSC270: 77
NSC271: 78
NRN272: Value Row | NSC272: 79 | NSE272: Value Row | NTQ272: Value Row
NRN273: Value Row | NSC273: 80 | NSE273: Value Row | NTQ273: Value Row
NRN274: Value Row | NSC274: 81 | NSE274: Value Row | NTQ274: Value Row
NRN275: Value Row | NSC275: 82 | NSE275: Value Row | NTQ275: Value Row
NRN276: Value Row | NSC276: 83 | NSE276: Value Row | NTO276: 74 | NTQ276: Value Row
NRN277: Value Row | NSC277: 84 | NSE277: Value Row | NTO277: 75 | NTQ277: Value Row
NSC278: 85 | NTO278: 76
NRN279: Value Row | NSC279: 86 | NSE279: Value Row | NTO279: 77 | NTQ279: Value Row
NRN280: Value Row | NSC280: 87 | NSE280: Value Row | NTO280: 78 | NTQ280: Value Row
NRN281: Value Row | NSC281: 88 | NSE281: Value Row | NTO281: 79 | NTQ281: Value Row
NRN282: Value Row | NSC282: 89 | NSE282: Value Row | NTO282: 80 | NTQ282: Value Row
NRN283: Value Row | NSC283: 90 | NSE283: Value Row | NTO283: 81 | NTQ283: Value Row
NRN284: Summation Row | NSC284: 91 | NSE284: Summation Row | NTO284: 82 | NTQ284: Summation Row
NSC285: 92 | NTO285: 83
NRN286: Value Row | NSC286: 93 | NSE286: Value Row | NTO286: 84 | NTQ286: Value Row
NRN287: Value Row | NSC287: 94 | NSE287: Value Row | NTO287: 85 | NTQ287: Value Row
NRN288: Value Row | NSE288: Value Row | NTO288: 86 | NTQ288: Value Row
NRN289: Value Row | NSE289: Value Row | NTO289: 87 | NTQ289: Value Row
NRN290: Summation Row | NSE290: Summation Row | NTO290: 88 | NTQ290: Summation Row
NRN291: Value Row | NSE291: Value Row | NTO291: 89 | NTQ291: Value Row
NRN292: Value Row | NSE292: Value Row | NTO292: 90 | NTQ292: Value Row
NRN293: Value Row | NSE293: Value Row | NTO293: 91 | NTQ293: Value Row
NTO294: 92
NRN295: Value Row | NSE295: Value Row | NTO295: 93 | NTQ295: Value Row
NSE296: Value Row | NTO296: 94 | NTQ296: Value Row
NSE297: Summation Row | NTO297: 95 | NTQ297: Summation Row
NTO298: 96
NTO299: 97
NTO300: 98
NTO301: 99
NTO302: 100
NTO303: 101
NTO304: 102

Sheet CS_Budget
A1: Income Statement
A2: Your CFO Guy
A3: Customer Support
C4: Growth | E4: 44957 | F4: =EOMONTH(E4,1) -> 44985 | G4: =EOMONTH(F4,1) -> 45016 | H4: =EOMONTH(G4,1) -> 45046 | I4: =EOMONTH(H4,1) -> 45077 | J4: =EOMONTH(I4,1) -> 45107 | K4: =EOMONTH(J4,1) -> 45138 | L4: =EOMONTH(K4,1) -> 45169 | M4: =EOMONTH(L4,1) -> 45199 | ... AN4: =EOMONTH(AM4,1) -> 46022
B5: Revenue
B6: Sales | C6: 0.1 | E6: 0 | F6: 0 | G6: 0 | H6: 0 | I6: 0 | J6: 0 | K6: 0 | L6: 0 | M6: 0 | N6: 0 | O6: 0 | P6: 0 | Q6: 0 | R6: 0 | S6: 0 | T6: 0 | U6: 0 | V6: 0 | W6: 0 | X6: 0 | Y6: 0 | Z6: 0 | AA6: 0 | AB6: 0 | AC6: 0 | AD6: 0 | AE6: 0 | AF6: 0 | AG6: 0 | AH6: 0 | AI6: 0 | AJ6: 0 | AK6: 0 | AL6: 0 | AM6: 0 | AN6: 0
B7: Total Revenue | E7: =SUM(E6 + E5) -> 0 | F7: =SUM(F6 + F5) -> 0 | G7: =SUM(G6 + G5) -> 0 | H7: =SUM(H6 + H5) -> 0 | I7: =SUM(I6 + I5) -> 0 | J7: =SUM(J6 + J5) -> 0 | K7: =SUM(K6 + K5) -> 0 | L7: =SUM(L6 + L5) -> 0 | ... AN7: =SUM(AN6 + AN5) -> 0
B8: Cost of Goods Sold
B9: Web Domain & Hosting Fees | C9: 0.04 | E9: 0 | F9: 0 | G9: 0 | H9: 0 | I9: 0 | J9: 0 | K9: 0 | L9: 0 | M9: 0 | N9: 0 | O9: 0 | P9: 0 | Q9: 0 | R9: 0 | S9: 0 | T9: 0 | U9: 0 | V9: 0 | W9: 0 | X9: 0 | Y9: 0 | Z9: 0 | AA9: 0 | AB9: 0 | AC9: 0 | AD9: 0 | AE9: 0 | AF9: 0 | AG9: 0 | AH9: 0 | AI9: 0 | AJ9: 0 | AK9: 0 | AL9: 0 | AM9: 0 | AN9: 0
B10: Merchant Account Fees | C10: 0.04 | E10: 0 | F10: 0 | G10: 0 | H10: 0 | I10: 0 | J10: 0 | K10: 0 | L10: 0 | M10: 0 | N10: 0 | O10: 0 | P10: 0 | Q10: 0 | R10: 0 | S10: 0 | T10: 0 | U10: 0 | V10: 0 | W10: 0 | X10: 0 | Y10: 0 | Z10: 0 | AA10: 0 | AB10: 0 | AC10: 0 | AD10: 0 | AE10: 0 | AF10: 0 | AG10: 0 | AH10: 0 | AI10: 0 | AJ10: 0 | AK10: 0 | AL10: 0 | AM10: 0 | AN10: 0
B11: Total Cost of Goods Sold | E11: =SUM(E10, E9 + E8) -> 0 | F11: =SUM(F10, F9 + F8) -> 0 | G11: =SUM(G10, G9 + G8) -> 0 | H11: =SUM(H10, H9 + H8) -> 0 | I11: =SUM(I10, I9 + I8) -> 0 | J11: =SUM(J10, J9 + J8) -> 0 | K11: =SUM(K10, K9 + K8) -> 0 | L11: =SUM(L10, L9 + L8) -> 0 | ... AN11: =SUM(AN10, AN9 + AN8) -> 0
B12: Gross Profit | E12: =E7-E11 -> 0 | F12: =F7-F11 -> 0 | G12: =G7-G11 -> 0 | H12: =H7-H11 -> 0 | I12: =I7-I11 -> 0 | J12: =J7-J11 -> 0 | K12: =K7-K11 -> 0 | L12: =L7-L11 -> 0 | ... AN12: =AN7-AN11 -> 0
B13: Expenses
B14: Advertising & Marketing | C14: 0.04 | E14: 0 | F14: 0 | G14: 0 | H14: 0 | I14: 0 | J14: 0 | K14: 0 | L14: 0 | M14: 0 | N14: 0 | O14: 0 | P14: 0 | Q14: 0 | R14: 0 | S14: 0 | T14: 0 | U14: 0 | V14: 0 | W14: 0 | X14: 0 | Y14: 0 | Z14: 0 | AA14: 0 | AB14: 0 | AC14: 0 | AD14: 0 | AE14: 0 | AF14: 0 | AG14: 0 | AH14: 0 | AI14: 0 | AJ14: 0 | AK14: 0 | AL14: 0 | AM14: 0 | AN14: 0
B15: Bank Charges & Fees | C15: 0.04 | E15: 0 | F15: 0 | G15: 0 | H15: 0 | I15: 0 | J15: 0 | K15: 0 | L15: 0 | M15: 0 | N15: 0 | O15: 0 | P15: 0 | Q15: 0 | R15: 0 | S15: 0 | T15: 0 | U15: 0 | V15: 0 | W15: 0 | X15: 0 | Y15: 0 | Z15: 0 | AA15: 0 | AB15: 0 | AC15: 0 | AD15: 0 | AE15: 0 | AF15: 0 | AG15: 0 | AH15: 0 | AI15: 0 | AJ15: 0 | AK15: 0 | AL15: 0 | AM15: 0 | AN15: 0
B16: Conferences & Events | C16: 0.03 | E16: 1500 | F16: =E16*(1+$C16) -> 1545 | G16: =F16*(1+$C16) -> 1591.35 | H16: =G16*(1+$C16) -> 1639.0905 | I16: =H16*(1+$C16) -> 1688.2632 | J16: =I16*(1+$C16) -> 1738.9111 | K16: =J16*(0.9) -> 1565.02 | L16: =K16*(1+$C16) -> 1611.9706 | M16: =L16*(1+$C16) -> 1660.3297 | N16: =M16*(1+$C16) -> 1710.1396 | O16: =N16*(1+$C16) -> 1761.4438 | P16: =O16*(1+$C16) -> 1814.2871 | Q16: =P16*(1+$C16) -> 1868.7157 | R16: =Q16*(1+$C16) -> 1924.7772 | S16: =R16*(1+$C16) -> 1982.5205 | ... W16: =V16*(1+$C16) -> 2231.3443 | X16: =W16*(0.9) -> 2008.2099 | Y16: =X16*(1+$C16) -> 2068.4562 | Z16: =Y16*(1+$C16) -> 2130.5099 | AA16: =Z16*(1+$C16) -> 2194.4252 | AB16: =AA16*(1+$C16) -> 2260.2579 | AC16: =AB16*(1+$C16) -> 2328.0656 | AD16: =AC16*(1+$C16) -> 2397.9076 | AE16: =AD16*(1+$C16) -> 2469.8448 | AF16: =AE16*(0.9) -> 2222.8604 | AG16: =AF16*(1+$C16) -> 2289.5462 | AH16: =AG16*(1+$C16) -> 2358.2326 | AI16: =AH16*(1+$C16) -> 2428.9795 | AJ16: =AI16*(1+$C16) -> 2501.8489 | AK16: =AJ16*(1+$C16) -> 2576.9044 | AL16: =AK16*(1+$C16) -> 2654.2115 | AM16: =AL16*(0.9) -> 2388.7904 | AN16: =AM16*(1+$C16) -> 2460.4541
B17: Software & Apps | C17: 0.02 | E17: 4500 | F17: =E17*(1+$C17) -> 4590 | G17: =F17*(1+$C17) -> 4681.8 | H17: =G17*(0.7) -> 3277.26 | I17: =H17*(1+$C17) -> 3342.8052 | J17: =I17*(1+$C17) -> 3409.6613 | K17: =J17*(1+$C17) -> 3477.8545 | L17: =K17*(1+$C17) -> 3547.4116 | M17: =L17*(1+$C17) -> 3618.3599 | N17: =M17*(1+$C17) -> 3690.7271 | O17: =N17*(1+$C17) -> 3764.5416 | P17: =O17*(1+$C17) -> 3839.8324 | ... R17: =Q17*(1+$C17) -> 3994.9617 | S17: =R17*(0.7) -> 2796.4732 | T17: =S17*(1+$C17) -> 2852.4026 | U17: =T17*(1+$C17) -> 2909.4507 | V17: =U17*(1+$C17) -> 2967.6397 | W17: =V17*(1+$C17) -> 3026.9925 | X17: =W17*(1+$C17) -> 3087.5323 | Y17: =X17*(1+$C17) -> 3149.283 | Z17: =Y17*(1+$C17) -> 3212.2686 | AA17: =Z17*(1+$C17) -> 3276.514 | AB17: =AA17*(1+$C17) -> 3342.0443 | AC17: =AB17*(0.7) -> 2339.431 | AD17: =AC17*(1+$C17) -> 2386.2196 | AE17: =AD17*(1+$C17) -> 2433.944 | AF17: =AE17*(1+$C17) -> 2482.6229 | AG17: =AF17*(1+$C17) -> 2532.2754 | AH17: =AG17*(1+$C17) -> 2582.9209 | AI17: =AH17*(1+$C17) -> 2634.5793 | AJ17: =AI17*(1+$C17) -> 2687.2709 | AK17: =AJ17*(0.7) -> 1881.0896 | AL17: =AK17*(1+$C17) -> 1918.7114 | AM17: =AL17*(1+$C17) -> 1957.0856 | AN17: =AM17*(1+$C17) -> 1996.2273
B18: Insurance | C18: 0.04 | E18: 0 | F18: 0 | G18: 0 | H18: 0 | I18: 0 | J18: 0 | K18: 0 | L18: 0 | M18: 0 | N18: 0 | O18: 0 | P18: 0 | Q18: 0 | R18: 0 | S18: 0 | T18: 0 | U18: 0 | V18: 0 | W18: 0 | X18: 0 | Y18: 0 | Z18: 0 | AA18: 0 | AB18: 0 | AC18: 0 | AD18: 0 | AE18: 0 | AF18: 0 | AG18: 0 | AH18: 0 | AI18: 0 | AJ18: 0 | AK18: 0 | AL18: 0 | AM18: 0 | AN18: 0
B19: Office Expenses | C19: 0.04 | E19: 0 | F19: =E19*(1+$C19) -> 0 | G19: =F19*(1+$C19) -> 0 | H19: =G19*(1+$C19) -> 0 | I19: =H19*(1+$C19) -> 0 | J19: =I19*(1+$C19) -> 0 | K19: =J19*(1+$C19) -> 0 | L19: =K19*(1+$C19) -> 0 | M19: =L19*(1+$C19) -> 0 | ... AN19: =AM19*(1+$C19) -> 0
B20: Office Supplies | C20: 0.05 | E20: 800 | F20: =E20*(1+$C20) -> 840 | G20: =F20*(1+$C20) -> 882 | H20: =G20*(1+$C20) -> 926.1 | I20: =H20*(1+$C20) -> 972.405 | J20: =I20*(1+$C20) -> 1021.0253 | K20: =J20*(1+$C20) -> 1072.0765 | L20: =K20*(1+$C20) -> 1125.6803 | M20: =L20*(1+$C20) -> 1181.9644 | ... AN20: =AM20*(1+$C20) -> 4412.8123
B21: Rent & Lease | C21: 0.04 | E21: 0 | F21: 0 | G21: 0 | H21: 0 | I21: 0 | J21: 0 | K21: 0 | L21: 0 | M21: 0 | N21: 0 | O21: 0 | P21: 0 | Q21: 0 | R21: 0 | S21: 0 | T21: 0 | U21: 0 | V21: 0 | W21: 0 | X21: 0 | Y21: 0 | Z21: 0 | AA21: 0 | AB21: 0 | AC21: 0 | AD21: 0 | AE21: 0 | AF21: 0 | AG21: 0 | AH21: 0 | AI21: 0 | AJ21: 0 | AK21: 0 | AL21: 0 | AM21: 0 | AN21: 0
B22: Utilities | C22: 0.04 | E22: 0 | F22: 0 | G22: 0 | H22: 0 | I22: 0 | J22: 0 | K22: 0 | L22: 0 | M22: 0 | N22: 0 | O22: 0 | P22: 0 | Q22: 0 | R22: 0 | S22: 0 | T22: 0 | U22: 0 | V22: 0 | W22: 0 | X22: 0 | Y22: 0 | Z22: 0 | AA22: 0 | AB22: 0 | AC22: 0 | AD22: 0 | AE22: 0 | AF22: 0 | AG22: 0 | AH22: 0 | AI22: 0 | AJ22: 0 | AK22: 0 | AL22: 0 | AM22: 0 | AN22: 0
B23: Total Office Expenses | E23: =SUM(E22, E21, E20 + E19) -> 800 | F23: =SUM(F22, F21, F20 + F19) -> 840 | G23: =SUM(G22, G21, G20 + G19) -> 882 | H23: =SUM(H22, H21, H20 + H19) -> 926.1 | I23: =SUM(I22, I21, I20 + I19) -> 972.405 | J23: =SUM(J22, J21, J20 + J19) -> 1021.0253 | K23: =SUM(K22, K21, K20 + K19) -> 1072.0765 | L23: =SUM(L22, L21, L20 + L19) -> 1125.6803 | ... AN23: =SUM(AN22, AN21, AN20 + AN19) -> 4412.8123
B24: Professional Services | E24: 0 | F24: =E24*(1+$C24) -> 0 | G24: =F24*(1+$C24) -> 0 | H24: =G24*(1+$C24) -> 0 | I24: =H24*(1+$C24) -> 0 | J24: =I24*(1+$C24) -> 0 | K24: =J24*(1+$C24) -> 0 | L24: =K24*(1+$C24) -> 0 | M24: =L24*(1+$C24) -> 0 | ... AN24: =AM24*(1+$C24) -> 0
B25: Accounting Fees | C25: 0.04 | E25: 0 | F25: 0 | G25: 0 | H25: 0 | I25: 0 | J25: 0 | K25: 0 | L25: 0 | M25: 0 | N25: 0 | O25: 0 | P25: 0 | Q25: 0 | R25: 0 | S25: 0 | T25: 0 | U25: 0 | V25: 0 | W25: 0 | X25: 0 | Y25: 0 | Z25: 0 | AA25: 0 | AB25: 0 | AC25: 0 | AD25: 0 | AE25: 0 | AF25: 0 | AG25: 0 | AH25: 0 | AI25: 0 | AJ25: 0 | AK25: 0 | AL25: 0 | AM25: 0 | AN25: 0
B26: Consulting Fees | C26: 0.04 | E26: 0 | F26: 0 | G26: 0 | H26: 0 | I26: 0 | J26: 0 | K26: 0 | L26: 0 | M26: 0 | N26: 0 | O26: 0 | P26: 0 | Q26: 0 | R26: 0 | S26: 0 | T26: 0 | U26: 0 | V26: 0 | W26: 0 | X26: 0 | Y26: 0 | Z26: 0 | AA26: 0 | AB26: 0 | AC26: 0 | AD26: 0 | AE26: 0 | AF26: 0 | AG26: 0 | AH26: 0 | AI26: 0 | AJ26: 0 | AK26: 0 | AL26: 0 | AM26: 0 | AN26: 0
B27: Legal Fees | C27: 0.04 | E27: 0 | F27: 0 | G27: 0 | H27: 0 | I27: 0 | J27: 0 | K27: 0 | L27: 0 | M27: 0 | N27: 0 | O27: 0 | P27: 0 | Q27: 0 | R27: 0 | S27: 0 | T27: 0 | U27: 0 | V27: 0 | W27: 0 | X27: 0 | Y27: 0 | Z27: 0 | AA27: 0 | AB27: 0 | AC27: 0 | AD27: 0 | AE27: 0 | AF27: 0 | AG27: 0 | AH27: 0 | AI27: 0 | AJ27: 0 | AK27: 0 | AL27: 0 | AM27: 0 | AN27: 0
B28: Recruiting Fees | C28: 0.08 | E28: 600 | F28: =E28*(1+$C28) -> 648 | G28: =F28*(1+$C28) -> 699.84 | H28: =G28*(1+$C28) -> 755.8272 | I28: =H28*(1+$C28) -> 816.29338 | J28: =I28*(1+$C28) -> 881.59685 | K28: =J28*(1+$C28) -> 952.12459 | L28: =K28*(1+$C28) -> 1028.2946 | M28: =L28*(1+$C28) -> 1110.5581 | ... AN28: =AM28*(1+$C28) -> 8871.2066
B29: Total Professional Services | E29: =SUM(E28, E27, E26, E25 + E24) -> 600 | F29: =SUM(F28, F27, F26, F25 + F24) -> 648 | G29: =SUM(G28, G27, G26, G25 + G24) -> 699.84 | H29: =SUM(H28, H27, H26, H25 + H24) -> 755.8272 | I29: =SUM(I28, I27, I26, I25 + I24) -> 816.29338 | J29: =SUM(J28, J27, J26, J25 + J24) -> 881.59685 | K29: =SUM(K28, K27, K26, K25 + K24) -> 952.12459 | L29: =SUM(L28, L27, L26, L25 + L24) -> 1028.2946 | ... AN29: =SUM(AN28, AN27, AN26, AN25 + AN24) -> 8871.2066
B30: Payroll Expenses | C30: 0.04 | E30: 0 | F30: =E30*(1+$C30) -> 0 | G30: =F30*(1+$C30) -> 0 | H30: =G30*(1+$C30) -> 0 | I30: =H30*(1+$C30) -> 0 | J30: =I30*(1+$C30) -> 0 | K30: =J30*(1+$C30) -> 0 | L30: =K30*(1+$C30) -> 0 | M30: =L30*(1+$C30) -> 0 | ... AN30: =AM30*(1+$C30) -> 0
B31: Salary & Wages | C31: 0.07 | E31: 6000 | F31: =E31*(1+$C31) -> 6420 | G31: =F31*(1+$C31) -> 6869.4 | H31: =G31*(1+$C31) -> 7350.258 | I31: =H31*(0.7) -> 5145.1806 | J31: =I31*(1+$C31) -> 5505.3432 | K31: =J31*(1+$C31) -> 5890.7173 | L31: =K31*(1+$C31) -> 6303.0675 | M31: =L31*(1+$C31) -> 6744.2822 | N31: =M31*(1+$C31) -> 7216.382 | O31: =N31*(1+$C31) -> 7721.5287 | P31: =O31*(1+$C31) -> 8262.0357 | Q31: =P31*(1+$C31) -> 8840.3782 | ... U31: =T31*(1+$C31) -> 11587.932 | V31: =U31*(0.7) -> 8111.5527 | W31: =V31*(1+$C31) -> 8679.3614 | X31: =W31*(1+$C31) -> 9286.9167 | Y31: =X31*(1+$C31) -> 9937.0009 | Z31: =Y31*(1+$C31) -> 10632.591 | AA31: =Z31*(1+$C31) -> 11376.872 | AB31: =AA31*(1+$C31) -> 12173.253 | AC31: =AB31*(0.7) -> 8521.2774 | AD31: =AC31*(0.7) -> 5964.8942 | AE31: =AD31*(1+$C31) -> 6382.4367 | AF31: =AE31*(1+$C31) -> 6829.2073 | AG31: =AF31*(1+$C31) -> 7307.2518 | AH31: =AG31*(1+$C31) -> 7818.7595 | AI31: =AH31*(1+$C31) -> 8366.0726 | AJ31: =AI31*(1+$C31) -> 8951.6977 | AK31: =AJ31*(1+$C31) -> 9578.3165 | AL31: =AK31*(0.7) -> 6704.8216 | AM31: =AL31*(1+$C31) -> 7174.1591 | AN31: =AM31*(1+$C31) -> 7676.3502
B32: Payroll Taxes | C32: 0.04 | E32: =E31*0.1 -> 600 | F32: =E32*(1+$C32) -> 624 | G32: =F32*(1+$C32) -> 648.96 | H32: =G32*(1+$C32) -> 674.9184 | I32: =H32*(1+$C32) -> 701.91514 | J32: =I32*(1+$C32) -> 729.99174 | K32: =J32*(1+$C32) -> 759.19141 | L32: =K32*(1+$C32) -> 789.55907 | M32: =L32*(1+$C32) -> 821.14143 | ... AN32: =AM32*(1+$C32) -> 2367.6534
B33: Health Insurance | C33: 0.04 | E33: 550 | F33: =E33*(1+$C33) -> 572 | G33: =F33*(1+$C33) -> 594.88 | H33: =G33*(1+$C33) -> 618.6752 | I33: =H33*(1+$C33) -> 643.42221 | J33: =I33*(1+$C33) -> 669.1591 | K33: =J33*(1+$C33) -> 695.92546 | L33: =K33*(1+$C33) -> 723.76248 | M33: =L33*(1+$C33) -> 752.71298 | ... AN33: =AM33*(1+$C33) -> 2170.3489
B34: Payroll Processing Fees | C34: 0.04 | E34: 57.375 | F34: =E34*(1+$C34) -> 59.67 | G34: =F34*(1+$C34) -> 62.0568 | H34: =G34*(1+$C34) -> 64.539072 | I34: =H34*(1+$C34) -> 67.120635 | J34: =I34*(1+$C34) -> 69.80546 | K34: =J34*(1+$C34) -> 72.597679 | L34: =K34*(1+$C34) -> 75.501586 | M34: =L34*(1+$C34) -> 78.521649 | ... AN34: =AM34*(1+$C34) -> 226.40686
B35: Commissions Expense | C35: 0.04 | E35: 0 | F35: =E35*(1+$C35) -> 0 | G35: =F35*(1+$C35) -> 0 | H35: =G35*(1+$C35) -> 0 | I35: =H35*(1+$C35) -> 0 | J35: =I35*(1+$C35) -> 0 | K35: =J35*(1+$C35) -> 0 | L35: =K35*(1+$C35) -> 0 | M35: =L35*(1+$C35) -> 0 | ... AN35: =AM35*(1+$C35) -> 0
